Workbook

Sheet CR Sales
A1: Brand | B1: SKU | C1: Product | D1: Quantity
A2: Grundfos | B2: 96501699-BIP66 | C2: Grundfos CR 15-3 3kW 2P Vertical multistage mounted on base with rubber mounts IP-66 Upgrade | D2: 6
A3: Grundfos | B3: 99247817-B | C3: Grundfos CRIE 15-3 3 kW IE3 IP-55 integral variable speed mounted on base with rubber mounts | D3: 6
A4: Grundfos | B4: 96500327BASE | C4: Grundfos CR 20-2 2.2kW 2P Vertical multistage mounted on base with rubber mounts | D4: 4
A5: Grundfos | B5: 96501698-BIP66 | C5: Grundfos CR 15-2 2.2kW 2P IP66 Vertical multistage mounted on base with rubber mounts | D5: 4
A6: Grundfos | B6: 99655815 | C6: CRE10-4 PV-A-A-E-HQQE 1x200-240 60 HZ | D6: 3
A7: Grundfos | B7: 92959623 | C7: Grundfos CR 10-4 1.5kW 240/1/50 Fixed speed vertical multistage pump IE3 IP-55 | D7: 2
A8: Grundfos | B8: 96516172 | C8: Grundfos CR 1-4 0.37kW 415V Vertical multistage pump | D8: 2
A9: Grundfos | B9: 96516173 | C9: Grundfos CR 1-5 0.37kW 415V Vertical multistage pump | D9: 2
A10: Grundfos | B10: 96121952-IP66 | C10: Grundfos CR 32-2-2 3kW 2P Vertical multistage pump. Motor upgraded to IP-66 for external installation. | D10: 2
A11: Grundfos | B11: 96500964DTBASE | C11: Grundfos CR 10-2 0.75kW 2P Vertical multistage mounted on base with rubber mounts and stainless steel drip tray | D11: 2
A12: Grundfos | B12: 96501697-BDT | C12: Grundfos CR 15-1 1.1kW 2P Vertical multistage mounted on base with SS drip tray & rubber mounts | D12: 2
A13: Grundfos | B13: 96501698-B | C13: Grundfos CR 15-2 2.2kW 2P Vertical multistage mounted on base with rubber mounts | D13: 2
A14: Grundfos | B14: 96501896-IP56 | C14: Grundfos CR 15-4 4kW Vertical Multistage + IP56 | D14: 2
A15: Grundfos | B15: 96516592DTBASE | C15: Grundfos CR 3-4 0.37kW 2P Vertical multistage mounted on base with rubber mounts and stainless steel drip tray | D15: 2
A16: Grundfos | B16: 96517037-B | C16: Grundfos CR 5-2 0.37kW 2P Vertical multistage mounted on base with rubber mounts | D16: 2
A17: Grundfos | B17: 96517039-B | C17: Grundfos CR 5-4 0.55kW 2P Vertical multistage mounted on base with rubber mounts | D17: 2
A18: Grundfos | B18: 96517039ISEIS-IP-56 | C18: Grundfos CR 5-4 0.55kW + IB + SEIS + IP-56 | D18: 2
A19: Grundfos | B19: 96520640DTBASE | C19: Grundfos CRN 1-4 0.37kW 415/3/50 | D19: 2
A20: Grundfos | B20: 92900972 | C20: Grundfos CR 1-7 0.37kW 240/1/50 Fixed speed vertical multistage pump IE3 IP-55 | D20: 1
A21: Grundfos | B21: 96122799 | C21: Grundfos CR 45-2 7.5kW IE3 IP-55 80mm DIN Flanged inline vertical multistage pump | D21: 1
A22: Grundfos | B22: 96511750 | C22: Grundfos CR 5-8 1.1kW 415V Vertical multistage pump | D22: 1
A23: Grundfos | B23: 96515647 | C23: Grundfos CR 1S-2 0.37kW Vertical multistage pump | D23: 1
A24: Grundfos | B24: 96515649 | C24: Grundfos CR 1S-3 0.37kW Vertical multistage pump | D24: 1
A25: Grundfos | B25: 99237436 | C25: CRE 10-3 2.2kW vertical multistage pump with integral variable speed drive | D25: 1
A26: Grundfos | B26: 99237443 | C26: CRE 15-1 1.5kW vertical multistage pump with integral variable speed drive | D26: 1
A27: Grundfos | B27: 99237456 | C27: CRE 20-2 inline vertical multistage pump with integral variable speed drive. | D27: 1
A28: Grundfos | B28: 99237528 | C28: CRE 45-2-1 11kW vertical multistage pump with integral variable speed drive | D28: 1
A29: Grundfos | B29: 96121952DTBASE | C29: Grundfos CR 32-2-2 3kW 2P Vertical multistage mounted on base with SS drip tray & rubber mounts | D29: 1
A30: Grundfos | B30: 96500966-BIP66 | C30: Grundfos CR 10-4 1.5kW 2P Vertical multistage mounted on base with rubber mounts IP-66 Upgrade | D30: 1
A31: Grundfos | B31: 96516977BASE | C31: Grundfos CR 5-4 0.55kW + BASE + RUBBER MOUNT | D31: 1

Sheet NBG BOM
A1: Item No | B1: Name | C1: kW | D1: Poles | E1: Inertia PN | F1: Inertia Size | G1: Standard Spring PN | H1: Standard Spring | I1: 50mm Static Spring PN | J1: 50mm Spring | K1: Qty Springs | L1: Pump List | M1: Pump Nett | N1: IP-56 List | O1: IP-56 Nett | P1: IP-66 List | Q1: IP-66 Nett | R1: Inertia Nett | S1: Crossbar Nett | T1: Standard Spring Nett | U1: Total Standard Spring Nett | V1: 50mm Spring Nett | W1: Total 50mm Spring | X1: 24/25 Pump List | Y1: 24/25 Pump Nett | Z1: Total Cost | AA1: Total Sell | AB1: Margin
A2: 99801136 | B2: NBG 125-100-160/167 | C2: 22 | D2: 2 | E2: 98327389 | F2: 1200 x 800 x 200 | G2: 91338018 | H2: CLM-97 | I2: 93176762 | J2: CDM-521 | K2: 4 | L2: 9151 | M2: 4575.5 | R2: 663.42 | S2: 284.76 | T2: 170.3 | U2: 681.2 | V2: 668.94 | W2: 2675.76 | X2: 9151 | Y2: 4575.5 | Z2: 5920.12 | AA2: 7264 | AB2: 0.815
A3: 99801135 | B3: NBG 125-100-160/160-154 | C3: 18.5 | D3: 2 | E3: 98327389 | F3: 1200 x 800 x 200 | G3: 91338018 | H3: CLM-97 | I3: 93176762 | J3: CDM-521 | K3: 4 | L3: 8227 | M3: 4113.5 | R3: 663.42 | S3: 284.76 | T3: 170.3 | U3: 681.2 | V3: 668.94 | W3: 2675.76 | X3: 8227 | Y3: 4113.5 | Z3: 5458.12 | AA3: 6698
A4: 99796408 | B4: NBG 50-32-160/163 | C4: 4 | D4: 2 | E4: 98336369 | F4: 800 x 630 x 125 | G4: 92932672 | H4: CSM-14 | I4: 93176749 | J4: CWDM-36 | K4: 4 | L4: 4233 | M4: 2116.5 | P4: 380 | Q4: 190 | R4: 565.52 | S4: 284.76 | T4: 59.52 | U4: 238.08 | V4: 288.58 | W4: 1154.32 | X4: 4233 | Y4: 2116.5 | Z4: 2920.1 | AA4: 3583
A5: 99801330 | B5: NBG 125-80-200/179 | C5: 3 | D5: 4 | E5: 98327382 | F5: 950 x 720 x 150 | G5: 91338157 | H5: CSM-17 | I5: 93176761 | J5: CWDM-37 | K5: 4 | L5: 5455 | M5: 2727.5 | R5: 532.03 | S5: 284.76 | T5: 59.52 | U5: 238.08 | V5: 288.59 | W5: 1154.36 | X5: 5455 | Y5: 2727.5 | Z5: 3497.61 | AA5: 4292
A6: 99801137 | B6: NBG 125-100-160/176 | C6: 30 | D6: 4 | E6: 99051550 | F6: 1500 x 800 x 225 | G6: 91338019 | H6: CLM-98 | J6: CDM-53 | K6: 4 | L6: 11109 | M6: 5554.5 | R6: 741.99 | S6: 284.76 | T6: 170.3 | U6: 681.2 | V6: 668.94 | W6: 2675.76 | X6: 11109 | Y6: 5554.5 | Z6: 6977.69 | AA6: 8562
A7: 99801329 | B7: NBG 125-80-200/164 | C7: 2.2 | D7: 4 | E7: 98327382 | F7: 950 x 720 x 150 | G7: 92932673 | H7: CSM-16 | I7: 93176761 | J7: CWDM-37 | K7: 4 | L7: 5346 | M7: 2673 | R7: 532.03 | S7: 284.76 | T7: 59.52 | U7: 238.08 | V7: 288.59 | W7: 1154.36 | X7: 5346 | Y7: 2673 | Z7: 3443.11 | AA7: 4225
A8: 99801142 | B8: NBG 125-100-250/205 | C8: 55 | D8: 2 | F8: #N/A | G8: #N/A | H8: #N/A | I8: #N/A | J8: #N/A | L8: 17256 | M8: 8628 | R8: #REF! | S8: $ - | T8: #N/A | U8: #N/A | V8: #N/A | W8: #N/A | X8: 17256 | Y8: 8628 | Z8: 1 | AA8: 2
A9: 99801331 | B9: NBG 125-80-200/196 | C9: 4 | D9: 4 | E9: 98327382 | F9: 950 x 720 x 150 | G9: 91338157 | H9: CSM-17 | I9: 93176761 | J9: CWDM-37 | K9: 4 | L9: 5748 | M9: 2874 | R9: 532.03 | S9: 284.76 | T9: 59.52 | U9: 238.08 | V9: 288.59 | W9: 1154.36 | X9: 5748 | Y9: 2874 | Z9: 3644.11 | AA9: 4472
A10: 99801348 | B10: NBG 125-100-160/169 | C10: 3 | D10: 4 | E10: 98327389 | F10: 1200 x 800 x 200 | G10: 91338016 | H10: CLM-96 | I10: 93176760 | J10: CWDM-38 | K10: 4 | L10: 5144 | M10: 2572 | R10: 663.42 | S10: 284.76 | T10: 135.26 | U10: 541.04 | V10: 288.61 | W10: 1154.44 | X10: 5144 | Y10: 2572 | Z10: 3776.46 | AA10: 4634
A11: 99801347 | B11: NBG 125-100-160/160-140 | C11: 2.2 | D11: 4 | E11: 98327382 | F11: 950 x 720 x 150 | G11: 92932673 | H11: CSM-16 | I11: 93176761 | J11: CWDM-37 | K11: 4 | L11: 5035 | M11: 2517.5 | R11: 532.03 | S11: 284.76 | T11: 59.52 | U11: 238.08 | V11: 288.59 | W11: 1154.36 | X11: 5035 | Y11: 2517.5 | Z11: 3287.61 | AA11: 4034
A12: 99801144 | B12: NBG 125-100-250/242 | C12: 90 | D12: 2 | E12: TBA | F12: 2100 x 1000 x 300 | G12: 91338021 | H12: CLM-100 | J12: CDM-55 | K12: 6 | L12: 22297 | M12: 11148.5 | R12: 1100 | S12: 427.14 | T12: 170.3 | U12: 1021.8 | V12: 717.41 | W12: 4304.46 | X12: 22297 | Y12: 11148.5 | Z12: 13270.3 | AA12: 16283
A13: 99801349 | B13: NBG 125-100-160/176 | C13: 4 | D13: 4 | E13: 98327389 | F13: 1200 x 800 x 200 | G13: 91338016 | H13: CLM-96 | I13: 93176760 | J13: CWDM-38 | K13: 4 | L13: 5437 | M13: 2718.5 | R13: 663.42 | S13: 284.76 | T13: 135.26 | U13: 541.04 | V13: 288.61 | W13: 1154.44 | X13: 5437 | Y13: 2718.5 | Z13: 3922.96 | AA13: 4814
A14: 99801122 | B14: NBG 125-80-160/167 | C14: 22 | D14: 2 | E14: 98327389 | F14: 1200 x 800 x 200 | G14: 91338018 | H14: CLM-97 | I14: 93176762 | J14: CDM-521 | K14: 4 | L14: 8955 | M14: 4477.5 | N14: 866 | O14: 433 | R14: 663.42 | S14: 284.76 | T14: 170.3 | U14: 681.2 | V14: 668.94 | W14: 2675.76 | X14: 8955 | Y14: 4477.5 | Z14: 5822.12 | AA14: 7144
A15: 99801143 | B15: NBG 125-100-250/229 | C15: 75 | D15: 2 | E15: TBA | F15: 2100 x 1000 x 300 | G15: 91338020 | H15: CLM-99 | J15: CDM-531 | K15: 6 | L15: 20550 | M15: 10275 | R15: 1100 | S15: 427.14 | T15: 170.3 | U15: 1021.8 | V15: 717.41 | W15: 4304.46 | X15: 20550 | Y15: 10275 | Z15: 12396.8 | AA15: 15211
A16: 99801116 | B16: NBG 100-80-160/143 | C16: 7.5 | D16: 2 | E16: 98327382 | F16: 950 x 720 x 150 | G16: 91338157 | H16: CSM-17 | I16: 93176761 | J16: CWDM-37 | K16: 4 | L16: 5687 | M16: 2843.5 | N16: 1209.33 | O16: 604.67 | P16: 2102.22 | Q16: 1051.11 | R16: 532.03 | S16: 284.76 | T16: 59.52 | U16: 238.08 | V16: 288.59 | W16: 1154.36 | X16: 5687 | Y16: 2843.5 | Z16: 3613.61 | AA16: 4434
A17: 99801332 | B17: NBG 125-80-200/214 | C17: 5.5 | D17: 4 | E17: 92513065 | F17: 1100 x 800 x 150 | G17: 91338157 | H17: CSM-17 | I17: 93176761 | J17: CWDM-37 | K17: 4 | L17: 6465 | M17: 3232.5 | R17: 610.6 | S17: 284.76 | T17: 59.52 | U17: 238.08 | V17: 288.59 | W17: 1154.36 | X17: 6465 | Y17: 3232.5 | Z17: 4081.18 | AA17: 5008
A18: 99801334 | B18: NBG 125-80-200/222 | C18: 7.5 | D18: 4 | E18: 98327389 | F18: 1200 x 800 x 200 | G18: 91338018 | H18: CLM-97 | I18: 93176762 | J18: CDM-521 | K18: 4 | L18: 7040 | M18: 3520 | R18: 663.42 | S18: 284.76 | T18: 170.3 | U18: 681.2 | V18: 668.94 | W18: 2675.76 | X18: 7040 | Y18: 3520 | Z18: 4864.62 | AA18: 5969
A19: 99801395 | B19: NBG 200-150-400/343 | C19: 55 | D19: 4 | E19: TBA | F19: 2100 x 1000 x 300 | G19: 91338020 | H19: CLM-99 | J19: CDM-531 | K19: 6 | L19: 27708 | M19: 13854 | R19: 1100 | S19: 427.14 | T19: 170.3 | U19: 1021.8 | V19: 717.41 | W19: 4304.46 | X19: 27708 | Y19: 13854 | Z19: 15975.8 | AA19: 19603
A20: 99801320 | B20: NBG 100-80-160/149 | C20: 1.1 | D20: 4 | E20: 98336369 | F20: 800 x 630 x 125 | G20: 92932672 | H20: CSM-14 | I20: 93176749 | J20: CWDM-36 | K20: 4 | L20: 3821 | M20: 1910.5 | R20: 565.52 | S20: 284.76 | T20: 59.52 | U20: 238.08 | V20: 288.58 | W20: 1154.32 | X20: 3821 | Y20: 1910.5 | Z20: 2714.1 | AA20: 3331
A21: 99801123 | B21: NBG 125-80-160/177 | C21: 30 | D21: 2 | E21: 99051550 | F21: 1500 x 800 x 225 | G21: 91338019 | H21: CLM-98 | J21: CDM-53 | K21: 4 | L21: 11151 | M21: 5575.5 | R21: 741.99 | S21: 284.76 | T21: 170.3 | U21: 681.2 | V21: 668.94 | W21: 2675.76 | X21: 11151 | Y21: 5575.5 | Z21: 6998.69 | AA21: 8588
A22: 99801321 | B22: NBG 100-80-160/165 | C22: 1.5 | D22: 4 | E22: 98336369 | F22: 800 x 630 x 125 | G22: 92932672 | H22: CSM-14 | I22: 93176749 | J22: CWDM-36 | K22: 4 | L22: 3862 | M22: 1931 | R22: 565.52 | S22: 284.76 | T22: 59.52 | U22: 238.08 | V22: 288.58 | W22: 1154.32 | X22: 3862 | Y22: 1931 | Z22: 2734.6 | AA22: 3356
A23: 99801276 | B23: NBG 50-32-200/216 | C23: 1.1 | D23: 4 | E23: 98336369 | F23: 800 x 630 x 125 | G23: 92932672 | H23: CSM-14 | I23: 93176749 | J23: CWDM-36 | K23: 4 | L23: 3589 | M23: 1794.5 | R23: 565.52 | S23: 284.76 | T23: 59.52 | U23: 238.08 | V23: 288.58 | W23: 1154.32 | X23: 3589 | Y23: 1794.5 | Z23: 2598.1 | AA23: 3188
A24: 99801328 | B24: NBG 125-80-160/177 | C24: 4 | D24: 4 | E24: 98327389 | F24: 1200 x 800 x 200 | G24: 91338016 | H24: CLM-96 | I24: 93176760 | J24: CWDM-38 | K24: 4 | L24: 4822 | M24: 2411 | R24: 663.42 | S24: 284.76 | T24: 135.26 | U24: 541.04 | V24: 288.61 | W24: 1154.44 | X24: 4822 | Y24: 2411 | Z24: 3615.46 | AA24: 4437
A25: 99801327 | B25: NBG 125-80-160/175 | C25: 3 | D25: 4 | E25: 98327382 | F25: 950 x 720 x 150 | G25: 92932673 | H25: CSM-16 | I25: 93176761 | J25: CWDM-37 | K25: 4 | L25: 4542 | M25: 2271 | R25: 532.03 | S25: 284.76 | T25: 59.52 | U25: 238.08 | V25: 288.59 | W25: 1154.36 | X25: 4542 | Y25: 2271 | Z25: 3041.11 | AA25: 3732
A26: 99801128 | B26: NBG 125-80-200/222 | C26: 55 | D26: 4 | E26: 98299752 | F26: 1500 x 900 x 300 | G26: 91338021 | H26: CLM-100 | J26: CDM-55 | K26: 4 | L26: 17320 | M26: 8660 | R26: 824.44 | S26: 284.76 | T26: 170.3 | U26: 681.2 | V26: 717.41 | W26: 2869.64 | X26: 17320 | Y26: 8660 | Z26: 10165.64 | AA26: 12474
A27: 99801325 | B27: NBG 125-80-160/146 | C27: 1.5 | D27: 4 | E27: 98336369 | F27: 800 x 630 x 125 | G27: 92932672 | H27: CSM-14 | I27: 93176749 | J27: CWDM-36 | K27: 4 | L27: 4250 | M27: 2125 | R27: 565.52 | S27: 284.76 | T27: 59.52 | U27: 238.08 | V27: 288.58 | W27: 1154.32 | X27: 4250 | Y27: 2125 | Z27: 2928.6 | AA27: 3594
A28: 99801272 | B28: NBG 50-32-160/172 | C28: 0.55 | D28: 4 | E28: 98336369 | F28: 800 x 630 x 125 | G28: 92932672 | H28: CSM-14 | I28: 93176749 | J28: CWDM-36 | K28: 4 | L28: 3189 | M28: 1594.5 | R28: 565.52 | S28: 284.76 | T28: 59.52 | U28: 238.08 | V28: 288.58 | W28: 1154.32 | X28: 3189 | Y28: 1594.5 | Z28: 2398.1 | AA28: 2943
A29: 99801326 | B29: NBG 125-80-160/161 | C29: 2.2 | D29: 4 | E29: 92513065 | F29: 1100 x 800 x 150 | G29: 92932673 | H29: CSM-16 | I29: 93176761 | J29: CWDM-37 | K29: 4 | L29: 4445 | M29: 2222.5 | R29: 610.6 | S29: 284.76 | T29: 59.52 | U29: 238.08 | V29: 288.59 | W29: 1154.36 | X29: 4445 | Y29: 2222.5 | Z29: 3071.18 | AA29: 3769
A30: 99801275 | B30: NBG 50-32-200/197 | C30: 0.75 | D30: 4 | E30: 98336369 | F30: 800 x 630 x 125 | G30: 92932672 | H30: CSM-14 | I30: 93176749 | J30: CWDM-36 | K30: 4 | L30: 3520 | M30: 1760 | R30: 565.52 | S30: 284.76 | T30: 59.52 | U30: 238.08 | V30: 288.58 | W30: 1154.32 | X30: 3520 | Y30: 1760 | Z30: 2563.6 | AA30: 3146
A31: 99801289 | B31: NBG 65-50-160/162 | C31: 0.75 | D31: 4 | E31: 98336369 | F31: 800 x 630 x 125 | G31: 92932672 | H31: CSM-14 | I31: 93176749 | J31: CWDM-36 | K31: 4 | L31: 3542 | M31: 1771 | R31: 565.52 | S31: 284.76 | T31: 59.52 | U31: 238.08 | V31: 288.58 | W31: 1154.32 | X31: 3542 | Y31: 1771 | Z31: 2574.6 | AA31: 3160
A32: 99801345 | B32: NBG 125-80-400/419 | C32: 37 | D32: 4 | E32: 98299752 | F32: 1500 x 900 x 300 | G32: 91338021 | H32: CLM-100 | J32: CDM-55 | K32: 4 | L32: 19642 | M32: 9821 | N32: 2065.75 | O32: 1032.88 | P32: 4916.58 | Q32: 2458.29 | R32: 824.44 | S32: 284.76 | T32: 170.3 | U32: 681.2 | V32: 717.41 | W32: 2869.64 | X32: 19642 | Y32: 9821 | Z32: 11326.64 | AA32: 13898
A33: 99801323 | B33: NBG 100-80-160/177 | C33: 2.2 | D33: 4 | E33: 92513065 | F33: 1100 x 800 x 150 | G33: 92932673 | H33: CSM-16 | I33: 93176761 | J33: CWDM-37 | K33: 4 | L33: 4057 | M33: 2028.5 | R33: 610.6 | S33: 284.76 | T33: 59.52 | U33: 238.08 | V33: 288.59 | W33: 1154.36 | X33: 4057 | Y33: 2028.5 | Z33: 2877.18 | AA33: 3531
A34: 99796406 | B34: NBG 50-32-160/139 | C34: 2.2 | D34: 2 | E34: 98336369 | F34: 800 x 630 x 125 | G34: 92932672 | H34: CSM-14 | I34: 93176749 | J34: CWDM-36 | K34: 4 | L34: 3552 | M34: 1776 | R34: 565.52 | S34: 284.76 | T34: 59.52 | U34: 238.08 | V34: 288.58 | W34: 1154.32 | X34: 3552 | Y34: 1776 | Z34: 2579.6 | AA34: 3166
A35: 99801311 | B35: NBG 100-65-250/215 | C35: 3 | D35: 4 | E35: 98327382 | F35: 950 x 720 x 150 | G35: 91338157 | H35: CSM-17 | I35: 93176761 | J35: CWDM-37 | K35: 4 | L35: 5543 | M35: 2771.5 | R35: 532.03 | S35: 284.76 | T35: 59.52 | U35: 238.08 | V35: 288.59 | W35: 1154.36 | X35: 5543 | Y35: 2771.5 | Z35: 3541.61 | AA35: 4346
A36: 99801146 | B36: NBG 150-125-200/196-166 | C36: 55 | D36: 2 | E36: TBA | F36: 2100 x 1000 x 300 | G36: 91338020 | H36: CLM-99 | J36: CDM-531 | K36: 6 | L36: 16250 | M36: 8125 | R36: 1100 | S36: 427.14 | T36: 170.3 | U36: 1021.8 | V36: 717.41 | W36: 4304.46 | X36: 16250 | Y36: 8125 | Z36: 10246.8 | AA36: 12573
A37: 99801290 | B37: NBG 65-50-160/177 | C37: 1.1 | D37: 2 | E37: 98336369 | F37: 800 x 630 x 125 | G37: 92932672 | H37: CSM-14 | I37: 93176749 | J37: CWDM-36 | K37: 4 | L37: 3669 | M37: 1834.5 | R37: 565.52 | S37: 284.76 | T37: 59.52 | U37: 238.08 | V37: 288.58 | W37: 1154.32 | X37: 3669 | Y37: 1834.5 | Z37: 2638.1 | AA37: 3237
A38: 99801365 | B38: NBG 150-125-200/196-180 | C38: 7.5 | D38: 4 | E38: 98327389 | F38: 1200 x 800 x 200 | G38: 91338018 | H38: CLM-97 | I38: 93176762 | J38: CDM-521 | K38: 4 | L38: 7763 | M38: 3881.5 | R38: 663.42 | S38: 284.76 | T38: 170.3 | U38: 681.2 | V38: 668.94 | W38: 2675.76 | X38: 7763 | Y38: 3881.5 | Z38: 5226.12 | AA38: 6413
A39: 99801273 | B39: NBG 50-32-160/173 | C39: 0.75 | D39: 4 | E39: 98336369 | F39: 800 x 630 x 125 | G39: 92932672 | H39: CSM-14 | I39: 93176749 | J39: CWDM-36 | K39: 4 | L39: 3326 | M39: 1663 | R39: 565.52 | S39: 284.76 | T39: 59.52 | U39: 238.08 | V39: 288.58 | W39: 1154.32 | X39: 3326 | Y39: 1663 | Z39: 2466.6 | AA39: 3027
A40: 99801364 | B40: NBG 150-125-200/176-154 | C40: 5.5 | D40: 4 | E40: 92513065 | F40: 1100 x 800 x 150 | G40: 91338016 | H40: CLM-96 | I40: 93176760 | J40: CWDM-38 | K40: 4 | L40: 7308 | M40: 3654 | R40: 610.6 | S40: 284.76 | T40: 135.26 | U40: 541.04 | V40: 288.61 | W40: 1154.44 | X40: 7308 | Y40: 3654 | Z40: 4805.64 | AA40: 5897
A41: 99801274 | B41: NBG 50-32-200/184 | C41: 0.55 | D41: 4 | E41: 98336369 | F41: 800 x 630 x 125 | G41: 92932672 | H41: CSM-14 | I41: 93176749 | J41: CWDM-36 | K41: 4 | L41: 3379 | M41: 1689.5 | R41: 565.52 | S41: 284.76 | T41: 59.52 | U41: 238.08 | V41: 288.58 | W41: 1154.32 | X41: 3379 | Y41: 1689.5 | Z41: 2493.1 | AA41: 3060
A42: 99801291 | B42: NBG 80-50-200/171 | C42: 1.1 | D42: 4 | E42: 98336369 | F42: 800 x 630 x 125 | G42: 92932672 | H42: CSM-14 | I42: 93176749 | J42: CWDM-36 | K42: 4 | L42: 4053 | M42: 2026.5 | R42: 565.52 | S42: 284.76 | T42: 59.52 | U42: 238.08 | V42: 288.58 | W42: 1154.32 | X42: 4053 | Y42: 2026.5 | Z42: 2830.1 | AA42: 3473
A43: 99801288 | B43: NBG 65-50-160/151 | C43: 0.55 | D43: 4 | E43: 98336369 | F43: 800 x 630 x 125 | G43: 92932672 | H43: CSM-14 | I43: 93176749 | J43: CWDM-36 | K43: 4 | L43: 3428 | M43: 1714 | R43: 565.52 | S43: 284.76 | T43: 59.52 | U43: 238.08 | V43: 288.58 | W43: 1154.32 | X43: 3428 | Y43: 1714 | Z43: 2517.6 | AA43: 3090
A44: 99801148 | B44: NBG 150-125-200/219 | C44: 90 | D44: 4 | E44: TBA | F44: 2100 x 1000 x 300 | G44: 91338021 | H44: CLM-100 | J44: CDM-55 | K44: 6 | L44: 20759 | M44: 10379.5 | R44: 1100 | S44: 427.14 | T44: 170.3 | U44: 1021.8 | V44: 717.41 | W44: 4304.46 | X44: 20759 | Y44: 10379.5 | Z44: 12501.3 | AA44: 15340
A45: 99801277 | B45: NBG 50-32-200/219 | C45: 1.5 | D45: 4 | E45: 98336369 | F45: 800 x 630 x 125 | G45: 92932672 | H45: CSM-14 | I45: 93176749 | J45: CWDM-36 | K45: 4 | L45: 3787 | M45: 1893.5 | R45: 565.52 | S45: 284.76 | T45: 59.52 | U45: 238.08 | V45: 288.58 | W45: 1154.32 | X45: 3787 | Y45: 1893.5 | Z45: 2697.1 | AA45: 3310
A46: 99801306 | B46: NBG 80-65-160/177 | C46: 2.2 | D46: 2 | E46: 98336369 | F46: 800 x 630 x 125 | G46: 92932672 | H46: CSM-14 | I46: 93176749 | J46: CWDM-36 | K46: 4 | L46: 4004 | M46: 2002 | R46: 565.52 | S46: 284.76 | T46: 59.52 | U46: 238.08 | V46: 288.58 | W46: 1154.32 | X46: 4004 | Y46: 2002 | Z46: 2805.6 | AA46: 3443
A47: 99801382 | B47: NBG 150-125-400/438 | C47: 90 | D47: 4 | F47: #N/A | G47: 91338019 | H47: CLM-98 | J47: CDM-53 | K47: 4 | L47: 26530 | M47: 13265 | R47: #N/A | S47: 284.76 | T47: 170.3 | U47: 681.2 | V47: 668.94 | W47: 2675.76 | X47: 26530 | Y47: 13265 | Z47: 1 | AA47: 2
A48: 99801381 | B48: NBG 150-125-400/433 | C48: 75 | D48: 4 | E48: TBA-8 | F48: 1500 x 100 x 300 | G48: 91338021 | H48: CLM-100 | J48: CDM-55 | K48: 4 | L48: 25130 | M48: 12565 | R48: 1550 | S48: 284.76 | T48: 170.3 | U48: 681.2 | V48: 717.41 | W48: 2869.64 | X48: 25130 | Y48: 12565 | Z48: 14796.2 | AA48: 18155
A49: 99801121 | B49: NBG 125-80-160/161 | C49: 18.5 | D49: 4 | E49: 98327389 | F49: 1200 x 800 x 200 | G49: 91338018 | H49: CLM-97 | I49: 93176762 | J49: CDM-521 | K49: 4 | L49: 8399 | M49: 4199.5 | R49: 663.42 | S49: 284.76 | T49: 170.3 | U49: 681.2 | V49: 668.94 | W49: 2675.76 | X49: 8399 | Y49: 4199.5 | Z49: 5544.12 | AA49: 6803
A50: 99801342 | B50: NBG 125-80-400/347 | C50: 18.5 | D50: 4 | E50: 99051550 | F50: 1500 x 800 x 225 | G50: 91338019 | H50: CLM-98 | J50: CDM-53 | K50: 4 | L50: 14794 | M50: 7397 | R50: 741.99 | S50: 284.76 | T50: 170.3 | U50: 681.2 | V50: 668.94 | W50: 2675.76 | X50: 14794 | Y50: 7397 | Z50: 8820.19 | AA50: 10823
A51: 99801120 | B51: NBG 125-80-160/151 | C51: 15 | D51: 2 | E51: 92513065 | F51: 1100 x 800 x 150 | G51: 91338016 | H51: CLM-96 | I51: 93176760 | J51: CWDM-38 | K51: 4 | L51: 7990 | M51: 3995 | N51: 888.24 | O51: 444.12 | P51: 1041.4 | Q51: 520.7 | R51: 610.6 | S51: 284.76 | T51: 135.26 | U51: 541.04 | V51: 288.61 | W51: 1154.44 | X51: 7990 | Y51: 3995 | Z51: 5146.64 | AA51: 6315
A52: 99801343 | B52: NBG 125-80-400/365 | C52: 22 | D52: 4 | E52: 99051550 | F52: 1500 x 800 x 225 | G52: 91338019 | H52: CLM-98 | J52: CDM-53 | K52: 4 | L52: 15298 | M52: 7649 | R52: 741.99 | S52: 284.76 | T52: 170.3 | U52: 681.2 | V52: 668.94 | W52: 2675.76 | X52: 15298 | Y52: 7649 | Z52: 9072.19 | AA52: 11132
A53: 99801319 | B53: NBG 100-80-160/135 | C53: 0.75 | D53: 4 | E53: 98336369 | F53: 800 x 630 x 125 | G53: 92932672 | H53: CSM-14 | I53: 93176749 | J53: CWDM-36 | K53: 4 | L53: 3740 | M53: 1870 | R53: 565.52 | S53: 284.76 | T53: 59.52 | U53: 238.08 | V53: 288.58 | W53: 1154.32 | X53: 3740 | Y53: 1870 | Z53: 2673.6 | AA53: 3281
A54: 99801140 | B54: NBG 125-100-200/192 | C54: 45 | D54: 2 | E54: 98299752 | F54: 1500 x 900 x 300 | G54: 91338020 | H54: CLM-99 | J54: CDM-531 | K54: 4 | L54: 14793 | M54: 7396.5 | R54: 824.44 | S54: 284.76 | T54: 170.3 | U54: 681.2 | V54: 717.41 | W54: 2869.64 | X54: 14793 | Y54: 7396.5 | Z54: 8902.14 | AA54: 10923
A55: 99801134 | B55: NBG 125-80-315/278 | C55: 90 | D55: 2 | E55: TBA | F55: 2100 x 1000 x 300 | G55: 91338021 | H55: CLM-100 | J55: CDM-55 | K55: 6 | L55: 23919 | M55: 11959.5 | R55: 1100 | S55: 427.14 | T55: 170.3 | U55: 1021.8 | V55: 717.41 | W55: 4304.46 | X55: 23919 | Y55: 11959.5 | Z55: 14081.3 | AA55: 17278
A56: 99801119 | B56: NBG 125-80-160/147-127 | C56: 11 | D56: 2 | E56: 92513065 | F56: 1100 x 800 x 150 | G56: 91338016 | H56: CLM-96 | I56: 93176760 | J56: CWDM-38 | K56: 4 | L56: 7653 | M56: 3826.5 | R56: 610.6 | S56: 284.76 | T56: 135.26 | U56: 541.04 | V56: 288.61 | W56: 1154.44 | X56: 7653 | Y56: 3826.5 | Z56: 4978.14 | AA56: 6109
A57: 99801279 | B57: NBG 65-40-200/198 | C57: 1.1 | D57: 4 | E57: 98336369 | F57: 800 x 630 x 125 | G57: 92932672 | H57: CSM-14 | I57: 93176749 | J57: CWDM-36 | K57: 4 | L57: 3854 | M57: 1927 | R57: 565.52 | S57: 284.76 | T57: 59.52 | U57: 238.08 | V57: 288.58 | W57: 1154.32 | X57: 3854 | Y57: 1927 | Z57: 2730.6 | AA57: 3351
A58: 99801149 | B58: NBG 150-125-250/221 | C58: 90 | D58: 2 | E58: TBA | F58: 2100 x 1000 x 300 | G58: 91338021 | H58: CLM-100 | J58: CDM-55 | K58: 6 | L58: 21947 | M58: 10973.5 | R58: 1100 | S58: 427.14 | T58: 170.3 | U58: 1021.8 | V58: 717.41 | W58: 4304.46 | X58: 21947 | Y58: 10973.5 | Z58: 13095.3 | AA58: 16068
A59: 99801346 | B59: NBG 125-80-400/438 | C59: 45 | D59: 4 | E59: 98299752 | F59: 1500 x 900 x 300 | G59: 91338021 | H59: CLM-100 | J59: CDM-55 | K59: 4 | L59: 20412 | M59: 10206 | R59: 824.44 | S59: 284.76 | T59: 170.3 | U59: 681.2 | V59: 717.41 | W59: 2869.64 | X59: 20412 | Y59: 10206 | Z59: 11711.64 | AA59: 14371
A60: 99801280 | B60: NBG 65-40-200/217 | C60: 1.5 | D60: 4 | E60: 98336369 | F60: 800 x 630 x 125 | G60: 92932672 | H60: CSM-14 | I60: 93176749 | J60: CWDM-36 | K60: 4 | L60: 3905 | M60: 1952.5 | R60: 565.52 | S60: 284.76 | T60: 59.52 | U60: 238.08 | V60: 288.58 | W60: 1154.32 | X60: 3905 | Y60: 1952.5 | Z60: 2756.1 | AA60: 3382
A61: 99801355 | B61: NBG 125-100-250/274 | C61: 15 | D61: 4 | E61: 98327389 | F61: 1200 x 800 x 200 | G61: 91338018 | H61: CLM-97 | I61: 93176762 | J61: CDM-521 | K61: 4 | L61: 10262 | M61: 5131 | N61: 1318 | O61: 659 | R61: 663.42 | S61: 284.76 | T61: 170.3 | U61: 681.2 | V61: 668.94 | W61: 2675.76 | X61: 10262 | Y61: 5131 | Z61: 6475.62 | AA61: 7946
A62: 99801350 | B62: NBG 125-100-200/178 | C62: 4 | D62: 4 | E62: 98327382 | F62: 950 x 720 x 150 | G62: 91338157 | H62: CSM-17 | I62: 93176761 | J62: CWDM-37 | K62: 4 | L62: 6183 | M62: 3091.5 | R62: 532.03 | S62: 284.76 | T62: 59.52 | U62: 238.08 | V62: 288.59 | W62: 1154.36 | X62: 6183 | Y62: 3091.5 | Z62: 3861.61 | AA62: 4739
A63: 99801145 | B63: NBG 150-125-200/176-154 | C63: 45 | D63: 4 | E63: 98299752 | F63: 1500 x 900 x 300 | G63: 91338021 | H63: CLM-100 | J63: CDM-55 | K63: 4 | L63: 14286 | M63: 7143 | R63: 824.44 | S63: 284.76 | T63: 170.3 | U63: 681.2 | V63: 717.41 | W63: 2869.64 | X63: 14286 | Y63: 7143 | Z63: 8648.64 | AA63: 10612
A64: 99801305 | B64: NBG 80-65-160/175 | C64: 1.5 | D64: 4 | E64: 98336369 | F64: 800 x 630 x 125 | G64: 92932672 | H64: CSM-14 | I64: 93176749 | J64: CWDM-36 | K64: 4 | L64: 3837 | M64: 1918.5 | R64: 565.52 | S64: 284.76 | T64: 59.52 | U64: 238.08 | V64: 288.58 | W64: 1154.32 | X64: 3837 | Y64: 1918.5 | Z64: 2722.1 | AA64: 3340
A65: 99801392 | B65: NBG 200-150-315/291 | C65: 45 | D65: 4 | E65: 98299752 | F65: 1500 x 900 x 300 | G65: 91338020 | H65: CLM-99 | J65: CDM-531 | K65: 4 | L65: 23642 | M65: 11821 | R65: 824.44 | S65: 284.76 | T65: 170.3 | U65: 681.2 | V65: 717.41 | W65: 2869.64 | X65: 23642 | Y65: 11821 | Z65: 13326.64 | AA65: 16352
A66: 99801302 | B66: NBG 80-65-160/131 | C66: 0.55 | D66: 4 | E66: 98336369 | F66: 800 x 630 x 125 | G66: 92932672 | H66: CSM-14 | I66: 93176749 | J66: CWDM-36 | K66: 4 | L66: 3612 | M66: 1806 | R66: 565.52 | S66: 284.76 | T66: 59.52 | U66: 238.08 | V66: 288.58 | W66: 1154.32 | X66: 3612 | Y66: 1806 | Z66: 2609.6 | AA66: 3202
A67: 99801105 | B67: NBG 100-65-200/198 | C67: 22 | D67: 2 | E67: 98327389 | F67: 1200 x 800 x 200 | G67: 91338018 | H67: CLM-97 | I67: 93176762 | J67: CDM-521 | K67: 4 | L67: 8858 | M67: 4429 | R67: 663.42 | S67: 284.76 | T67: 170.3 | U67: 681.2 | V67: 668.94 | W67: 2675.76 | X67: 8858 | Y67: 4429 | Z67: 5773.62 | AA67: 7085
A68: 99801354 | B68: NBG 125-100-250/245 | C68: 11 | D68: 4 | E68: 98327389 | F68: 1200 x 800 x 200 | G68: 91338018 | H68: CLM-97 | I68: 93176762 | J68: CDM-521 | K68: 4 | L68: 9730 | M68: 4865 | R68: 663.42 | S68: 284.76 | T68: 170.3 | U68: 681.2 | V68: 668.94 | W68: 2675.76 | X68: 9730 | Y68: 4865 | Z68: 6209.62 | AA68: 7620
A69: 99801391 | B69: NBG 200-150-315/275 | C69: 37 | D69: 4 | E69: TBA | F69: 2100 x 1000 x 300 | G69: 91338020 | H69: CLM-99 | J69: CDM-531 | K69: 6 | L69: 22370 | M69: 11185 | R69: 1100 | S69: 427.14 | T69: 170.3 | U69: 1021.8 | V69: 717.41 | W69: 4304.46 | X69: 22370 | Y69: 11185 | Z69: 13306.8 | AA69: 16328
A70: 99801309 | B70: NBG 100-65-200/205 | C70: 3 | D70: 4 | E70: 98327382 | F70: 950 x 720 x 150 | G70: 92932673 | H70: CSM-16 | I70: 93176761 | J70: CWDM-37 | K70: 4 | L70: 4676 | M70: 2338 | R70: 532.03 | S70: 284.76 | T70: 59.52 | U70: 238.08 | V70: 288.59 | W70: 1154.36 | X70: 4676 | Y70: 2338 | Z70: 3108.11 | AA70: 3814
A71: 99796407 | B71: NBG 50-32-160/151 | C71: 3 | D71: 2 | E71: 98336369 | F71: 800 x 630 x 125 | G71: 92932672 | H71: CSM-14 | I71: 93176749 | J71: CWDM-36 | K71: 4 | L71: 3898 | M71: 1949 | R71: 565.52 | S71: 284.76 | T71: 59.52 | U71: 238.08 | V71: 288.58 | W71: 1154.32 | X71: 3898 | Y71: 1949 | Z71: 2752.6 | AA71: 3378
A72: 99801304 | B72: NBG 80-65-160/158 | C72: 1.1 | D72: 4 | E72: 98336369 | F72: 800 x 630 x 125 | G72: 92932672 | H72: CSM-14 | I72: 93176749 | J72: CWDM-36 | K72: 4 | L72: 3786 | M72: 1893 | R72: 565.52 | S72: 284.76 | T72: 59.52 | U72: 238.08 | V72: 288.58 | W72: 1154.32 | X72: 3786 | Y72: 1893 | Z72: 2696.6 | AA72: 3309
A73: 99801372 | B73: NBG 150-125-250/269 | C73: 30 | D73: 4 | E73: 99051550 | F73: 1500 x 800 x 225 | G73: 91338019 | H73: CLM-98 | J73: CDM-53 | K73: 4 | L73: 13675 | M73: 6837.5 | R73: 741.99 | S73: 284.76 | T73: 170.3 | U73: 681.2 | V73: 668.94 | W73: 2675.76 | X73: 13675 | Y73: 6837.5 | Z73: 8260.69 | AA73: 10136
A74: 99801303 | B74: NBG 80-65-160/139 | C74: 0.75 | D74: 4 | E74: 98336369 | F74: 800 x 630 x 125 | G74: 92932672 | H74: CSM-14 | I74: 93176749 | J74: CWDM-36 | K74: 4 | L74: 3738 | M74: 1869 | R74: 565.52 | S74: 284.76 | T74: 59.52 | U74: 238.08 | V74: 288.58 | W74: 1154.32 | X74: 3738 | Y74: 1869 | Z74: 2672.6 | AA74: 3280
A75: 99801358 | B75: NBG 125-100-315/312 | C75: 22 | D75: 4 | E75: 99051550 | F75: 1500 x 800 x 225 | G75: 91338019 | H75: CLM-98 | J75: CDM-53 | K75: 4 | L75: 12750 | M75: 6375 | R75: 741.99 | S75: 284.76 | T75: 170.3 | U75: 681.2 | V75: 668.94 | W75: 2675.76 | X75: 12750 | Y75: 6375 | Z75: 7798.19 | AA75: 9569
A76: 99801361 | B76: NBG 125-100-400/375 | C76: 37 | D76: 4 | E76: 98299752 | F76: 1500 x 900 x 300 | G76: 91338021 | H76: CLM-100 | J76: CDM-55 | K76: 4 | L76: 20069 | M76: 10034.5 | R76: 824.44 | S76: 284.76 | T76: 170.3 | U76: 681.2 | V76: 717.41 | W76: 2869.64 | X76: 20069 | Y76: 10034.5 | Z76: 11540.14 | AA76: 14160
A77: 99801357 | B77: NBG 125-100-315/295 | C77: 18.5 | D77: 4 | E77: 99051550 | F77: 1500 x 800 x 225 | G77: 91338019 | H77: CLM-98 | J77: CDM-53 | K77: 4 | L77: 12247 | M77: 6123.5 | R77: 741.99 | S77: 284.76 | T77: 170.3 | U77: 681.2 | V77: 668.94 | W77: 2675.76 | X77: 12247 | Y77: 6123.5 | Z77: 7546.69 | AA77: 9260
A78: 99801356 | B78: NBG 125-100-315/279 | C78: 15 | D78: 4 | E78: 98327389 | F78: 1200 x 800 x 200 | G78: 91338018 | H78: CLM-97 | I78: 93176762 | J78: CDM-521 | K78: 4 | L78: 11503 | M78: 5751.5 | R78: 663.42 | S78: 284.76 | T78: 170.3 | U78: 681.2 | V78: 668.94 | W78: 2675.76 | X78: 11503 | Y78: 5751.5 | Z78: 7096.12 | AA78: 8707
A79: 99817806 | B79: NBG 125-100-200/195 | C79: 5.5 | D79: 4 | E79: 92513065 | F79: 1100 x 800 x 150 | G79: 91338157 | H79: CSM-17 | I79: 93176761 | J79: CWDM-37 | K79: 4 | L79: 6678 | M79: 3339 | R79: 610.6 | S79: 284.76 | T79: 59.52 | U79: 238.08 | V79: 288.59 | W79: 1154.36 | X79: 6678 | Y79: 3339 | Z79: 4187.68 | AA79: 5139
A80: 99801147 | B80: NBG 150-125-200/205 | C80: 75 | D80: 2 | E80: TBA | F80: 2100 x 1000 x 300 | G80: 91338020 | H80: CLM-99 | J80: CDM-531 | K80: 6 | L80: 19801 | M80: 9900.5 | R80: 1100 | S80: 427.14 | T80: 170.3 | U80: 1021.8 | V80: 717.41 | W80: 4304.46 | X80: 19801 | Y80: 9900.5 | Z80: 12022.3 | AA80: 14752
A81: 99801281 | B81: NBG 65-40-200/219 | C81: 2.2 | D81: 4 | E81: 92513065 | F81: 1100 x 800 x 150 | G81: 92932673 | H81: CSM-16 | I81: 93176761 | J81: CWDM-37 | K81: 4 | L81: 4160 | M81: 2080 | R81: 610.6 | S81: 284.76 | T81: 59.52 | U81: 238.08 | V81: 288.59 | W81: 1154.36 | X81: 4160 | Y81: 2080 | Z81: 2928.68 | AA81: 3594
A82: 99801341 | B82: NBG 125-80-315/334 | C82: 22 | D82: 4 | E82: 99051550 | F82: 1500 x 800 x 225 | G82: 91338019 | H82: CLM-98 | J82: CDM-53 | K82: 4 | L82: 12283 | M82: 6141.5 | N82: 1166 | O82: 583 | R82: 741.99 | S82: 284.76 | T82: 170.3 | U82: 681.2 | V82: 668.94 | W82: 2675.76 | X82: 12283 | Y82: 6141.5 | Z82: 7564.69 | AA82: 9282
A83: 99801367 | B83: NBG 150-125-200/226 | C83: 15 | D83: 4 | E83: 98327389 | F83: 1200 x 800 x 200 | G83: 91338018 | H83: CLM-97 | I83: 93176762 | J83: CDM-521 | K83: 4 | L83: 9648 | M83: 4824 | R83: 663.42 | S83: 284.76 | T83: 170.3 | U83: 681.2 | V83: 668.94 | W83: 2675.76 | X83: 9648 | Y83: 4824 | Z83: 6168.62 | AA83: 7569
A84: 99801124 | B84: NBG 125-80-200/171 | C84: 22 | D84: 2 | E84: 98327389 | F84: 1200 x 800 x 200 | G84: 91338018 | H84: CLM-97 | I84: 93176762 | J84: CDM-521 | K84: 4 | L84: 9004 | M84: 4502 | R84: 663.42 | S84: 284.76 | T84: 170.3 | U84: 681.2 | V84: 668.94 | W84: 2675.76 | X84: 9004 | Y84: 4502 | Z84: 5846.62 | AA84: 7174
A85: 99801396 | B85: NBG 200-150-400/375 | C85: 75 | D85: 4 | E85: TBA | F85: 2100 x 1000 x 300 | G85: 91338020 | H85: CLM-99 | J85: CDM-531 | K85: 6 | L85: 32328 | M85: 16164 | R85: 1100 | S85: 427.14 | T85: 170.3 | U85: 1021.8 | V85: 717.41 | W85: 4304.46 | X85: 32328 | Y85: 16164 | Z85: 18285.8 | AA85: 22437
A86: 99801344 | B86: NBG 125-80-400/397 | C86: 30 | D86: 4 | E86: 98299752 | F86: 1500 x 900 x 300 | G86: 91338020 | H86: CLM-99 | J86: CDM-531 | K86: 4 | L86: 17710 | M86: 8855 | N86: 1385.73 | O86: 692.87 | P86: 4448.34 | Q86: 2224.17 | R86: 824.44 | S86: 284.76 | T86: 170.3 | U86: 681.2 | V86: 717.41 | W86: 2869.64 | X86: 17710 | Y86: 8855 | Z86: 10360.64 | AA86: 12713
A87: 99801370 | B87: NBG 150-125-250/249 | C87: 18.5 | D87: 4 | E87: 99051550 | F87: 1500 x 800 x 225 | G87: 91338019 | H87: CLM-98 | J87: CDM-53 | K87: 4 | L87: 11154 | M87: 5577 | R87: 741.99 | S87: 284.76 | T87: 170.3 | U87: 681.2 | V87: 668.94 | W87: 2675.76 | X87: 11154 | Y87: 5577 | Z87: 7000.19 | AA87: 8590
A88: 99801307 | B88: NBG 100-65-200/170 | C88: 1.5 | D88: 4 | E88: 98336369 | F88: 800 x 630 x 125 | G88: 92932672 | H88: CSM-14 | I88: 93176749 | J88: CWDM-36 | K88: 4 | L88: 4427 | M88: 2213.5 | R88: 565.52 | S88: 284.76 | T88: 59.52 | U88: 238.08 | V88: 288.58 | W88: 1154.32 | X88: 4427 | Y88: 2213.5 | Z88: 3017.1 | AA88: 3702
A89: 99817805 | B89: NBG 125-80-250/247 | C89: 7.5 | D89: #N/A | E89: 92513065 | F89: 1100 x 800 x 150 | G89: 91338157 | H89: CSM-17 | I89: 93176761 | J89: CWDM-37 | K89: 4 | L89: 7428 | M89: 3714 | R89: 610.6 | S89: 284.76 | T89: 59.52 | U89: 238.08 | V89: 288.59 | W89: 1154.36 | X89: 7428 | Y89: 3714 | Z89: 4562.68 | AA89: 5599
A90: 99801336 | B90: NBG 125-80-250/225 | C90: 5.5 | D90: 4 | E90: 92513065 | F90: 1100 x 800 x 150 | G90: 91338157 | H90: CSM-17 | I90: 93176761 | J90: CWDM-37 | K90: 4 | L90: 6873 | M90: 3436.5 | R90: 610.6 | S90: 284.76 | T90: 59.52 | U90: 238.08 | V90: 288.59 | W90: 1154.36 | X90: 6873 | Y90: 3436.5 | Z90: 4285.18 | AA90: 5258
A91: 99801339 | B91: NBG 125-80-315/305 | C91: 15 | D91: 4 | E91: 98327389 | F91: 1200 x 800 x 200 | G91: 91338018 | H91: CLM-97 | I91: 93176762 | J91: CDM-521 | K91: 4 | L91: 10983 | M91: 5491.5 | R91: 663.42 | S91: 284.76 | T91: 170.3 | U91: 681.2 | V91: 668.94 | W91: 2675.76 | X91: 10983 | Y91: 5491.5 | Z91: 6836.12 | AA91: 8388
A92: 99801340 | B92: NBG 125-80-315/320 | C92: 18.5 | D92: 4 | E92: 99051550 | F92: 1500 x 800 x 225 | G92: 91338019 | H92: CLM-98 | J92: CDM-53 | K92: 4 | L92: 11812 | M92: 5906 | Q92: 1000 | R92: 741.99 | S92: 284.76 | T92: 170.3 | U92: 681.2 | V92: 668.94 | W92: 2675.76 | X92: 11812 | Y92: 5906 | Z92: 7329.19 | AA92: 8993
A93: 99801132 | B93: NBG 125-80-250/257 | C93: 75 | D93: 2 | E93: TBA | F93: 2100 x 1000 x 300 | G93: 91338020 | H93: CLM-99 | J93: CDM-531 | K93: 6 | L93: 20194 | M93: 10097 | R93: 1100 | S93: 427.14 | T93: 170.3 | U93: 1021.8 | V93: 717.41 | W93: 4304.46 | X93: 20194 | Y93: 10097 | Z93: 12218.8 | AA93: 14993
A94: 99801133 | B94: NBG 125-80-250/270 | C94: 90 | D94: 4 | E94: TBA | F94: 2100 x 1000 x 300 | G94: 91338021 | H94: CLM-100 | J94: CDM-55 | K94: 6 | L94: 22594 | M94: 11297 | R94: 1100 | S94: 427.14 | T94: 170.3 | U94: 1021.8 | V94: 717.41 | W94: 4304.46 | X94: 22594 | Y94: 11297 | Z94: 13418.8 | AA94: 16465
A95: 99801129 | B95: NBG 125-80-250/220 | C95: 45 | D95: 2 | E95: 98299752 | F95: 1500 x 900 x 300 | G95: 91338020 | H95: CLM-99 | J95: CDM-531 | K95: 4 | L95: 15048 | M95: 7524 | R95: 824.44 | S95: 284.76 | T95: 170.3 | U95: 681.2 | V95: 717.41 | W95: 2869.64 | X95: 15048 | Y95: 7524 | Z95: 9029.64 | AA95: 11080
A96: 99801338 | B96: NBG 125-80-315/280 | C96: 11 | D96: 4 | E96: 98327389 | F96: 1200 x 800 x 200 | G96: 91338018 | H96: CLM-97 | I96: 93176762 | J96: CDM-521 | K96: 4 | L96: 10501 | M96: 5250.5 | R96: 663.42 | S96: 284.76 | T96: 170.3 | U96: 681.2 | V96: 668.94 | W96: 2675.76 | X96: 10501 | Y96: 5250.5 | Z96: 6595.12 | AA96: 8093
A97: 99796414 | B97: NBG 65-40-200/172 | C97: 5.5 | D97: 2 | E97: 98327382 | F97: 950 x 720 x 150 | G97: 91338157 | H97: CSM-17 | I97: 93176761 | J97: CWDM-37 | K97: 4 | L97: 5175 | M97: 2587.5 | R97: 532.03 | S97: 284.76 | T97: 59.52 | U97: 238.08 | V97: 288.59 | W97: 1154.36 | X97: 5175 | Y97: 2587.5 | Z97: 3357.61 | AA97: 4120
A98: 99801310 | B98: NBG 100-65-200/219 | C98: 4 | D98: 4 | E98: 92513065 | F98: 1100 x 800 x 150 | G98: 91338157 | H98: CSM-17 | I98: 93176761 | J98: CWDM-37 | K98: 4 | L98: 5028 | M98: 2514 | R98: 610.6 | S98: 284.76 | T98: 59.52 | U98: 238.08 | V98: 288.59 | W98: 1154.36 | X98: 5028 | Y98: 2514 | Z98: 3362.68 | AA98: 4126
A99: 99801366 | B99: NBG 150-125-200/219 | C99: 11 | D99: 4 | E99: 98327389 | F99: 1200 x 800 x 200 | G99: 91338018 | H99: CLM-97 | I99: 93176762 | J99: CDM-521 | K99: 4 | L99: 9217 | M99: 4608.5 | R99: 663.42 | S99: 284.76 | T99: 170.3 | U99: 681.2 | V99: 668.94 | W99: 2675.76 | X99: 9217 | Y99: 4608.5 | Z99: 5953.12 | AA99: 7305
A100: 99801371 | B100: NBG 150-125-250/262 | C100: 22 | D100: 4 | E100: 99051550 | F100: 1500 x 800 x 225 | G100: 91338019 | H100: CLM-98 | J100: CDM-53 | K100: 4 | L100: 11665 | M100: 5832.5 | N100: 946 | O100: 473 | R100: 741.99 | S100: 284.76 | T100: 170.3 | U100: 681.2 | V100: 668.94 | W100: 2675.76 | X100: 11665 | Y100: 5832.5 | Z100: 7255.69 | AA100: 8903
...

Sheet NK BOM
A1: Item No | B1: Name | C1: kW | D1: Poles | E1: Inertia PN | F1: Inertia Size | G1: Std Spring PN | H1: Standard Spring | I1: 50mm Static Spring PN | J1: 50mm Spring | K1: Qty Springs | L1: Pump List | M1: Pump Nett | N1: IP-56 List | O1: IP-56 Nett | P1: IP-66 List | Q1: IP-66 Nett | R1: Inertia Nett | S1: Crossbar Nett | T1: Standard Spring Nett | U1: Total Standard Spring Nett | V1: 50mm Spring Nett | W1: Total 50mm Spring | X1: IE4
A2: 93030793 | B2: NK 150-280/273 | C2: 30 | D2: 4 | E2: 91338088 | F2: 1700 x 810 x 200 | G2: 91338019 | H2: CLM-98 | K2: 4 | L2: 13609.67 | M2: =L2/2 -> 6804.835 | R2: =VLOOKUP(E2,'Inertia Bases 2025'!$A:$H,8,0) -> 547.49 | T2: =VLOOKUP(G2,'Seismic Springs 2025'!$A:$I,9,0) -> 170.3 | U2: =T2*K2 -> 681.2
A3: 93030794 | B3: NK 100-280/240 | C3: 11 | D3: 4 | E3: 99051549 | F3: 1450 x 800 x 200 | G3: 91338018 | H3: CLM-97 | K3: 4 | L3: 10146.19 | M3: =L3/2 -> 5073.095 | R3: =VLOOKUP(E3,'Inertia Bases 2025'!$A:$H,8,0) -> 525.59 | T3: =VLOOKUP(G3,'Seismic Springs 2025'!$A:$I,9,0) -> 170.3 | U3: =T3*K3 -> 681.2
A4: 93030795 | B4: NK 125-380/307 | C4: 37 | D4: 4 | L4: 17265.15 | M4: =L4/2 -> 8632.575 | R4: =VLOOKUP(E4,'Inertia Bases 2025'!$A:$H,8,0) -> #N/A | T4: =VLOOKUP(G4,'Seismic Springs 2025'!$A:$I,9,0) -> #N/A | U4: =T4*K4 -> #N/A
A5: 93030796 | B5: NK 150-300/289 | C5: 30 | D5: 4 | E5: 92792038 | F5: 1700 x 900 x 200 | G5: 91338020 | H5: CLM-99 | K5: 4 | L5: 14226.58 | M5: =L5/2 -> 7113.29 | R5: =VLOOKUP(E5,'Inertia Bases 2025'!$A:$H,8,0) -> 780.65 | T5: =VLOOKUP(G5,'Seismic Springs 2025'!$A:$I,9,0) -> 170.3 | U5: =T5*K5 -> 681.2
A6: 93030797 | B6: NK 200-350/307 | C6: 55 | D6: 4 | E6: TBA-5 | F6: 1900 x 1200 x 250 | G6: 91338020 | H6: CLM-99 | K6: 6 | L6: 25256.92 | M6: =L6/2 -> 12628.46 | R6: =VLOOKUP(E6,'Inertia Bases 2025'!$A:$H,8,0) -> 1550 | T6: =VLOOKUP(G6,'Seismic Springs 2025'!$A:$I,9,0) -> 170.3 | U6: =T6*K6 -> 1021.8
A7: 93030798 | B7: NK 125-350/289 | C7: 22 | D7: 4 | E7: 91338088 | F7: 1700 x 810 x 200 | G7: 91338019 | H7: CLM-98 | K7: 4 | L7: 12765.38 | M7: =L7/2 -> 6382.69 | R7: =VLOOKUP(E7,'Inertia Bases 2025'!$A:$H,8,0) -> 547.49 | T7: =VLOOKUP(G7,'Seismic Springs 2025'!$A:$I,9,0) -> 170.3 | U7: =T7*K7 -> 681.2
A8: 93030799 | B8: NK 125-350/319 | C8: 30 | D8: 4 | E8: 91338088 | F8: 1700 x 810 x 200 | G8: 91338019 | H8: CLM-98 | K8: 4 | L8: 14899.28 | M8: =L8/2 -> 7449.64 | R8: =VLOOKUP(E8,'Inertia Bases 2025'!$A:$H,8,0) -> 547.49 | T8: =VLOOKUP(G8,'Seismic Springs 2025'!$A:$I,9,0) -> 170.3 | U8: =T8*K8 -> 681.2
A9: 93055390 | B9: NK 40-180/176 | C9: 11 | D9: 2 | L9: 6147.48 | M9: =L9/2 -> 3073.74 | R9: =VLOOKUP(E9,'Inertia Bases 2025'!$A:$H,8,0) -> #N/A | T9: =VLOOKUP(G9,'Seismic Springs 2025'!$A:$I,9,0) -> #N/A | U9: =T9*K9 -> #N/A
A10: 93055392 | B10: NK 40-180/173 | C10: 7.5 | D10: 2 | E10: 91338257 | F10: 1200 x 650 x 150 | G10: 92932673 | H10: CSM-16 | K10: 4 | L10: 5223.83 | M10: =L10/2 -> 2611.915 | R10: =VLOOKUP(E10,'Inertia Bases 2025'!$A:$H,8,0) -> 653.11 | T10: =VLOOKUP(G10,'Seismic Springs 2025'!$A:$I,9,0) -> 66.3 | U10: =T10*K10 -> 265.2
A11: 93055393 | B11: NK 40-180/155 | C11: 5.5 | D11: 2 | L11: 4934.38 | M11: =L11/2 -> 2467.19 | R11: =VLOOKUP(E11,'Inertia Bases 2025'!$A:$H,8,0) -> #N/A | T11: =VLOOKUP(G11,'Seismic Springs 2025'!$A:$I,9,0) -> #N/A | U11: =T11*K11 -> #N/A
A12: 93055394 | B12: NK 40-180/140 | C12: 4 | D12: 2 | E12: 92513065 | F12: 1100 x 800 x 150 | G12: 92932673 | H12: CSM-16 | K12: 4 | L12: 4552.89 | M12: =L12/2 -> 2276.445 | R12: =VLOOKUP(E12,'Inertia Bases 2025'!$A:$H,8,0) -> 610.6 | T12: =VLOOKUP(G12,'Seismic Springs 2025'!$A:$I,9,0) -> 66.3 | U12: =T12*K12 -> 265.2
A13: 93055395 | B13: NK 40-180/125 | C13: 3 | D13: 2 | L13: 4304.53 | M13: =L13/2 -> 2152.265 | R13: =VLOOKUP(E13,'Inertia Bases 2025'!$A:$H,8,0) -> #N/A | T13: =VLOOKUP(G13,'Seismic Springs 2025'!$A:$I,9,0) -> #N/A | U13: =T13*K13 -> #N/A
A14: 93055396 | B14: NK 40-180/112 | C14: 2.2 | D14: 2 | L14: 4004.36 | M14: =L14/2 -> 2002.18 | R14: =VLOOKUP(E14,'Inertia Bases 2025'!$A:$H,8,0) -> #N/A | T14: =VLOOKUP(G14,'Seismic Springs 2025'!$A:$I,9,0) -> #N/A | U14: =T14*K14 -> #N/A
A15: 93055397 | B15: NK 40-180/176 | C15: 1.1 | D15: 4 | L15: 3942.55 | M15: =L15/2 -> 1971.275 | R15: =VLOOKUP(E15,'Inertia Bases 2025'!$A:$H,8,0) -> #N/A | T15: =VLOOKUP(G15,'Seismic Springs 2025'!$A:$I,9,0) -> #N/A | U15: =T15*K15 -> #N/A
A16: 93055398 | B16: NK 40-180/162 | C16: 0.75 | D16: 4 | L16: 3744.24 | M16: =L16/2 -> 1872.12 | R16: =VLOOKUP(E16,'Inertia Bases 2025'!$A:$H,8,0) -> #N/A | T16: =VLOOKUP(G16,'Seismic Springs 2025'!$A:$I,9,0) -> #N/A | U16: =T16*K16 -> #N/A
A17: 93055399 | B17: NK 40-180/145 | C17: 0.55 | D17: 4 | L17: 3671.32 | M17: =L17/2 -> 1835.66 | R17: =VLOOKUP(E17,'Inertia Bases 2025'!$A:$H,8,0) -> #N/A | T17: =VLOOKUP(G17,'Seismic Springs 2025'!$A:$I,9,0) -> #N/A | U17: =T17*K17 -> #N/A
A18: 93055400 | B18: NK 40-180/130 | C18: 0.37 | D18: 4 | L18: 3433.98 | M18: =L18/2 -> 1716.99 | R18: =VLOOKUP(E18,'Inertia Bases 2025'!$A:$H,8,0) -> #N/A | T18: =VLOOKUP(G18,'Seismic Springs 2025'!$A:$I,9,0) -> #N/A | U18: =T18*K18 -> #N/A
A19: 93055401 | B19: NK 40-220/250 | C19: 18.5 | D19: 2 | L19: 7133.1 | M19: =L19/2 -> 3566.55 | R19: =VLOOKUP(E19,'Inertia Bases 2025'!$A:$H,8,0) -> #N/A | T19: =VLOOKUP(G19,'Seismic Springs 2025'!$A:$I,9,0) -> #N/A | U19: =T19*K19 -> #N/A
A20: 93055402 | B20: NK 40-220/244 | C20: 15 | D20: 2 | L20: 6876.54 | M20: =L20/2 -> 3438.27 | R20: =VLOOKUP(E20,'Inertia Bases 2025'!$A:$H,8,0) -> #N/A | T20: =VLOOKUP(G20,'Seismic Springs 2025'!$A:$I,9,0) -> #N/A | U20: =T20*K20 -> #N/A
A21: 93055403 | B21: NK 40-220/212 | C21: 11 | D21: 2 | E21: 91338087 | F21: 1320 x 740 x 125 | G21: 91338157 | H21: CSM-17 | K21: 4 | L21: 6633.58 | M21: =L21/2 -> 3316.79 | R21: =VLOOKUP(E21,'Inertia Bases 2025'!$A:$H,8,0) -> 541.04 | T21: =VLOOKUP(G21,'Seismic Springs 2025'!$A:$I,9,0) -> 66.3 | U21: =T21*K21 -> 265.2
A22: 93055404 | B22: NK 40-220/192 | C22: 7.5 | D22: 2 | L22: 5598.53 | M22: =L22/2 -> 2799.265 | R22: =VLOOKUP(E22,'Inertia Bases 2025'!$A:$H,8,0) -> #N/A | T22: =VLOOKUP(G22,'Seismic Springs 2025'!$A:$I,9,0) -> #N/A | U22: =T22*K22 -> #N/A
A23: 93055405 | B23: NK 40-220/172 | C23: 5.5 | D23: 2 | L23: 5320.18 | M23: =L23/2 -> 2660.09 | R23: =VLOOKUP(E23,'Inertia Bases 2025'!$A:$H,8,0) -> #N/A | T23: =VLOOKUP(G23,'Seismic Springs 2025'!$A:$I,9,0) -> #N/A | U23: =T23*K23 -> #N/A
A24: 93055406 | B24: NK 40-220/250 | C24: 2.2 | D24: 4 | L24: 4748.32 | M24: =L24/2 -> 2374.16 | R24: =VLOOKUP(E24,'Inertia Bases 2025'!$A:$H,8,0) -> #N/A | T24: =VLOOKUP(G24,'Seismic Springs 2025'!$A:$I,9,0) -> #N/A | U24: =T24*K24 -> #N/A
A25: 93055407 | B25: NK 40-220/218 | C25: 1.5 | D25: 4 | L25: 4491.34 | M25: =L25/2 -> 2245.67 | R25: =VLOOKUP(E25,'Inertia Bases 2025'!$A:$H,8,0) -> #N/A | T25: =VLOOKUP(G25,'Seismic Springs 2025'!$A:$I,9,0) -> #N/A | U25: =T25*K25 -> #N/A
A26: 93055408 | B26: NK 40-220/200 | C26: 1.1 | D26: 4 | L26: 4436.06 | M26: =L26/2 -> 2218.03 | R26: =VLOOKUP(E26,'Inertia Bases 2025'!$A:$H,8,0) -> #N/A | T26: =VLOOKUP(G26,'Seismic Springs 2025'!$A:$I,9,0) -> #N/A | U26: =T26*K26 -> #N/A
A27: 93055409 | B27: NK 40-220/179 | C27: 0.75 | D27: 4 | L27: 4122.63 | M27: =L27/2 -> 2061.315 | R27: =VLOOKUP(E27,'Inertia Bases 2025'!$A:$H,8,0) -> #N/A | T27: =VLOOKUP(G27,'Seismic Springs 2025'!$A:$I,9,0) -> #N/A | U27: =T27*K27 -> #N/A
A28: 93055411 | B28: NK 40-220/167 | C28: 0.55 | D28: 4 | L28: 4038.53 | M28: =L28/2 -> 2019.265 | R28: =VLOOKUP(E28,'Inertia Bases 2025'!$A:$H,8,0) -> #N/A | T28: =VLOOKUP(G28,'Seismic Springs 2025'!$A:$I,9,0) -> #N/A | U28: =T28*K28 -> #N/A
A29: 93055413 | B29: NK 40-225/246 | C29: 22 | D29: 2 | L29: 7784.02 | M29: =L29/2 -> 3892.01 | R29: =VLOOKUP(E29,'Inertia Bases 2025'!$A:$H,8,0) -> #N/A | T29: =VLOOKUP(G29,'Seismic Springs 2025'!$A:$I,9,0) -> #N/A | U29: =T29*K29 -> #N/A
A30: 93055414 | B30: NK 40-225/230 | C30: 18.5 | D30: 2 | L30: 7296.13 | M30: =L30/2 -> 3648.065 | R30: =VLOOKUP(E30,'Inertia Bases 2025'!$A:$H,8,0) -> #N/A | T30: =VLOOKUP(G30,'Seismic Springs 2025'!$A:$I,9,0) -> #N/A | U30: =T30*K30 -> #N/A
A31: 93055415 | B31: NK 40-225/210 | C31: 15 | D31: 2 | L31: 6902.16 | M31: =L31/2 -> 3451.08 | R31: =VLOOKUP(E31,'Inertia Bases 2025'!$A:$H,8,0) -> #N/A | T31: =VLOOKUP(G31,'Seismic Springs 2025'!$A:$I,9,0) -> #N/A | U31: =T31*K31 -> #N/A
A32: 93055417 | B32: NK 40-225/192 | C32: 11 | D32: 2 | E32: 91338087 | F32: 1320 x 740 x 125 | G32: 91338157 | H32: CSM-17 | K32: 4 | L32: 6644.33 | M32: =L32/2 -> 3322.165 | R32: =VLOOKUP(E32,'Inertia Bases 2025'!$A:$H,8,0) -> 541.04 | T32: =VLOOKUP(G32,'Seismic Springs 2025'!$A:$I,9,0) -> 66.3 | U32: =T32*K32 -> 265.2
A33: 93055418 | B33: NK 40-225/173 | C33: 7.5 | D33: 2 | L33: 5605.58 | M33: =L33/2 -> 2802.79 | R33: =VLOOKUP(E33,'Inertia Bases 2025'!$A:$H,8,0) -> #N/A | T33: =VLOOKUP(G33,'Seismic Springs 2025'!$A:$I,9,0) -> #N/A | U33: =T33*K33 -> #N/A
A34: 93055419 | B34: NK 40-225/158 | C34: 5.5 | D34: 2 | L34: 5360.62 | M34: =L34/2 -> 2680.31 | R34: =VLOOKUP(E34,'Inertia Bases 2025'!$A:$H,8,0) -> #N/A | T34: =VLOOKUP(G34,'Seismic Springs 2025'!$A:$I,9,0) -> #N/A | U34: =T34*K34 -> #N/A
A35: 93055420 | B35: NK 40-225/250 | C35: 3 | D35: 4 | E35: 92513065 | F35: 1100 x 800 x 150 | G35: 91338157 | H35: CSM-17 | L35: 4871.85 | M35: =L35/2 -> 2435.925 | R35: =VLOOKUP(E35,'Inertia Bases 2025'!$A:$H,8,0) -> 610.6 | T35: =VLOOKUP(G35,'Seismic Springs 2025'!$A:$I,9,0) -> 66.3 | U35: =T35*K35 -> 0
A36: 93055421 | B36: NK 40-225/226 | C36: 2.2 | D36: 4 | L36: 4755.35 | M36: =L36/2 -> 2377.675 | R36: =VLOOKUP(E36,'Inertia Bases 2025'!$A:$H,8,0) -> #N/A | T36: =VLOOKUP(G36,'Seismic Springs 2025'!$A:$I,9,0) -> #N/A | U36: =T36*K36 -> #N/A
A37: 93055422 | B37: NK 40-225/199 | C37: 1.5 | D37: 4 | L37: 4520.65 | M37: =L37/2 -> 2260.325 | R37: =VLOOKUP(E37,'Inertia Bases 2025'!$A:$H,8,0) -> #N/A | T37: =VLOOKUP(G37,'Seismic Springs 2025'!$A:$I,9,0) -> #N/A | U37: =T37*K37 -> #N/A
A38: 93055423 | B38: NK 40-225/182 | C38: 1.1 | D38: 4 | L38: 4443.12 | M38: =L38/2 -> 2221.56 | R38: =VLOOKUP(E38,'Inertia Bases 2025'!$A:$H,8,0) -> #N/A | T38: =VLOOKUP(G38,'Seismic Springs 2025'!$A:$I,9,0) -> #N/A | U38: =T38*K38 -> #N/A
A39: 93055424 | B39: NK 40-225/162 | C39: 0.75 | D39: 4 | L39: 4148.24 | M39: =L39/2 -> 2074.12 | R39: =VLOOKUP(E39,'Inertia Bases 2025'!$A:$H,8,0) -> #N/A | T39: =VLOOKUP(G39,'Seismic Springs 2025'!$A:$I,9,0) -> #N/A | U39: =T39*K39 -> #N/A
A40: 93055426 | B40: NK 50-225/240 | C40: 30 | D40: 2 | L40: 9278.9 | M40: =L40/2 -> 4639.45 | R40: =VLOOKUP(E40,'Inertia Bases 2025'!$A:$H,8,0) -> #N/A | T40: =VLOOKUP(G40,'Seismic Springs 2025'!$A:$I,9,0) -> #N/A | U40: =T40*K40 -> #N/A
A41: 93055427 | B41: NK 50-225/225 | C41: 22 | D41: 2 | L41: 8233.53 | M41: =L41/2 -> 4116.765 | R41: =VLOOKUP(E41,'Inertia Bases 2025'!$A:$H,8,0) -> #N/A | T41: =VLOOKUP(G41,'Seismic Springs 2025'!$A:$I,9,0) -> #N/A | U41: =T41*K41 -> #N/A
A42: 93055428 | B42: NK 50-225/208 | C42: 18.5 | D42: 2 | E42: 93047546 | F42: 1400 x 700 x 175 | G42: 91338017 | H42: CLM-96 | K42: 4 | L42: 7407.66 | M42: =L42/2 -> 3703.83 | R42: =VLOOKUP(E42,'Inertia Bases 2025'!$A:$H,8,0) -> 729.11 | T42: =VLOOKUP(G42,'Seismic Springs 2025'!$A:$I,9,0) -> 135.26 | U42: =T42*K42 -> 541.04
A43: 93055429 | B43: NK 50-225/193 | C43: 15 | D43: 2 | E43: 99051564 | F43: 1350 x 800 x 175 | G43: 91338018 | H43: CLM-97 | K43: 4 | L43: 7013.69 | M43: =L43/2 -> 3506.845 | O43: =3590.15-M43 -> 83.305 | P43: =Q43*2 -> 1339.47 | Q43: 669.735 | R43: =VLOOKUP(E43,'Inertia Bases 2025'!$A:$H,8,0) -> 722.67 | T43: =VLOOKUP(G43,'Seismic Springs 2025'!$A:$I,9,0) -> 170.3 | U43: =T43*K43 -> 681.2
A44: 93055430 | B44: NK 50-225/172 | C44: 11 | D44: 2 | E44: 99051564 | F44: 1350 x 800 x 175 | G44: 91338018 | H44: CLM-97 | K44: 4 | L44: 6752.14 | M44: =L44/2 -> 3376.07 | P44: =Q44*2 -> 1215.324 | Q44: 607.662 | R44: =VLOOKUP(E44,'Inertia Bases 2025'!$A:$H,8,0) -> 722.67 | T44: =VLOOKUP(G44,'Seismic Springs 2025'!$A:$I,9,0) -> 170.3 | U44: =T44*K44 -> 681.2
A45: 93055431 | B45: NK 50-225/151 | C45: 7.5 | D45: 2 | L45: 5668.83 | M45: =L45/2 -> 2834.415 | R45: =VLOOKUP(E45,'Inertia Bases 2025'!$A:$H,8,0) -> #N/A | T45: =VLOOKUP(G45,'Seismic Springs 2025'!$A:$I,9,0) -> #N/A | U45: =T45*K45 -> #N/A
A46: 93055432 | B46: NK 50-225/139 | C46: 5.5 | D46: 2 | L46: 5429.1 | M46: =L46/2 -> 2714.55 | R46: =VLOOKUP(E46,'Inertia Bases 2025'!$A:$H,8,0) -> #N/A | T46: =VLOOKUP(G46,'Seismic Springs 2025'!$A:$I,9,0) -> #N/A | U46: =T46*K46 -> #N/A
A47: 93055433 | B47: NK 50-225/240 | C47: 4 | D47: 4 | L47: 5121.02 | M47: =L47/2 -> 2560.51 | R47: =VLOOKUP(E47,'Inertia Bases 2025'!$A:$H,8,0) -> #N/A | T47: =VLOOKUP(G47,'Seismic Springs 2025'!$A:$I,9,0) -> #N/A | U47: =T47*K47 -> #N/A
A48: 93055434 | B48: NK 50-225/237 | C48: 3 | D48: 4 | L48: 4920.23 | M48: =L48/2 -> 2460.115 | R48: =VLOOKUP(E48,'Inertia Bases 2025'!$A:$H,8,0) -> #N/A | T48: =VLOOKUP(G48,'Seismic Springs 2025'!$A:$I,9,0) -> #N/A | U48: =T48*K48 -> #N/A
A49: 93055435 | B49: NK 50-225/207 | C49: 2.2 | D49: 4 | L49: 4807.49 | M49: =L49/2 -> 2403.745 | R49: =VLOOKUP(E49,'Inertia Bases 2025'!$A:$H,8,0) -> #N/A | T49: =VLOOKUP(G49,'Seismic Springs 2025'!$A:$I,9,0) -> #N/A | U49: =T49*K49 -> #N/A
A50: 93055436 | B50: NK 50-225/181 | C50: 1.5 | D50: 4 | L50: 4632.18 | M50: =L50/2 -> 2316.09 | R50: =VLOOKUP(E50,'Inertia Bases 2025'!$A:$H,8,0) -> #N/A | T50: =VLOOKUP(G50,'Seismic Springs 2025'!$A:$I,9,0) -> #N/A | U50: =T50*K50 -> #N/A
A51: 93055437 | B51: NK 50-225/160 | C51: 1.1 | D51: 4 | L51: 4571.38 | M51: =L51/2 -> 2285.69 | R51: =VLOOKUP(E51,'Inertia Bases 2025'!$A:$H,8,0) -> #N/A | T51: =VLOOKUP(G51,'Seismic Springs 2025'!$A:$I,9,0) -> #N/A | U51: =T51*K51 -> #N/A
A52: 93055438 | B52: NK 50-225/144 | C52: 0.75 | D52: 4 | L52: 4517.25 | M52: =L52/2 -> 2258.625 | R52: =VLOOKUP(E52,'Inertia Bases 2025'!$A:$H,8,0) -> #N/A | T52: =VLOOKUP(G52,'Seismic Springs 2025'!$A:$I,9,0) -> #N/A | U52: =T52*K52 -> #N/A
A53: 93055439 | B53: NK 50-280/262 | C53: 5.5 | D53: 4 | L53: 5646.55 | M53: =L53/2 -> 2823.275 | R53: =VLOOKUP(E53,'Inertia Bases 2025'!$A:$H,8,0) -> #N/A | T53: =VLOOKUP(G53,'Seismic Springs 2025'!$A:$I,9,0) -> #N/A | U53: =T53*K53 -> #N/A
A54: 93055440 | B54: NK 50-280/250 | C54: 4 | D54: 4 | L54: 5250.69 | M54: =L54/2 -> 2625.345 | R54: =VLOOKUP(E54,'Inertia Bases 2025'!$A:$H,8,0) -> #N/A | T54: =VLOOKUP(G54,'Seismic Springs 2025'!$A:$I,9,0) -> #N/A | U54: =T54*K54 -> #N/A
A55: 93055441 | B55: NK 50-280/226 | C55: 3 | D55: 4 | L55: 5001.84 | M55: =L55/2 -> 2500.92 | R55: =VLOOKUP(E55,'Inertia Bases 2025'!$A:$H,8,0) -> #N/A | T55: =VLOOKUP(G55,'Seismic Springs 2025'!$A:$I,9,0) -> #N/A | U55: =T55*K55 -> #N/A
A56: 93055442 | B56: NK 50-280/208 | C56: 2.2 | D56: 4 | L56: 4887.76 | M56: =L56/2 -> 2443.88 | R56: =VLOOKUP(E56,'Inertia Bases 2025'!$A:$H,8,0) -> #N/A | T56: =VLOOKUP(G56,'Seismic Springs 2025'!$A:$I,9,0) -> #N/A | U56: =T56*K56 -> #N/A
A57: 93055443 | B57: NK 50-350/340-336 | C57: 11 | D57: 4 | E57: 99051549 | F57: 1450 x 800 x 200 | G57: 91338018 | H57: CLM-97 | K57: 4 | L57: 9618.28 | M57: =L57/2 -> 4809.14 | R57: =VLOOKUP(E57,'Inertia Bases 2025'!$A:$H,8,0) -> 525.59 | T57: =VLOOKUP(G57,'Seismic Springs 2025'!$A:$I,9,0) -> 170.3 | U57: =T57*K57 -> 681.2
A58: 93055444 | B58: NK 50-350/304 | C58: 7.5 | D58: 4 | L58: 8380.48 | M58: =L58/2 -> 4190.24 | R58: =VLOOKUP(E58,'Inertia Bases 2025'!$A:$H,8,0) -> #N/A | T58: =VLOOKUP(G58,'Seismic Springs 2025'!$A:$I,9,0) -> #N/A | U58: =T58*K58 -> #N/A
A59: 93055445 | B59: NK 50-350/278 | C59: 5.5 | D59: 4 | E59: 91338087 | F59: 1320 x 740 x 125 | G59: 91338157 | H59: CSM-17 | K59: 4 | L59: 8027.54 | M59: =L59/2 -> 4013.77 | R59: =VLOOKUP(E59,'Inertia Bases 2025'!$A:$H,8,0) -> 541.04 | T59: =VLOOKUP(G59,'Seismic Springs 2025'!$A:$I,9,0) -> 66.3 | U59: =T59*K59 -> 265.2
A60: 93055446 | B60: NK 50-350/256 | C60: 4 | D60: 4 | L60: 7786.7 | M60: =L60/2 -> 3893.35 | R60: =VLOOKUP(E60,'Inertia Bases 2025'!$A:$H,8,0) -> #N/A | T60: =VLOOKUP(G60,'Seismic Springs 2025'!$A:$I,9,0) -> #N/A | U60: =T60*K60 -> #N/A
A61: 93055447 | B61: NK 50-350/236 | C61: 3 | D61: 4 | L61: 7597.6 | M61: =L61/2 -> 3798.8 | R61: =VLOOKUP(E61,'Inertia Bases 2025'!$A:$H,8,0) -> #N/A | T61: =VLOOKUP(G61,'Seismic Springs 2025'!$A:$I,9,0) -> #N/A | U61: =T61*K61 -> #N/A
A62: 93055448 | B62: NK 65-180/172 | C62: 15 | D62: 2 | L62: 6758.93 | M62: =L62/2 -> 3379.465 | R62: =VLOOKUP(E62,'Inertia Bases 2025'!$A:$H,8,0) -> #N/A | T62: =VLOOKUP(G62,'Seismic Springs 2025'!$A:$I,9,0) -> #N/A | U62: =T62*K62 -> #N/A
A63: 93055449 | B63: NK 65-180/169 | C63: 11 | D63: 2 | E63: 93000767 | F63: 1300 x 800 x 200 | G63: 91338017 | H63: CLM-96 | K63: 4 | L63: 6501.07 | M63: =L63/2 -> 3250.535 | R63: =VLOOKUP(E63,'Inertia Bases 2025'!$A:$H,8,0) -> 669.87 | T63: =VLOOKUP(G63,'Seismic Springs 2025'!$A:$I,9,0) -> 135.26 | U63: =T63*K63 -> 541.04
A64: 93055450 | B64: NK 65-180/154 | C64: 7.5 | D64: 2 | L64: 5451.19 | M64: =L64/2 -> 2725.595 | R64: =VLOOKUP(E64,'Inertia Bases 2025'!$A:$H,8,0) -> #N/A | T64: =VLOOKUP(G64,'Seismic Springs 2025'!$A:$I,9,0) -> #N/A | U64: =T64*K64 -> #N/A
A65: 93055451 | B65: NK 65-180/139 | C65: 5.5 | D65: 2 | L65: 5280.52 | M65: =L65/2 -> 2640.26 | R65: =VLOOKUP(E65,'Inertia Bases 2025'!$A:$H,8,0) -> #N/A | T65: =VLOOKUP(G65,'Seismic Springs 2025'!$A:$I,9,0) -> #N/A | U65: =T65*K65 -> #N/A
A66: 93055452 | B66: NK 65-180/124 | C66: 4 | D66: 2 | L66: 4850.81 | M66: =L66/2 -> 2425.405 | R66: =VLOOKUP(E66,'Inertia Bases 2025'!$A:$H,8,0) -> #N/A | T66: =VLOOKUP(G66,'Seismic Springs 2025'!$A:$I,9,0) -> #N/A | U66: =T66*K66 -> #N/A
A67: 93055453 | B67: NK 65-180/113 | C67: 3 | D67: 2 | L67: 4534.56 | M67: =L67/2 -> 2267.28 | R67: =VLOOKUP(E67,'Inertia Bases 2025'!$A:$H,8,0) -> #N/A | T67: =VLOOKUP(G67,'Seismic Springs 2025'!$A:$I,9,0) -> #N/A | U67: =T67*K67 -> #N/A
A68: 93055454 | B68: NK 65-180/172 | C68: 1.5 | D68: 4 | L68: 4373.7 | M68: =L68/2 -> 2186.85 | R68: =VLOOKUP(E68,'Inertia Bases 2025'!$A:$H,8,0) -> #N/A | T68: =VLOOKUP(G68,'Seismic Springs 2025'!$A:$I,9,0) -> #N/A | U68: =T68*K68 -> #N/A
A69: 93055455 | B69: NK 65-180/162 | C69: 1.1 | D69: 4 | L69: 4299.86 | M69: =L69/2 -> 2149.93 | R69: =VLOOKUP(E69,'Inertia Bases 2025'!$A:$H,8,0) -> #N/A | T69: =VLOOKUP(G69,'Seismic Springs 2025'!$A:$I,9,0) -> #N/A | U69: =T69*K69 -> #N/A
A70: 93055456 | B70: NK 65-180/145 | C70: 0.75 | D70: 4 | L70: 4082.97 | M70: =L70/2 -> 2041.485 | R70: =VLOOKUP(E70,'Inertia Bases 2025'!$A:$H,8,0) -> #N/A | T70: =VLOOKUP(G70,'Seismic Springs 2025'!$A:$I,9,0) -> #N/A | U70: =T70*K70 -> #N/A
A71: 93055457 | B71: NK 65-180/131 | C71: 0.55 | D71: 4 | L71: 4021.22 | M71: =L71/2 -> 2010.61 | R71: =VLOOKUP(E71,'Inertia Bases 2025'!$A:$H,8,0) -> #N/A | T71: =VLOOKUP(G71,'Seismic Springs 2025'!$A:$I,9,0) -> #N/A | U71: =T71*K71 -> #N/A
A72: 93055458 | B72: NK 65-225/242 | C72: 37 | D72: 2 | L72: 12045.49 | M72: =L72/2 -> 6022.745 | R72: =VLOOKUP(E72,'Inertia Bases 2025'!$A:$H,8,0) -> #N/A | T72: =VLOOKUP(G72,'Seismic Springs 2025'!$A:$I,9,0) -> #N/A | U72: =T72*K72 -> #N/A
A73: 93055459 | B73: NK 65-225/232 | C73: 30 | D73: 2 | E73: 91338088 | F73: 1700 x 810 x 200 | G73: 91338019 | H73: CLM-98 | K73: 4 | L73: 10842.32 | M73: =L73/2 -> 5421.16 | R73: =VLOOKUP(E73,'Inertia Bases 2025'!$A:$H,8,0) -> 547.49 | T73: =VLOOKUP(G73,'Seismic Springs 2025'!$A:$I,9,0) -> 170.3 | U73: =T73*K73 -> 681.2
A74: 93055460 | B74: NK 65-225/200 | C74: 22 | D74: 2 | E74: 99051549 | F74: 1450 x 800 x 200 | G74: 91338019 | H74: CLM-98 | K74: 4 | L74: 9277.01 | M74: =L74/2 -> 4638.505 | R74: =VLOOKUP(E74,'Inertia Bases 2025'!$A:$H,8,0) -> 525.59 | T74: =VLOOKUP(G74,'Seismic Springs 2025'!$A:$I,9,0) -> 170.3 | U74: =T74*K74 -> 681.2
A75: 93055461 | B75: NK 65-225/184 | C75: 18.5 | D75: 2 | E75: 93047546 | F75: 1400 x 700 x 175 | G75: 91338018 | H75: CLM-97 | K75: 4 | L75: 8417.69 | M75: =L75/2 -> 4208.845 | R75: =VLOOKUP(E75,'Inertia Bases 2025'!$A:$H,8,0) -> 729.11 | T75: =VLOOKUP(G75,'Seismic Springs 2025'!$A:$I,9,0) -> 170.3 | U75: =T75*K75 -> 681.2
A76: 93055462 | B76: NK 65-225/167 | C76: 15 | D76: 2 | L76: 7318.15 | M76: =L76/2 -> 3659.075 | R76: =VLOOKUP(E76,'Inertia Bases 2025'!$A:$H,8,0) -> #N/A | T76: =VLOOKUP(G76,'Seismic Springs 2025'!$A:$I,9,0) -> #N/A | U76: =T76*K76 -> #N/A
A77: 93055463 | B77: NK 65-225/150 | C77: 11 | D77: 2 | L77: 7060.28 | M77: =L77/2 -> 3530.14 | R77: =VLOOKUP(E77,'Inertia Bases 2025'!$A:$H,8,0) -> #N/A | T77: =VLOOKUP(G77,'Seismic Springs 2025'!$A:$I,9,0) -> #N/A | U77: =T77*K77 -> #N/A
A78: 93055464 | B78: NK 65-225/242 | C78: 4 | D78: 4 | L78: 5570.3 | M78: =L78/2 -> 2785.15 | R78: =VLOOKUP(E78,'Inertia Bases 2025'!$A:$H,8,0) -> #N/A | T78: =VLOOKUP(G78,'Seismic Springs 2025'!$A:$I,9,0) -> #N/A | U78: =T78*K78 -> #N/A
A79: 93055465 | B79: NK 65-225/211 | C79: 3 | D79: 4 | L79: 5284.05 | M79: =L79/2 -> 2642.025 | R79: =VLOOKUP(E79,'Inertia Bases 2025'!$A:$H,8,0) -> #N/A | T79: =VLOOKUP(G79,'Seismic Springs 2025'!$A:$I,9,0) -> #N/A | U79: =T79*K79 -> #N/A
A80: 93055466 | B80: NK 65-225/183 | C80: 2.2 | D80: 4 | L80: 5171.3 | M80: =L80/2 -> 2585.65 | R80: =VLOOKUP(E80,'Inertia Bases 2025'!$A:$H,8,0) -> #N/A | T80: =VLOOKUP(G80,'Seismic Springs 2025'!$A:$I,9,0) -> #N/A | U80: =T80*K80 -> #N/A
A81: 93055468 | B81: NK 65-225/158 | C81: 1.5 | D81: 4 | L81: 5092.57 | M81: =L81/2 -> 2546.285 | R81: =VLOOKUP(E81,'Inertia Bases 2025'!$A:$H,8,0) -> #N/A | T81: =VLOOKUP(G81,'Seismic Springs 2025'!$A:$I,9,0) -> #N/A | U81: =T81*K81 -> #N/A
A82: 93055469 | B82: NK 65-225/144 | C82: 1.1 | D82: 4 | L82: 5070.74 | M82: =L82/2 -> 2535.37 | R82: =VLOOKUP(E82,'Inertia Bases 2025'!$A:$H,8,0) -> #N/A | T82: =VLOOKUP(G82,'Seismic Springs 2025'!$A:$I,9,0) -> #N/A | U82: =T82*K82 -> #N/A
A83: 93055470 | B83: NK 65-225/240 | C83: 1.1 | D83: 6 | L83: 5742.63 | M83: =L83/2 -> 2871.315 | R83: =VLOOKUP(E83,'Inertia Bases 2025'!$A:$H,8,0) -> #N/A | T83: =VLOOKUP(G83,'Seismic Springs 2025'!$A:$I,9,0) -> #N/A | U83: =T83*K83 -> #N/A
A84: 93055472 | B84: NK 65-225/193 | C84: 0.75 | D84: 6 | L84: 5723.2 | M84: =L84/2 -> 2861.6 | R84: =VLOOKUP(E84,'Inertia Bases 2025'!$A:$H,8,0) -> #N/A | T84: =VLOOKUP(G84,'Seismic Springs 2025'!$A:$I,9,0) -> #N/A | U84: =T84*K84 -> #N/A
A85: 93055473 | B85: NK 65-225/182 | C85: 0.55 | D85: 6 | L85: 5684.58 | M85: =L85/2 -> 2842.29 | R85: =VLOOKUP(E85,'Inertia Bases 2025'!$A:$H,8,0) -> #N/A | T85: =VLOOKUP(G85,'Seismic Springs 2025'!$A:$I,9,0) -> #N/A | U85: =T85*K85 -> #N/A
A86: 93055474 | B86: NK 65-280/280 | C86: 7.5 | D86: 4 | L86: 6831.89 | M86: =L86/2 -> 3415.945 | R86: =VLOOKUP(E86,'Inertia Bases 2025'!$A:$H,8,0) -> #N/A | T86: =VLOOKUP(G86,'Seismic Springs 2025'!$A:$I,9,0) -> #N/A | U86: =T86*K86 -> #N/A
A87: 93055475 | B87: NK 65-280/270 | C87: 5.5 | D87: 4 | L87: 6528.38 | M87: =L87/2 -> 3264.19 | R87: =VLOOKUP(E87,'Inertia Bases 2025'!$A:$H,8,0) -> #N/A | T87: =VLOOKUP(G87,'Seismic Springs 2025'!$A:$I,9,0) -> #N/A | U87: =T87*K87 -> #N/A
... A94: 93055482 | B94: NK 80-180/174 | C94: 18.5 | D94: 2 | L94: 8338.36 | M94: =L94/2 -> 4169.18 | R94: =VLOOKUP(E94,'Inertia Bases 2025'!$A:$H,8,0) -> #N/A | T94: =VLOOKUP(G94,'Seismic Springs 2025'!$A:$I,9,0) -> #N/A | U94: =T94*K94 -> #N/A
A95: 93055483 | B95: NK 80-180/172 | C95: 15 | D95: 2 | E95: 91338087 | F95: 1320 x 740 x 125 | G95: 91338157 | H95: CSM-17 | K95: 4 | L95: 7097.69 | M95: =L95/2 -> 3548.845 | R95: =VLOOKUP(E95,'Inertia Bases 2025'!$A:$H,8,0) -> 541.04 | T95: =VLOOKUP(G95,'Seismic Springs 2025'!$A:$I,9,0) -> 66.3 | U95: =T95*K95 -> 265.2
A96: 93055484 | B96: NK 80-180/153 | C96: 11 | D96: 2 | E96: 91338087 | F96: 1320 x 740 x 125 | G96: 91338157 | H96: CSM-17 | K96: 4 | L96: 6839.82 | M96: =L96/2 -> 3419.91 | R96: =VLOOKUP(E96,'Inertia Bases 2025'!$A:$H,8,0) -> 541.04 | T96: =VLOOKUP(G96,'Seismic Springs 2025'!$A:$I,9,0) -> 66.3 | U96: =T96*K96 -> 265.2
A97: 93055485 | B97: NK 80-180/137 | C97: 7.5 | D97: 2 | L97: 5797.39 | M97: =L97/2 -> 2898.695 | R97: =VLOOKUP(E97,'Inertia Bases 2025'!$A:$H,8,0) -> #N/A | T97: =VLOOKUP(G97,'Seismic Springs 2025'!$A:$I,9,0) -> #N/A | U97: =T97*K97 -> #N/A
A98: 93055486 | B98: NK 80-180/123 | C98: 5.5 | D98: 2 | L98: 5626.72 | M98: =L98/2 -> 2813.36 | R98: =VLOOKUP(E98,'Inertia Bases 2025'!$A:$H,8,0) -> #N/A | T98: =VLOOKUP(G98,'Seismic Springs 2025'!$A:$I,9,0) -> #N/A | U98: =T98*K98 -> #N/A
A99: 93055487 | B99: NK 80-180/112 | C99: 4 | D99: 2 | L99: 5215.57 | M99: =L99/2 -> 2607.785 | R99: =VLOOKUP(E99,'Inertia Bases 2025'!$A:$H,8,0) -> #N/A | T99: =VLOOKUP(G99,'Seismic Springs 2025'!$A:$I,9,0) -> #N/A | U99: =T99*K99 -> #N/A
A100: 93055488 | B100: NK 80-180/174 | C100: 2.2 | D100: 4 | L100: 4950.88 | M100: =L100/2 -> 2475.44 | R100: =VLOOKUP(E100,'Inertia Bases 2025'!$A:$H,8,0) -> #N/A | T100: =VLOOKUP(G100,'Seismic Springs 2025'!$A:$I,9,0) -> #N/A | U100: =T100*K100 -> #N/A
A101: 93055489 | B101: NK 80-180/165 | C101: 1.5 | D101: 4 | L101: 4716.18 | M101: =L101/2 -> 2358.09 | R101: =VLOOKUP(E101,'Inertia Bases 2025'!$A:$H,8,0) -> #N/A | T101: =VLOOKUP(G101,'Seismic Springs 2025'!$A:$I,9,0) -> #N/A | U101: =T101*K101 -> #N/A
A102: 93055490 | B102: NK 80-180/145 | C102: 1.1 | D102: 4 | L102: 4601.47 | M102: =L102/2 -> 2300.735 | R102: =VLOOKUP(E102,'Inertia Bases 2025'!$A:$H,8,0) -> #N/A | T102: =VLOOKUP(G102,'Seismic Springs 2025'!$A:$I,9,0) -> #N/A | U102: =T102*K102 -> #N/A
A103: 93055492 | B103: NK 80-180/128 | C103: 0.75 | D103: 4 | L103: 4421.75 | M103: =L103/2 -> 2210.875 | R103: =VLOOKUP(E103,'Inertia Bases 2025'!$A:$H,8,0) -> #N/A | T103: =VLOOKUP(G103,'Seismic Springs 2025'!$A:$I,9,0) -> #N/A | U103: =T103*K103 -> #N/A
A104: 93055493 | B104: NK 80-225/225 | C104: 55 | D104: 2 | L104: 17535.98 | M104: =L104/2 -> 8767.99 | R104: =VLOOKUP(E104,'Inertia Bases 2025'!$A:$H,8,0) -> #N/A | T104: =VLOOKUP(G104,'Seismic Springs 2025'!$A:$I,9,0) -> #N/A | U104: =T104*K104 -> #N/A
A105: 93055494 | B105: NK 80-225/205 | C105: 45 | D105: 2 | L105: 16313.14 | M105: =L105/2 -> 8156.57 | R105: =VLOOKUP(E105,'Inertia Bases 2025'!$A:$H,8,0) -> #N/A | T105: =VLOOKUP(G105,'Seismic Springs 2025'!$A:$I,9,0) -> #N/A | U105: =T105*K105 -> #N/A
A106: 93055495 | B106: NK 80-225/193 | C106: 37 | D106: 2 | L106: 12246.84 | M106: =L106/2 -> 6123.42 | R106: =VLOOKUP(E106,'Inertia Bases 2025'!$A:$H,8,0) -> #N/A | T106: =VLOOKUP(G106,'Seismic Springs 2025'!$A:$I,9,0) -> #N/A | U106: =T106*K106 -> #N/A
...

Sheet CR BOM
A1: Item No | B1: Name | C1: Pump List | D1: Pump Nett | E1: IP-56 Nett | F1: IP-66 Nett | G1: Base Nett | H1: Inertia SKU | I1: Inertia Size | J1: Inertia Nett | K1: RM Nett | L1: Mount Qty | M1: RM Total | N1: Seismic SKU | O1: Seismic Name | P1: Seismic Qty | Q1: Seismic Total
A2: 92900978 | B2: CR1-10 | C2: 1811 | D2: 905.5 | G2: 520 | K2: 11.83 | L2: 4 | M2: =K2*L2 -> 47.32
A3: 92901041 | B3: CR1-10 | C3: 1902 | D3: 951 | G3: 520 | K3: 11.83 | L3: 4 | M3: =K3*L3 -> 47.32
A4: 96516180 | B4: CR1-10 | C4: 1694 | D4: 847 | G4: 520 | K4: 11.83 | L4: 4 | M4: =K4*L4 -> 47.32
A5: 96516246 | B5: CR1-10 | C5: 1784 | D5: 892 | G5: 520 | K5: 11.83 | L5: 4 | M5: =K5*L5 -> 47.32
A6: 92900981 | B6: CR1-11 | C6: 1888 | D6: 944 | G6: 520 | K6: 11.83 | L6: 4 | M6: =K6*L6 -> 47.32
A7: 92901044 | B7: CR1-11 | C7: 1979 | D7: 989.5 | G7: 520 | K7: 11.83 | L7: 4 | M7: =K7*L7 -> 47.32
A8: 96516181 | B8: CR1-11 | C8: 1771 | D8: 885.5 | G8: 520 | K8: 11.83 | L8: 4 | M8: =K8*L8 -> 47.32
A9: 96516247 | B9: CR1-11 | C9: 1861 | D9: 930.5 | G9: 520 | K9: 11.83 | L9: 4 | M9: =K9*L9 -> 47.32
A10: 92900982 | B10: CR1-12 | C10: 2060 | D10: 1030 | G10: 520 | K10: 11.83 | L10: 4 | M10: =K10*L10 -> 47.32
A11: 92901045 | B11: CR1-12 | C11: 2150 | D11: 1075 | G11: 520 | K11: 11.83 | L11: 4 | M11: =K11*L11 -> 47.32
A12: 96516183 | B12: CR1-12 | C12: 1849 | D12: 924.5 | G12: 520 | K12: 11.83 | L12: 4 | M12: =K12*L12 -> 47.32
A13: 96516248 | B13: CR1-12 | C13: 1939 | D13: 969.5 | G13: 520 | K13: 11.83 | L13: 4 | M13: =K13*L13 -> 47.32
... A95: 92959626 | B95: CR10-5 | C95: 3538 | D95: 1769 | G95: 520 | K95: 11.83 | L95: 4 | M95: =K95*L95 -> 47.32
A96: 96500967 | B96: CR10-5 | C96: 3045 | D96: 1522.5 | F96: 135 | G96: 520 | K96: 11.83 | L96: 4 | M96: =K96*L96 -> 47.32
A97: 92959628 | B97: CR10-6 | C97: 3373 | D97: 1686.5 | G97: 520 | K97: 11.83 | L97: 4 | M97: =K97*L97 -> 47.32
A98: 96500968 | B98: CR10-6 | C98: 3209 | D98: 1604.5 | G98: 520 | K98: 11.83 | L98: 4 | M98: =K98*L98 -> 47.32
A99: 96500969 | B99: CR10-7 | C99: 3535 | D99: 1767.5 | G99: 520 | K99: 11.83 | L99: 4 | M99: =K99*L99 -> 47.32
A100: 96500970 | B100: CR10-8 | C100: 3699 | D100: 1849.5 | G100: 520 | K100: 11.83 | L100: 4 | M100: =K100*L100 -> 47.32
A101: 96500971 | B101: CR10-9 | C101: 3870 | D101: 1935 | G101: 520 | K101: 11.83 | L101: 4 | M101: =K101*L101 -> 47.32
A102: 99142431 | B102: CR125-1 | C102: 11052 | D102: 5526 | M102: =K102*L102 -> 0
A103: 99142574 | B103: CR125-2 | C103: 18036 | D103: 9018 | M103: =K103*L103 -> 0
A104: 99142573 | B104: CR125-2-1 | C104: 16127 | D104: 8063.5 | M104: =K104*L104 -> 0
A105: 99142432 | B105: CR125-2-2 | C105: 13765 | D105: 6882.5 | M105: =K105*L105 -> 0
A106: 99751480 | B106: CR125-3 | C106: 19973 | D106: 9986.5 | M106: =K106*L106 -> 0
A107: 99751479 | B107: CR125-3-1 | C107: 19342 | D107: 9671 | M107: =K107*L107 -> 0
A108: 99751483 | B108: CR125-4 | C108: 26409 | D108: 13204.5 | M108: =K108*L108 -> 0
A109: 99751482 | B109: CR125-4-2 | C109: 20861 | D109: 10430.5 | M109: =K109*L109 -> 0
A110: 99751486 | B110: CR125-5 | C110: 32401 | D110: 16200.5 | M110: =K110*L110 -> 0
A111: 92959640 | B111: CR15-1 | C111: 2959 | D111: 1479.5 | G111: 520 | K111: 11.83 | L111: 4 | M111: =K111*L111 -> 47.32
A112: 96501697 | B112: CR15-1 | C112: 2622 | D112: 1311 | G112: 520 | K112: 11.83 | L112: 4 | M112: =K112*L112 -> 47.32
A113: 96501901 | B113: CR15-10 | C113: 8141 | D113: 4070.5 | G113: 520 | K113: 11.83 | L113: 4 | M113: =K113*L113 -> 47.32
A114: 96501902 | B114: CR15-12 | C114: 8579 | D114: 4289.5 | G114: 520 | K114: 11.83 | L114: 4 | M114: =K114*L114 -> 47.32
A115: 96501903 | B115: CR15-14 | C115: 9025 | D115: 4512.5 | G115: 520 | K115: 11.83 | L115: 4 | M115: =K115*L115 -> 47.32
A116: 96501904 | B116: CR15-17 | C116: 11540 | D116: 5770 | G116: 520 | K116: 11.83 | L116: 4 | M116: =K116*L116 -> 47.32
A117: 92959642 | B117: CR15-2 | C117: 3795 | D117: 1897.5 | G117: 520 | K117: 11.83 | L117: 4 | M117: =K117*L117 -> 47.32
A118: 96501698 | B118: CR15-2 | C118: 3305 | D118: 1652.5 | G118: 520 | K118: 11.83 | L118: 4 | M118: =K118*L118 -> 47.32
A119: 96501699 | B119: CR15-3 | C119: 3820 | D119: 1910 | F119: 62 | G119: 520 | K119: 11.83 | L119: 4 | M119: =K119*L119 -> 47.32
A120: 96501895 | B120: CR15-4 | C120: 4437 | D120: 2218.5 | G120: 520 | K120: 11.83 | L120: 4 | M120: =K120*L120 -> 47.32
A121: 96501896 | B121: CR15-5 | C121: 4657 | D121: 2328.5 | G121: 520 | K121: 11.83 | L121: 4 | M121: =K121*L121 -> 47.32
A122: 96501897 | B122: CR15-6 | C122: 5541 | D122: 2770.5 | G122: 520 | K122: 11.83 | L122: 4 | M122: =K122*L122 -> 47.32
A123: 96501898 | B123: CR15-7 | C123: 5761 | D123: 2880.5 | G123: 520 | K123: 11.83 | L123: 4 | M123: =K123*L123 -> 47.32
A124: 96501899 | B124: CR15-8 | C124: 6704 | D124: 3352 | G124: 520 | K124: 11.83 | L124: 4 | M124: =K124*L124 -> 47.32
A125: 96501900 | B125: CR15-9 | C125: 6929 | D125: 3464.5 | G125: 520 | K125: 11.83 | L125: 4 | M125: =K125*L125 -> 47.32
A126: 99143255 | B126: CR155-1 | C126: 13829 | D126: 6914.5 | M126: =K126*L126 -> 0
A127: 99143254 | B127: CR155-1-1 | C127: 11103 | D127: 5551.5 | M127: =K127*L127 -> 0
A128: 99751487 | B128: CR155-2 | C128: 17990 | D128: 8995 | M128: =K128*L128 -> 0
A129: 99143257 | B129: CR155-2-2 | C129: 18119 | D129: 9059.5 | M129: =K129*L129 -> 0
A130: 99751489 | B130: CR155-3 | C130: 26474 | D130: 13237 | M130: =K130*L130 -> 0
A131: 99751488 | B131: CR155-3-2 | C131: 20912 | D131: 10456 | M131: =K131*L131 -> 0
A132: 99751490 | B132: CR155-4-1 | C132: 32482 | D132: 16241 | M132: =K132*L132 -> 0
A133: 99143712 | B133: CR185-1 | C133: 20926 | D133: 10463 | M133: =K133*L133 -> 0
A134: 99143711 | B134: CR185-1-1 | C134: 19065 | D134: 9532.5 | M134: =K134*L134 -> 0
A135: 92501238 | B135: CR185-2 | C135: 33017 | D135: 16508.5 | M135: =K135*L135 -> 0
A136: 92501226 | B136: CR185-2-2 | C136: 26594 | D136: 13297 | M136: =K136*L136 -> 0
A137: 92501272 | B137: CR185-3 | C137: 47771 | D137: 23885.5 | M137: =K137*L137 -> 0
... A148: 92501925 | B148: CR185-8-3 | C148: 99251 | D148: 49625.5 | M148: =K148*L148 -> 0
A149: 92899728 | B149: CR1S-10 | C149: 1707 | D149: 853.5 | G149: 520 | K149: 11.83 | L149: 4 | M149: =K149*L149 -> 47.32
A150: 92899792 | B150: CR1S-10 | C150: 1793 | D150: 896.5 | G150: 520 | K150: 11.83 | L150: 4 | M150: =K150*L150 -> 47.32
A151: 96515560 | B151: CR1S-10 | C151: 1618 | D151: 809 | G151: 520 | K151: 11.83 | L151: 4 | M151: =K151*L151 -> 47.32
A152: 96515658 | B152: CR1S-10 | C152: 1703 | D152: 851.5 | G152: 520 | K152: 11.83 | L152: 4 | M152: =K152*L152 -> 47.32
A153: 92899729 | B153: CR1S-11 | C153: 1754 | D153: 877 | G153: 520 | K153: 11.83 | L153: 4 | M153: =K153*L153 -> 47.32
A154: 92899793 | B154: CR1S-11 | C154: 1841 | D154: 920.5 | G154: 520 | K154: 11.83 | L154: 4 | M154: =K154*L154 -> 47.32
A155: 96515561 | B155: CR1S-11 | C155: 1666 | D155: 833 | G155: 520 | K155: 11.83 | L155: 4 | M155: =K155*L155 -> 47.32
A156: 96515660 | B156: CR1S-11 | C156: 1751 | D156: 875.5 | G156: 520 | K156: 11.83 | L156: 4 | M156: =K156*L156 -> 47.32
A157: 92899730 | B157: CR1S-12 | C157: 1801 | D157: 900.5 | G157: 520 | K157: 11.83 | L157: 4 | M157: =K157*L157 -> 47.32
A158: 92899794 | B158: CR1S-12 | C158: 1888 | D158: 944 | G158: 520 | K158: 11.83 | L158: 4 | M158: =K158*L158 -> 47.32
A159: 96515562 | B159: CR1S-12 | C159: 1712 | D159: 856 | G159: 520 | K159: 11.83 | L159: 4 | M159: =K159*L159 -> 47.32
A160: 96515661 | B160: CR1S-12 | C160: 1798 | D160: 899 | G160: 520 | K160: 11.83 | L160: 4 | M160: =K160*L160 -> 47.32
... A244: 96500514 | B244: CR20-8 | C244: 8551 | D244: 4275.5 | G244: 520 | K244: 11.83 | L244: 4 | M244: =K244*L244 -> 47.32
A245: 92541252 | B245: CR215-1 | C245: 26594 | D245: 13297 | M245: =K245*L245 -> 0
A246: 99144179 | B246: CR215-1-1 | C246: 20926 | D246: 10463 | M246: =K246*L246 -> 0
A247: 92541255 | B247: CR215-2 | C247: 47771 | D247: 23885.5 | M247: =K247*L247 -> 0
A248: 92541254 | B248: CR215-2-1 | C248: 39968 | D248: 19984 | M248: =K248*L248 -> 0
A249: 92541253 | B249: CR215-2-2 | C249: 33017 | D249: 16508.5 | M249: =K249*L249 -> 0
A250: 92541258 | B250: CR215-3 | C250: 56998 | D250: 28499 | M250: =K250*L250 -> 0
A251: 92541256 | B251: CR215-3-2 | C251: 48977 | D251: 24488.5 | M251: =K251*L251 -> 0
A252: 92541261 | B252: CR215-4 | C252: 71342 | D252: 35671 | M252: =K252*L252 -> 0
A253: 92541260 | B253: CR215-4-2 | C253: 63958 | D253: 31979 | M253: =K253*L253 -> 0
A254: 92541263 | B254: CR215-5 | C254: 84115 | D254: 42057.5 | M254: =K254*L254 -> 0
A255: 92541262 | B255: CR215-5-2 | C255: 72548 | D255: 36274 | M255: =K255*L255 -> 0
A256: 92541266 | B256: CR215-6 | C256: 99251 | D256: 49625.5 | G256: 520 | K256: 11.83 | L256: 4 | M256: =K256*L256 -> 47.32
A257: 92541265 | B257: CR215-6-3 | C257: 85321 | D257: 42660.5 | G257: 520 | K257: 11.83 | L257: 4 | M257: =K257*L257 -> 47.32
A258: 92541267 | B258: CR215-7-2 | C258: 100457 | D258: 50228.5 | G258: 520 | K258: 11.83 | L258: 4 | M258: =K258*L258 -> 47.32
A259: 92541463 | B259: CR255-1 | C259: 33025 | D259: 16512.5 | G259: 520 | K259: 11.83 | L259: 4 | M259: =K259*L259 -> 47.32
A260: 92541462 | B260: CR255-1-1 | C260: 22224 | D260: 11112 | G260: 520 | K260: 11.83 | L260: 4 | M260: =K260*L260 -> 47.32
A261: 92541465 | B261: CR255-2 | C261: 48989 | D261: 24494.5 | G261: 520 | K261: 11.83 | L261: 4 | M261: =K261*L261 -> 47.32
A262: 92541464 | B262: CR255-2-2 | C262: 39978 | D262: 19989 | G262: 520 | K262: 11.83 | L262: 4 | M262: =K262*L262 -> 47.32
A263: 92541467 | B263: CR255-3 | C263: 63974 | D263: 31987 | G263: 520 | K263: 11.83 | L263: 4 | M263: =K263*L263 -> 47.32
A264: 92541466 | B264: CR255-3-2 | C264: 57013 | D264: 28506.5 | G264: 520 | K264: 11.83 | L264: 4 | M264: =K264*L264 -> 47.32
A265: 92541469 | B265: CR255-4 | C265: 84137 | D265: 42068.5 | G265: 520 | K265: 11.83 | L265: 4 | M265: =K265*L265 -> 47.32
A266: 92541468 | B266: CR255-4-2 | C266: 72567 | D266: 36283.5 | G266: 520 | K266: 11.83 | L266: 4 | M266: =K266*L266 -> 47.32
A267: 92541481 | B267: CR255-5 | C267: 99277 | D267: 49638.5 | G267: 520 | K267: 11.83 | L267: 4 | M267: =K267*L267 -> 47.32
... A346: 96516656 | B346: CR3-9 | C346: 1889 | D346: 944.5 | G346: 520 | K346: 11.83 | L346: 4 | M346: =K346*L346 -> 47.32
A347: 96121951 | B347: CR32-1 | C347: 4032 | D347: 2016 | M347: =K347*L347 -> 0
A348: 96121950 | B348: CR32-1-1 | C348: 3776 | D348: 1888 | M348: =K348*L348 -> 0
A349: 96122025 | B349: CR32-10 | C349: 16333 | D349: 8166.5 | M349: =K349*L349 -> 0
A350: 96122024 | B350: CR32-10-2 | C350: 16333 | D350: 8166.5 | M350: =K350*L350 -> 0
A351: 96122027 | B351: CR32-11 | C351: 18318 | D351: 9159 | M351: =K351*L351 -> 0
A352: 96122026 | B352: CR32-11-2 | C352: 18318 | D352: 9159 | M352: =K352*L352 -> 0
...

Sheet CRE BOM
A1: Item No | B1: Name | C1: Pump List | D1: Pump Nett | E1: IP-56 Nett | F1: IP-66 Nett | G1: Base Nett | H1: Inertia SKU | I1: Inertia Size | J1: Inertia Nett | K1: RM Nett | L1: Mount Qty | M1: RM Total | N1: Seismic SKU | O1: Seismic Name | P1: Seismic Qty | Q1: Seismic Total
A2: 92959143 | B2: CRE95-1 | C2: 20908 | D2: 10454
A3: 92959148 | B3: CRE95-2-2 | C3: 24730 | D3: 12365
A4: 92959162 | B4: CRE95-2-1 | C4: 27759 | D4: 13879.5
A5: 92959181 | B5: CRE125-1-1 | C5: 19410 | D5: 9705
A6: 92959185 | B6: CRE125-1 | C6: 24927 | D6: 12463.5
A7: 92959225 | B7: CRE155-1-1 | C7: 23923 | D7: 11961.5
A8: 92962276 | B8: CRE32-4 | C8: 20744 | D8: 10372
A9: 92962277 | B9: CRE32-5-2 | C9: 21331 | D9: 10665.5
A10: 92962278 | B10: CRE32-5 | C10: 23215 | D10: 11607.5
A11: 92962279 | B11: CRE32-6 | C11: 23802 | D11: 11901
A12: 92962280 | B12: CRE32-6 | C12: 25155 | D12: 12577.5
A13: 92962281 | B13: CRE32-7 | C13: 27757 | D13: 13878.5
... A149: 99707619 | B149: CRE95-1-1 | C149: 16712 | D149: 8356

Sheet CRI BOM
A1: Item No | B1: Name | C1: Pump List | D1: Pump Nett | E1: IP-56 Nett | F1: IP-66 Nett | G1: Base Nett | H1: Inertia SKU | I1: Inertia Size | J1: Inertia Nett | K1: RM Nett | L1: Mount Qty | M1: RM Total | N1: Seismic SKU | O1: Seismic Name | P1: Seismic Qty | Q1: Seismic Total
A2: 92899847 | B2: CRI1S-2 | C2: 1526 | D2: 763 | G2: 520 | K2: 11.83 | L2: 4 | M2: =K2*L2 -> 47.32
A3: 92899848 | B3: CRI1S-3 | C3: 1574 | D3: 787 | G3: 520 | K3: 11.83 | L3: 4 | M3: =K3*L3 -> 47.32
A4: 92899849 | B4: CRI1S-4 | C4: 1621 | D4: 810.5 | G4: 520 | K4: 11.83 | L4: 4 | M4: =K4*L4 -> 47.32
A5: 92899850 | B5: CRI1S-5 | C5: 1668 | D5: 834 | G5: 520 | K5: 11.83 | L5: 4 | M5: =K5*L5 -> 47.32
A6: 92899851 | B6: CRI1S-6 | C6: 1716 | D6: 858 | G6: 520 | K6: 11.83 | L6: 4 | M6: =K6*L6 -> 47.32
A7: 92899852 | B7: CRI1S-7 | C7: 1763 | D7: 881.5 | G7: 520 | K7: 11.83 | L7: 4 | M7: =K7*L7 -> 47.32
A8: 92899853 | B8: CRI1S-8 | C8: 1812 | D8: 906 | G8: 520 | K8: 11.83 | L8: 4 | M8: =K8*L8 -> 47.32
A9: 92899854 | B9: CRI1S-9 | C9: 1859 | D9: 929.5 | G9: 520 | K9: 11.83 | L9: 4 | M9: =K9*L9 -> 47.32
A10: 92899855 | B10: CRI1S-10 | C10: 1904 | D10: 952 | G10: 520 | K10: 11.83 | L10: 4 | M10: =K10*L10 -> 47.32
A11: 92899856 | B11: CRI1S-11 | C11: 1952 | D11: 976 | G11: 520 | K11: 11.83 | L11: 4 | M11: =K11*L11 -> 47.32
A12: 92899857 | B12: CRI1S-12 | C12: 1999 | D12: 999.5 | G12: 520 | K12: 11.83 | L12: 4 | M12: =K12*L12 -> 47.32
A13: 92899858 | B13: CRI1S-13 | C13: 2047 | D13: 1023.5 | G13: 520 | K13: 11.83 | L13: 4 | M13: =K13*L13 -> 47.32
... A159: 92902523 | B159: CRI5-16 | C159: 3706 | D159: 1853 | G159: 520 | K159: 11.83 | L159: 4 | M159: =K159*L159 -> 47.32
A160: 92982745 | B160: CRI20-2 | C160: 4049 | D160: 2024.5
A161: 92982747 | B161: CRI10-6 | C161: 3988 | D161: 1994 | G161: 520 | K161: 11.83 | L161: 4 | M161: =K161*L161 -> 47.32
A162: 92982748 | B162: CRI10-5 | C162: 3819 | D162: 1909.5 | G162: 520 | K162: 11.83 | L162: 4 | M162: =K162*L162 -> 47.32
A163: 92982760 | B163: CRI15-2 | C163: 4133 | D163: 2066.5 | G163: 520 | K163: 11.83 | L163: 4 | M163: =K163*L163 -> 47.32
A164: 92983552 | B164: CRI10-1 | C164: 2435 | D164: 1217.5 | G164: 520 | K164: 11.83 | L164: 4 | M164: =K164*L164 -> 47.32
A165: 92983556 | B165: CRI10-2 | C165: 2639 | D165: 1319.5 | G165: 520 | K165: 11.83 | L165: 4 | M165: =K165*L165 -> 47.32
A166: 92983561 | B166: CRI10-3 | C166: 3121 | D166: 1560.5 | G166: 520 | K166: 11.83 | L166: 4 | M166: =K166*L166 -> 47.32
A167: 92983566 | B167: CRI10-4 | C167: 3535 | D167: 1767.5 | G167: 520 | K167: 11.83 | L167: 4 | M167: =K167*L167 -> 47.32
A168: 92983568 | B168: CRI15-1 | C168: 3335 | D168: 1667.5 | G168: 520 | K168: 11.83 | L168: 4 | M168: =K168*L168 -> 47.32
A169: 92983569 | B169: CRI20-1 | C169: 3255 | D169: 1627.5
A170: 96500345 | B170: CRI20-1 | C170: 2943 | D170: 1471.5
A171: 96500346 | B171: CRI20-2 | C171: 3595 | D171: 1797.5
A172: 96500526 | B172: CRI20-3 | C172: 4830 | D172: 2415
A173: 96500527 | B173: CRI20-4 | C173: 5863 | D173: 2931.5
A174: 96500528 | B174: CRI20-5 | C174: 6088 | D174: 3044
A175: 96500529 | B175: CRI20-6 | C175: 7026 | D175: 3513
A176: 96500530 | B176: CRI20-7 | C176: 7255 | D176: 3627.5
A177: 96500531 | B177: CRI20-8 | C177: 9001 | D177: 4500.5
A178: 96500532 | B178: CRI20-10 | C178: 9456 | D178: 4728
A179: 96500533 | B179: CRI20-12 | C179: 11495 | D179: 5747.5
A180: 96500534 | B180: CRI20-14 | C180: 12045 | D180: 6022.5
A181: 96500535 | B181: CRI20-17 | C181: 14213 | D181: 7106.5
A182: 96500992 | B182: CRI10-1 | C182: 2327 | D182: 1163.5 | G182: 520 | K182: 11.83 | L182: 4 | M182: =K182*L182 -> 47.32
A183: 96500993 | B183: CRI10-2 | C183: 2411 | D183: 1205.5 | G183: 520 | K183: 11.83 | L183: 4 | M183: =K183*L183 -> 47.32
A184: 96500994 | B184: CRI10-3 | C184: 2762 | D184: 1381 | G184: 520 | K184: 11.83 | L184: 4 | M184: =K184*L184 -> 47.32
A185: 96500995 | B185: CRI10-4 | C185: 3063 | D185: 1531.5 | G185: 520 | K185: 11.83 | L185: 4 | M185: =K185*L185 -> 47.32
A186: 96500996 | B186: CRI10-5 | C186: 3306 | D186: 1653 | G186: 520 | K186: 11.83 | L186: 4 | M186: =K186*L186 -> 47.32
A187: 96500997 | B187: CRI10-6 | C187: 3472 | D187: 1736 | G187: 520 | K187: 11.83 | L187: 4 | M187: =K187*L187 -> 47.32
A188: 96500998 | B188: CRI10-7 | C188: 3742 | D188: 1871 | G188: 520 | K188: 11.83 | L188: 4 | M188: =K188*L188 -> 47.32
A189: 96500999 | B189: CRI10-8 | C189: 3903 | D189: 1951.5 | G189: 520 | K189: 11.83 | L189: 4 | M189: =K189*L189 -> 47.32
A190: 96501000 | B190: CRI10-9 | C190: 4063 | D190: 2031.5 | G190: 520 | K190: 11.83 | L190: 4 | M190: =K190*L190 -> 47.32
A191: 96501242 | B191: CRI10-10 | C191: 4624 | D191: 2312 | G191: 520 | K191: 11.83 | L191: 4 | M191: =K191*L191 -> 47.32
A192: 96501243 | B192: CRI10-12 | C192: 4944 | D192: 2472 | G192: 520 | K192: 11.83 | L192: 4 | M192: =K192*L192 -> 47.32
A193: 96501244 | B193: CRI10-14 | C193: 5747 | D193: 2873.5 | G193: 520 | K193: 11.83 | L193: 4 | M193: =K193*L193 -> 47.32
... A390: 96528156 | B390: CRI1-6 | C390: 1707 | D390: 853.5 | G390: 520 | K390: 11.83 | L390: 4 | M390: =K390*L390 -> 47.32
A391: 96905389 | B391: CRI45-2-2 | C391: 7112 | D391: 3556
A392: 97513866 | B392: CRI32-2 | C392: 5787 | D392: 2893.5
A393: 97725468 | B393: CRI32-1-1 | C393: 4003 | D393: 2001.5
A394: 97725469 | B394: CRI32-1 | C394: 4276 | D394: 2138
A395: 97725470 | B395: CRI32-2-2 | C395: 4941 | D395: 2470.5
A396: 97725501 | B396: CRI32-3-2 | C396: 7275 | D396: 3637.5
A397: 97725502 | B397: CRI32-3 | C397: 7275 | D397: 3637.5
A398: 97725503 | B398: CRI32-4-2 | C398: 9030 | D398: 4515
A399: 97725504 | B399: CRI32-4 | C399: 9030 | D399: 4515
A400: 97725505 | B400: CRI32-5-2 | C400: 11354 | D400: 5677
A401: 97725506 | B401: CRI32-5 | C401: 11354 | D401: 5677
A402: 97725507 | B402: CRI32-6-2 | C402: 11972 | D402: 5986
... A465: 99736815 | B465: CRI45-6-2 | C465: 19053 | D465: 9526.5

Sheet CRIE BOM
A1: Item No | B1: Name | C1: Pump List | D1: Pump Nett | E1: IP-56 Nett | F1: IP-66 Nett | G1: Base Nett | H1: Inertia SKU | I1: Inertia Size | J1: Inertia Nett | K1: RM Nett | L1: Mount Qty | M1: RM Total | N1: Seismic SKU | O1: Seismic Name | P1: Seismic Qty | Q1: Seismic Total
A2: 93150535 | B2: CRIE1-3 | C2: 3015 | D2: 1507.5
A3: 93150536 | B3: CRIE1-4 | C3: 3086 | D3: 1543
A4: 93150537 | B4: CRIE1-5 | C4: 3241 | D4: 1620.5
A5: 93150538 | B5: CRIE1-6 | C5: 3307 | D5: 1653.5
A6: 93150539 | B6: CRIE1-6 | C6: 3377 | D6: 1688.5
A7: 93150550 | B7: CRIE1-9 | C7: 3607 | D7: 1803.5
A8: 93150552 | B8: CRIE1-12 | C8: 4462 | D8: 2231
A9: 93150553 | B9: CRIE1-13 | C9: 4171 | D9: 2085.5
A10: 93150554 | B10: CRIE1-17 | C10: 5070 | D10: 2535
A11: 93150555 | B11: CRIE3-2 | C11: 2989 | D11: 1494.5
A12: 93150556 | B12: CRIE3-3 | C12: 3111 | D12: 1555.5
A13: 93150558 | B13: CRIE3-4 | C13: 3247 | D13: 1623.5
... A104: 99852769 | B104: CRIE64-1 | C104: 18867 | D104: 9433.5

Sheet CRN BOM
A1: Item No | B1: Name | C1: Pump List | D1: Pump Nett | E1: IP-56 Nett | F1: IP-66 Nett | G1: Base Nett | H1: Inertia SKU | I1: Inertia Size | J1: Inertia Nett | K1: RM Nett | L1: Mount Qty | M1: RM Total | N1: Seismic SKU | O1: Seismic Name | P1: Seismic Qty | Q1: Seismic Total
A2: 92501229 | B2: CRN185-2-2 | C2: 50110 | D2: 25055
A3: 92501241 | B3: CRN185-2 | C3: 62221 | D3: 31110.5
A4: 92501258 | B4: CRN185-3-3 | C4: 72528 | D4: 36264
A5: 92501275 | B5: CRN185-3 | C5: 86857 | D5: 43428.5
A6: 92501288 | B6: CRN185-4-3 | C6: 88878 | D6: 44439
A7: 92501326 | B7: CRN185-4 | C7: 103435 | D7: 51717.5
A8: 92501790 | B8: CRN185-5-3 | C8: 111594 | D8: 55797
A9: 92501806 | B9: CRN185-5 | C9: 111594 | D9: 55797
A10: 92501843 | B10: CRN185-6-3 | C10: 126584 | D10: 63292
A11: 92501857 | B11: CRN185-6 | C11: 126584 | D11: 63292
A12: 92501881 | B12: CRN185-7-3 | C12: 146854 | D12: 73427
A13: 92501906 | B13: CRN185-7 | C13: 146854 | D13: 73427
... A554: 99751655 | B554: CRN155-8-2 | C554: 87969 | D554: 43984.5

Sheet CRNE BOM
A1: Item No | B1: Name | C1: Pump List | D1: Pump Nett | E1: IP-56 Nett | F1: IP-66 Nett | G1: Base Nett | H1: Inertia SKU | I1: Inertia Size | J1: Inertia Nett | K1: RM Nett | L1: Mount Qty | M1: RM Total | N1: Seismic SKU | O1: Seismic Name | P1: Seismic Qty | Q1: Seismic Total
A2: 92959167 | B2: CRNE95-1 | C2: 31419 | D2: 15709.5
A3: 92959172 | B3: CRNE95-2-2 | C3: 36195 | D3: 18097.5
A4: 92959178 | B4: CRNE95-2-1 | C4: 40640 | D4: 20320
A5: 92959207 | B5: CRNE125-1-1 | C5: 29447 | D5: 14723.5
A6: 92959217 | B6: CRNE125-1 | C6: 36927 | D6: 18463.5
A7: 92959229 | B7: CRNE155-1-1 | C7: 36450 | D7: 18225
A8: 92962319 | B8: CRNE32-4 | C8: 29534 | D8: 14767
A9: 92962320 | B9: CRNE32-5-2 | C9: 30322 | D9: 15161
A10: 92962321 | B10: CRNE32-5 | C10: 33251 | D10: 16625.5
A11: 92962322 | B11: CRNE32-6 | C11: 34039 | D11: 17019.5
A12: 92962323 | B12: CRNE32-6 | C12: 35685 | D12: 17842.5
A13: 92962324 | B13: CRNE32-7 | C13: 38856 | D13: 19428
... A117: 99315835 | B117: CRNE32-2-1 | C117: 15166 | D117: 7583
A118: 99655972 | B118: CRNE95-1-1 | C118: 24731 | D118: 12365.5 | H118: 99102010 | I118: 620 x 620 x 310 | J118: 646.67 | N118: 92932673 | O118: CSM-16 | P118: 4 | Q118: 238.08

Sheet TP BOM
A1: Item No | B1: Name | C1: Base | D1: RM SKU | E1: RM Name | F1: Pump List | G1: Pump Nett | H1: IP-56 Nett | I1: IP-66 Nett | J1: Base Nett | K1: Inertia SKU | L1: Inertia Size | M1: Rubber Mount Nett | N1: Seismic Spring SKU | O1: Seismic Spring Name | P1: Mount Qty | Q1: RM Total Nett | R1: Seismic Spring Nett | S1: Seis Total Nett | T1: Inertia Nett
A2: 96086842 | B2: TP 40-240/2 A-F-B-BQQE-IX1 | F2: 4703 | G2: =CEILING(F2*0.55,1) -> 2587 | R2: =VLOOKUP(N2,'Seismic Springs 2025'!$A:$I,9,0) -> #N/A | S2: =P2*R2 -> #N/A | T2: =VLOOKUP(K2,'Inertia Bases 2025'!$A:$H,8,0) -> #N/A
A3: 96086843 | B3: TP 40-300/2 A-F-B-BQQE-JX1 | F3: 4942 | G3: =CEILING(F3*0.55,1) -> 2719 | R3: =VLOOKUP(N3,'Seismic Springs 2025'!$A:$I,9,0) -> #N/A | S3: =P3*R3 -> #N/A | T3: =VLOOKUP(K3,'Inertia Bases 2025'!$A:$H,8,0) -> #N/A
A4: 96087029 | B4: TP 50-190/2 A-F-B-BQQE-HX1 | D4: 92996501 | E4: NR1 - Yellow | F4: 4328 | G4: =CEILING(F4*0.55,1) -> 2381 | I4: =CEILING(2505.68-G4,1) -> 125 | J4: 530 | M4: 11.7 | P4: 4 | Q4: =M4*P4 -> 46.8 | R4: =VLOOKUP(N4,'Seismic Springs 2025'!$A:$I,9,0) -> #N/A | S4: =P4*R4 -> #N/A | T4: =VLOOKUP(K4,'Inertia Bases 2025'!$A:$H,8,0) -> #N/A
A5: 96087030 | B5: TP 50-240/2 A-F-B-BQQE-IX1 | F5: 4503 | G5: =CEILING(F5*0.55,1) -> 2477 | R5: =VLOOKUP(N5,'Seismic Springs 2025'!$A:$I,9,0) -> #N/A | S5: =P5*R5 -> #N/A | T5: =VLOOKUP(K5,'Inertia Bases 2025'!$A:$H,8,0) -> #N/A
A6: 96087031 | B6: TP 50-290/2 A-F-B-BQQE-JX1 | F6: 4766 | G6: =CEILING(F6*0.55,1) -> 2622 | R6: =VLOOKUP(N6,'Seismic Springs 2025'!$A:$I,9,0) -> #N/A | S6: =P6*R6 -> #N/A | T6: =VLOOKUP(K6,'Inertia Bases 2025'!$A:$H,8,0) -> #N/A
A7: 96087139 | B7: TP 50-190/4 A-F-B-BQQE-IX3 | F7: 6238 | G7: =CEILING(F7*0.55,1) -> 3431 | R7: =VLOOKUP(N7,'Seismic Springs 2025'!$A:$I,9,0) -> #N/A | S7: =P7*R7 -> #N/A | T7: =VLOOKUP(K7,'Inertia Bases 2025'!$A:$H,8,0) -> #N/A
A8: 96087140 | B8: TP 50-230/4 A-F-B-BQQE-JX3 | F8: 6644 | G8: =CEILING(F8*0.55,1) -> 3655 | R8: =VLOOKUP(N8,'Seismic Springs 2025'!$A:$I,9,0) -> #N/A | S8: =P8*R8 -> #N/A | T8: =VLOOKUP(K8,'Inertia Bases 2025'!$A:$H,8,0) -> #N/A
A9: 96087224 | B9: TP 50-360/2 A-F-B-BQQE-KX1 | F9: 5619 | G9: =CEILING(F9*0.55,1) -> 3091 | R9: =VLOOKUP(N9,'Seismic Springs 2025'!$A:$I,9,0) -> #N/A | S9: =P9*R9 -> #N/A | T9: =VLOOKUP(K9,'Inertia Bases 2025'!$A:$H,8,0) -> #N/A
A10: 96087225 | B10: TP 50-430/2 A-F-B-BQQE-LX1 | F10: 7205 | G10: =CEILING(F10*0.55,1) -> 3963 | R10: =VLOOKUP(N10,'Seismic Springs 2025'!$A:$I,9,0) -> #N/A | S10: =P10*R10 -> #N/A | T10: =VLOOKUP(K10,'Inertia Bases 2025'!$A:$H,8,0) -> #N/A
A11: 96087462 | B11: TP 65-150/4 A-F-B-BQQE-IX3 | F11: 6183 | G11: =CEILING(F11*0.55,1) -> 3401 | R11: =VLOOKUP(N11,'Seismic Springs 2025'!$A:$I,9,0) -> #N/A | S11: =P11*R11 -> #N/A | T11: =VLOOKUP(K11,'Inertia Bases 2025'!$A:$H,8,0) -> #N/A
A12: 96087463 | B12: TP 65-170/4 A-F-B-BQQE-JX3 | F12: 6398 | G12: =CEILING(F12*0.55,1) -> 3519 | R12: =VLOOKUP(N12,'Seismic Springs 2025'!$A:$I,9,0) -> #N/A | S12: =P12*R12 -> #N/A | T12: =VLOOKUP(K12,'Inertia Bases 2025'!$A:$H,8,0) -> #N/A
A13: 96087554 | B13: TP 65-340/2 A-F-B-BQQE-LX1 | F13: 7362 | G13: =CEILING(F13*0.55,1) -> 4050 | R13: =VLOOKUP(N13,'Seismic Springs 2025'!$A:$I,9,0) -> #N/A | S13: =P13*R13 -> #N/A | T13: =VLOOKUP(K13,'Inertia Bases 2025'!$A:$H,8,0) -> #N/A
A14: 96087555 | B14: TP 65-410/2 A-F-B-BQQE-MX1 | F14: 7682 | G14: =CEILING(F14*0.55,1) -> 4226 | R14: =VLOOKUP(N14,'Seismic Springs 2025'!$A:$I,9,0) -> #N/A | S14: =P14*R14 -> #N/A | T14: =VLOOKUP(K14,'Inertia Bases 2025'!$A:$H,8,0) -> #N/A
A15: 96087556 | B15: TP 65-460/2 A-F-B-BQQE-NX1 | F15: 11091 | G15: =CEILING(F15*0.55,1) -> 6101 | R15: =VLOOKUP(N15,'Seismic Springs 2025'!$A:$I,9,0) -> #N/A | S15: =P15*R15 -> #N/A | T15: =VLOOKUP(K15,'Inertia Bases 2025'!$A:$H,8,0) -> #N/A
A16: 96087557 | B16: TP 65-550/2 A-F-B-BQQE-OX1 | F16: 12763 | G16: =CEILING(F16*0.55,1) -> 7020 | R16: =VLOOKUP(N16,'Seismic Springs 2025'!$A:$I,9,0) -> #N/A | S16: =P16*R16 -> #N/A | T16: =VLOOKUP(K16,'Inertia Bases 2025'!$A:$H,8,0) -> #N/A
... A46: 96109344 | B46: TP 100-250/4 A-F-B-BQQE-NX3 | F46: 14054 | G46: =CEILING(F46*0.55,1) -> 7730 | R46: =VLOOKUP(N46,'Seismic Springs 2025'!$A:$I,9,0) -> #N/A | S46: =P46*R46 -> #N/A | T46: =VLOOKUP(K46,'Inertia Bases 2025'!$A:$H,8,0) -> #N/A
A47: 96109345 | B47: TP 100-330/4 A-F-B-BQQE-OX3 | F47: 16835 | G47: =CEILING(F47*0.55,1) -> 9260 | K47: 92513065 | L47: 1100 x 800 x 150 | N47: 91338157 | O47: CSM-17 | P47: 4 | R47: =VLOOKUP(N47,'Seismic Springs 2025'!$A:$I,9,0) -> 66.3 | S47: =P47*R47 -> 265.2 | T47: =VLOOKUP(K47,'Inertia Bases 2025'!$A:$H,8,0) -> 610.6
A48: 96109346 | B48: TP 100-370/4 A-F-B-BQQE-PX3 | F48: 19126 | G48: =CEILING(F48*0.55,1) -> 10520 | R48: =VLOOKUP(N48,'Seismic Springs 2025'!$A:$I,9,0) -> #N/A | S48: =P48*R48 -> #N/A | T48: =VLOOKUP(K48,'Inertia Bases 2025'!$A:$H,8,0) -> #N/A
A49: 97851334 | B49: TP 40-120/2 A-F-A-BQQE-DX1 | F49: 2365 | G49: =CEILING(F49*0.55,1) -> 1301 | R49: =VLOOKUP(N49,'Seismic Springs 2025'!$A:$I,9,0) -> #N/A | S49: =P49*R49 -> #N/A | T49: =VLOOKUP(K49,'Inertia Bases 2025'!$A:$H,8,0) -> #N/A
A50: 98066916 | B50: TP 40-230/2 A-F-A-BQQE-GX1 | F50: 2985 | G50: =CEILING(F50*0.55,1) -> 1642 | R50: =VLOOKUP(N50,'Seismic Springs 2025'!$A:$I,9,0) -> #N/A | S50: =P50*R50 -> #N/A | T50: =VLOOKUP(K50,'Inertia Bases 2025'!$A:$H,8,0) -> #N/A
A51: 98122409 | B51: TP 40-60/2 A-F-A-BQQE-CX1 | F51: 1881 | G51: =CEILING(F51*0.55,1) -> 1035 | R51: =VLOOKUP(N51,'Seismic Springs 2025'!$A:$I,9,0) -> #N/A | S51: =P51*R51 -> #N/A | T51: =VLOOKUP(K51,'Inertia Bases 2025'!$A:$H,8,0) -> #N/A
A52: 98133648 | B52: TP 50-180/2 A-F-A-BQQE-FX1 | F52: 3279 | G52: =CEILING(F52*0.55,1) -> 1804 | R52: =VLOOKUP(N52,'Seismic Springs 2025'!$A:$I,9,0) -> #N/A | S52: =P52*R52 -> #N/A | T52: =VLOOKUP(K52,'Inertia Bases 2025'!$A:$H,8,0) -> #N/A
A53: 98133671 | B53: TP 40-180/2 A-F-A-BQQE-EX1 | F53: 2801 | G53: =CEILING(F53*0.55,1) -> 1541 | R53: =VLOOKUP(N53,'Seismic Springs 2025'!$A:$I,9,0) -> #N/A | S53: =P53*R53 -> #N/A | T53: =VLOOKUP(K53,'Inertia Bases 2025'!$A:$H,8,0) -> #N/A
A54: 98182027 | B54: TP 50-60/2 A-F-A-BQQE-DX1 | F54: 2366 | G54: =CEILING(F54*0.55,1) -> 1302 | R54: =VLOOKUP(N54,'Seismic Springs 2025'!$A:$I,9,0) -> #N/A | S54: =P54*R54 -> #N/A | T54: =VLOOKUP(K54,'Inertia Bases 2025'!$A:$H,8,0) -> #N/A
A55: 98279255 | B55: TP 50-120/2 A-F-A-BQQE-FX1 | F55: 2903 | G55: =CEILING(F55*0.55,1) -> 1597 | R55: =VLOOKUP(N55,'Seismic Springs 2025'!$A:$I,9,0) -> #N/A | S55: =P55*R55 -> #N/A | T55: =VLOOKUP(K55,'Inertia Bases 2025'!$A:$H,8,0) -> #N/A
A56: 98294231 | B56: TP 40-190/2 A-F-A-BQQE-FX1 | F56: 2893 | G56: =CEILING(F56*0.55,1) -> 1592 | R56: =VLOOKUP(N56,'Seismic Springs 2025'!$A:$I,9,0) -> #N/A | S56: =P56*R56 -> #N/A | T56: =VLOOKUP(K56,'Inertia Bases 2025'!$A:$H,8,0) -> #N/A
A57: 98299122 | B57: TP 32-90/2 A-O-A-BQQE-DX1 | F57: 1978 | G57: =CEILING(F57*0.55,1) -> 1088 | R57: =VLOOKUP(N57,'Seismic Springs 2025'!$A:$I,9,0) -> #N/A | S57: =P57*R57 -> #N/A | T57: =VLOOKUP(K57,'Inertia Bases 2025'!$A:$H,8,0) -> #N/A
A58: 98346582 | B58: TP 32-90/2 A-O-A-BQQE-DX1 | F58: 1646 | G58: =CEILING(F58*0.55,1) -> 906 | R58: =VLOOKUP(N58,'Seismic Springs 2025'!$A:$I,9,0) -> #N/A | S58: =P58*R58 -> #N/A | T58: =VLOOKUP(K58,'Inertia Bases 2025'!$A:$H,8,0) -> #N/A
A59: 98420371 | B59: TP 65-180/2 A-F-A-BQQE-HX1 | F59: 3986 | G59: =CEILING(F59*0.55,1) -> 2193 | R59: =VLOOKUP(N59,'Seismic Springs 2025'!$A:$I,9,0) -> #N/A | S59: =P59*R59 -> #N/A | T59: =VLOOKUP(K59,'Inertia Bases 2025'!$A:$H,8,0) -> #N/A
... A62: 98742355 | B62: TP 65-250/2 A-F-B-BQQE-KX1 | F62: 5459 | G62: =CEILING(F62*0.55,1) -> 3003 | R62: =VLOOKUP(N62,'Seismic Springs 2025'!$A:$I,9,0) -> #N/A | S62: =P62*R62 -> #N/A | T62: =VLOOKUP(K62,'Inertia Bases 2025'!$A:$H,8,0) -> #N/A
A63: 98742400 | B63: TP 65-210/2 A-F-B-BQQE-JX1 | D63: 92996501 | E63: NR1 - Yellow | F63: 4836 | G63: =CEILING(F63*0.55,1) -> 2660 | I63: =2938.37-G63 -> 278.37 | J63: 520 | M63: 11.7 | P63: 4 | Q63: =M63*P63 -> 46.8 | R63: =VLOOKUP(N63,'Seismic Springs 2025'!$A:$I,9,0) -> #N/A | S63: =P63*R63 -> #N/A | T63: =VLOOKUP(K63,'Inertia Bases 2025'!$A:$H,8,0) -> #N/A
A64: 98742915 | B64: TP 50-140/4 A-F-B-BQQE-HX3 | F64: 5211 | G64: =CEILING(F64*0.55,1) -> 2867 | R64: =VLOOKUP(N64,'Seismic Springs 2025'!$A:$I,9,0) -> #N/A | S64: =P64*R64 -> #N/A | T64: =VLOOKUP(K64,'Inertia Bases 2025'!$A:$H,8,0) -> #N/A
A65: 98743320 | B65: TP 40-140/4 A-F-B-BQQE-GX3 | F65: 4933 | G65: =CEILING(F65*0.55,1) -> 2714 | R65: =VLOOKUP(N65,'Seismic Springs 2025'!$A:$I,9,0) -> #N/A | S65: =P65*R65 -> #N/A | T65: =VLOOKUP(K65,'Inertia Bases 2025'!$A:$H,8,0) -> #N/A
A66: 98743360 | B66: TP 40-110/4 A-F-B-BQQE-FX3 | F66: 4374 | G66: =CEILING(F66*0.55,1) -> 2406 | R66: =VLOOKUP(N66,'Seismic Springs 2025'!$A:$I,9,0) -> #N/A | S66: =P66*R66 -> #N/A | T66: =VLOOKUP(K66,'Inertia Bases 2025'!$A:$H,8,0) -> #N/A
A67: 98810439 | B67: TP 50-120/2 A-F-A-BQQE-FX1 | F67: 3265 | G67: =CEILING(F67*0.55,1) -> 1796 | R67: =VLOOKUP(N67,'Seismic Springs 2025'!$A:$I,9,0) -> #N/A | S67: =P67*R67 -> #N/A | T67: =VLOOKUP(K67,'Inertia Bases 2025'!$A:$H,8,0) -> #N/A
A68: 98843904 | B68: TP 80-120/2 AI-F-A-BQQE-HX1 | F68: 4632 | G68: =CEILING(F68*0.55,1) -> 2548 | R68: =VLOOKUP(N68,'Seismic Springs 2025'!$A:$I,9,0) -> #N/A | S68: =P68*R68 -> #N/A | T68: =VLOOKUP(K68,'Inertia Bases 2025'!$A:$H,8,0) -> #N/A
A69: 98957960 | B69: TP 40-60/2 A-F-A-BQQE-CX1 | F69: 2214 | G69: =CEILING(F69*0.55,1) -> 1218 | R69: =VLOOKUP(N69,'Seismic Springs 2025'!$A:$I,9,0) -> #N/A | S69: =P69*R69 -> #N/A | T69: =VLOOKUP(K69,'Inertia Bases 2025'!$A:$H,8,0) -> #N/A
A70: 98957962 | B70: TP 40-120/2 A-F-A-BQQE-DX1 | F70: 2697 | G70: =CEILING(F70*0.55,1) -> 1484 | R70: =VLOOKUP(N70,'Seismic Springs 2025'!$A:$I,9,0) -> #N/A | S70: =P70*R70 -> #N/A | T70: =VLOOKUP(K70,'Inertia Bases 2025'!$A:$H,8,0) -> #N/A
A71: 98957977 | B71: TP 50-60/2 A-F-A-BQQE-DX1 | F71: 2699 | G71: =CEILING(F71*0.55,1) -> 1485 | R71: =VLOOKUP(N71,'Seismic Springs 2025'!$A:$I,9,0) -> #N/A | S71: =P71*R71 -> #N/A | T71: =VLOOKUP(K71,'Inertia Bases 2025'!$A:$H,8,0) -> #N/A
A72: 99272206 | B72: TPE3 32-200 S-A-F-A-BQQE-FDC | F72: 6835 | G72: =CEILING(F72*0.55,1) -> 3760 | R72: =VLOOKUP(N72,'Seismic Springs 2025'!$A:$I,9,0) -> #N/A | S72: =P72*R72 -> #N/A | T72: =VLOOKUP(K72,'Inertia Bases 2025'!$A:$H,8,0) -> #N/A
A73: 99272211 | B73: TPE3 40-200 S-A-F-A-BQQE-GDC | F73: 7540 | G73: =CEILING(F73*0.55,1) -> 4147 | R73: =VLOOKUP(N73,'Seismic Springs 2025'!$A:$I,9,0) -> #N/A | S73: =P73*R73 -> #N/A | T73: =VLOOKUP(K73,'Inertia Bases 2025'!$A:$H,8,0) -> #N/A
A74: 99272212 | B74: TPE3 40-240 S-A-F-A-BQQE-HDC | F74: 8053 | G74: =CEILING(F74*0.55,1) -> 4430 | R74: =VLOOKUP(N74,'Seismic Springs 2025'!$A:$I,9,0) -> #N/A | S74: =P74*R74 -> #N/A | T74: =VLOOKUP(K74,'Inertia Bases 2025'!$A:$H,8,0) -> #N/A
A75: 99272218 | B75: TPE3 50-200 S-A-F-A-BQQE-HDC | F75: 8316 | G75: =CEILING(F75*0.55,1) -> 4574 | R75: =VLOOKUP(N75,'Seismic Springs 2025'!$A:$I,9,0) -> #N/A | S75: =P75*R75 -> #N/A | T75: =VLOOKUP(K75,'Inertia Bases 2025'!$A:$H,8,0) -> #N/A
... A78: 99122807 | B78: TP 40-360/2 A-F-A-BQQE-KW1 | F78: 4465 | G78: =CEILING(F78*0.55,1) -> 2456 | R78: =VLOOKUP(N78,'Seismic Springs 2025'!$A:$I,9,0) -> #N/A | S78: =P78*R78 -> #N/A | T78: =VLOOKUP(K78,'Inertia Bases 2025'!$A:$H,8,0) -> #N/A
A79: 98742568 | B79: TP 125-340/4 A-F-B-BAQE-QW3 | F79: 21715 | G79: =CEILING(F79*0.55,1) -> 11944 | K79: 92909412 | L79: 1100 x 800 x 250 | N79: 91338019 | O79: CLM-98 | P79: 4 | R79: =VLOOKUP(N79,'Seismic Springs 2025'!$A:$I,9,0) -> 170.3 | S79: =P79*R79 -> 681.2 | T79: =VLOOKUP(K79,'Inertia Bases 2025'!$A:$H,8,0) -> 721.39

Sheet Co-Efficients
A1: 0 | B1: 0.0001308042 | H1: 0 | I1: 0.00013 | K1: Preset charge (Pi) | L1: 150 | N1: Max Charge (Pf) | O1: 400
A2: 1 | B2: 7.2195408e-05 | H2: 10 | I2: 0.00025 | L2: 200 | O2: 500
A3: 2 | B3: 3.0149188e-05 | H3: 20 | I3: 0.00172 | L3: 250 | O3: 600
A4: 3 | B4: 4.291046e-06 | H4: 30 | I4: 0.0043 | O4: 1000
A5: 4 | B5: -5.74398e-06 | H5: 40 | I5: 0.0078
A6: 5 | B6: -3.11444e-07 | H6: 50 | I6: 0.01209
A7: 6 | B7: 2.0242388e-05 | H7: 60 | I7: 0.01711
A8: 7 | B8: 5.5580418e-05 | H8: 70 | I8: 0.02282
A9: 8 | B9: 0.0001053746 | H9: 80 | I9: 0.02921
A10: 9 | B10: 0.0001693058 | H10: 90 | I10: 0.0363
A11: 10 | B11: 0.00024706372 | H11: 100 | I11: 0.04408
A12: 11 | B12: 0.00033834672
A13: 12 | B13: 0.00044286175
A14: 13 | B14: 0.0005603242
A15: 14 | B15: 0.00069045778
A16: 15 | B16: 0.00083299443
A17: 16 | B17: 0.00098767415
A18: 17 | B18: 0.0011542449
A19: 18 | B19: 0.0013324626
A20: 19 | B20: 0.0015220907
A21: 20 | B21: 0.0017229004
A22: 21 | B22: 0.0019346704
A23: 22 | B23: 0.0021571867
... A101: 100 | B101: 0.044026533

Sheet UPS Pricing
A1: P/N | B1: DESCRIPTION | C1: 2024 MPG | D1: List Price | E1: Nett
A2: 519806 | B2: Union valve set G11/2"x1" | C2: AD | D2: 78 | E2: 50.7
A3: 529922 | B3: UNION SET G11/2"X1" CI | C3: AD | D3: 28 | E3: 18.2
A4: 529972 | B4: Union set G11/2"x1" | C4: AD | D4: 39 | E4: 25.35
A5: 59643600 | B5: UP20-30 N 150 1X240V 50HZ 9H | C5: DF | D5: 681 | E5: 374.55
A6: 91348548 | B6: DUAL UPS20-60 N 1X240V 50HZ STD | C6: DF | D6: 4622 | E6: 2542.1
A7: 91348640 | B7: DUAL UPS32-80 N 1X240V 50HZ DLX | C7: DF | D7: 7664 | E7: 4215.2
A8: 91348762 | B8: DUAL UPS20-60 N 1X240V 50HZ DLX | C8: DF | D8: 5889 | E8: 3238.95
A9: 91349121 | B9: DUAL UPS32-80 N 1X240V 50HZ STD | C9: DF | D9: 6321 | E9: 3476.55
A10: 93107332 | B10: UNION SET 11/4" 32MM BRASS | C10: AD | D10: 192 | E10: 124.8
A11: 93107333 | B11: UNION SET G11/2"X1" | C11: AD | D11: 40 | E11: 26
A12: 93107335 | B12: UNION SET BRASS 3/4' | C12: AD | D12: 92 | E12: 59.8
A13: 93108132 | B13: UNION VALVE SET 3/4-5/4" | C13: AD | D13: 87 | E13: 56.55
... A82: 99726692 | B82: HWC- DUAL MAGNA3 32-120 N 1x230V 50Hz | C82: BB | D82: 13992 | E82: 6996

Sheet Costing Template
A1: Reference | B1: SKU | C1: Name | D1: Qty | E1: Unit Nett | F1: IP-56 Nett | G1: Support Bar SKU | H1: Support Bar Nett (x2) | I1: Spring SKU | J1: Seismic Spring (x4) | K1: DT nett | L1: Unit Cost | M1: Total Cost | N1: Unit Sell | O1: Total Sell | P1: Margin | Q1: 0.815

Sheet NK Pricing
A1: SKU | B1: Name | C1: Quote # | D1: Quote Name | E1: Quote Date | F1: DT | G1: IP Rating | H1: Unit | I1: Base | J1: Springs | K1: Spring QTY | L1: Total Cost | M1: Sell Price | N1: Margin
A2: 93055672 | B2: NK 125-180/166 | C2: 1007528826 | D2: Sydney Biomedical Accelerator | E2: 45436 | F2: Y | H2: 6346.96 | I2: 643.75 | J2: 148.75 | K2: 4 | L2: 7585.71 | M2: =L2/$N$2 -> 9307.6196 | N2: 0.815 | O2: 5331.255
C3: 1007528826 | D3: Sydney Biomedical Accelerator | E3: 45436 | F3: N | H3: 6000.39 | I3: 643.75 | J3: 148.75 | K3: 4 | L3: 7239.14 | M3: =L3/$N$2 -> 8882.3804
C4: 1007364439 | D4: Ipswich Hospital | E4: 45363 | F4: Y | H4: 5740.86 | I4: 643.75 | J4: 148.75 | K4: 4 | L4: 6979.61 | M4: =L4/$N$2 -> 8563.9387
C5: 1007903185 | D5: Baxter Chilled Water Upgrade | E5: 45609 | F5: Y | H5: 5768.25 | I5: 656.56 | J5: 133.25 | K5: 4 | L5: =(K5*J5)+H5+I5 -> 6957.81 | M5: =L5/$N$2 -> 8537.1902
A6: 92775911 | B6: NK 100-180/167 | C6: 1007528826 | D6: Sydney Biomedical Accelerator | E6: 45436 | F6: N | H6: 5188.49 | I6: 628.75 | J6: 57.75 | K6: 4 | L6: 6048.24 | M6: =L6/$N$2 -> 7421.1534 | O6: 4522.915
C7: 1007395137 | D7: Noosa Hotel | E7: 45376 | F7: N | H7: 5073 | I7: 1000 | J7: 131.25 | K7: 6 | L7: 6860.5 | M7: =L7/$N$2 -> 8417.7914
A8: 92776056 | B8: NK 150-380/350 | C8: 1007528826 | D8: Sydney Biomedical Accelerator | E8: 45436 | F8: Y | H8: 16279.93 | I8: 1050 | J8: 148.75 | K8: 4 | L8: 17924.93 | M8: =L8/$N$2 -> 21993.779 | O8: 12566.255
C9: 1007377895 | D9: Westfield Parramatta | E9: 45369 | F9: N | H9: 14324.2 | I9: 1050 | J9: 148.75 | K9: 6 | L9: 16266.7 | M9: =L9/$N$2 -> 19959.141
C10: 1007320496 | D10: Redcliffe Hospital | E10: 45344 | F10: Y | H10: 16029.26 | I10: 1050 | J10: 148.75 | K10: 6 | L10: 17971.76 | M10: =L10/$N$2 -> 22051.239
C11: 1007589574 | D11: TPCH | E11: 45463 | F11: Y | H11: 15791.07 | I11: 1050 | J11: 148.75 | K11: 4 | L11: 17436.07 | M11: =L11/$N$2 -> 21393.951
C12: 1007816507 | D12: MEL12 | E12: 45569 | F12: N | H12: 14741.2 | I12: 1301.95 | J12: 151.71 | K12: 4 | L12: =(K12*J12)+H12+I12 -> 16649.99 | M12: =L12/$N$2 -> 20429.436
A13: 92775845 | B13: NK 65-225/232 | C13: 1007528826 | D13: Sydney Biomedical Accelerator | E13: 45436 | F13: N | H13: 6059.46 | I13: 650 | J13: 148.75 | K13: 4 | L13: 7304.46 | M13: =L13/$N$2 -> 8962.5276 | O13: 5421.16
C14: 1007395137 | D14: Noosa Hotel | E14: 45376 | F14: Y | H14: 6624.47 | I14: 1000 | J14: 131.25 | K14: 6 | L14: 8411.97 | M14: =L14/$N$2 -> 10321.436
A15: 92775868 | B15: NK 80-180/172 | C15: 1007528826 | D15: Sydney Biomedical Accelerator | E15: 45436 | F15: Y | H15: 4518.3 | I15: 636.25 | J15: 57.75 | K15: 4 | L15: 5385.55 | M15: =L15/$N$2 -> 6608.0368 | O15: 3548.845
C16: 1007394704 | D16: Bundaberg Hospital | E16: 45376 | F16: N | H16: 3698.65 | I16: 623.75 | J16: 57.75 | K16: 4 | L16: 4553.4 | M16: =L16/$N$2 -> 5586.9939
C17: 1008060801 | D17: TRI Stage 2 | E17: 45692 | F17: Y | G17: 55 | H17: 4253.54 | I17: 648.92 | J17: 133.86 | K17: 4 | L17: =(K17*J17)+H17+I17 -> 5437.9 | M17: =L17/$N$2 -> 6672.2699
C18: 1008060993 | D18: TRI Stage 2 | E18: 45692 | F18: Y | G18: 56 | H18: 4335.06 | I18: 648.92 | J18: 133.86 | K18: 4 | L18: =(K18*J18)+H18+I18 -> 5519.42 | M18: =L18/$N$2 -> 6772.2945
A19: 92775925 | B19: NK 100-225/215 | C19: 1007541813 | D19: Towoomba Hospital | E19: 45442 | F19: N | H19: 10928.7 | I19: 800 | J19: 148.75 | K19: 4 | L19: 12323.7 | M19: =L19/$N$2 -> 15121.104 | O19: 8852.49
C20: 1007394704 | D20: Bundaberg Hospital | E20: 45376 | F20: Y | H20: 11737.29 | I20: 800 | J20: 148.75 | K20: 4 | L20: 13132.29 | M20: =L20/$N$2 -> 16113.239
A21: 92776315 | B21: NK 125-380/405 | C21: 1007433753 | D21: 899 Collins St | E21: 45393 | F21: N | H21: 17071.12 | I21: 1010 | J21: 148.75 | K21: 6 | L21: 18973.62 | M21: =L21/$N$2 -> 23280.515 | O21: 11869.91
C22: 1007463845 | D22: Logan Hospital | E22: 45406 | F22: Y | H22: 15338.89 | I22: 1050 | J22: 148.75 | K22: 6 | L22: 17281.39 | M22: =L22/$N$2 -> 21204.16
C23: 1007586374 | D23: D&C Hospital Brisbane | E23: 45462 | F23: Y | H23: 15016.86 | I23: 1050 | J23: 57.75 | K23: 4 | L23: 16297.86 | M23: =L23/$N$2 -> 19997.374
A24: 92775926 | B24: NK 100-225/197 | C24: 1007589574 | D24: TPCH | E24: 45463 | F24: Y | H24: 10722.23 | I24: 755 | J24: 148.75 | K24: 4 | L24: 12072.23 | M24: =L24/$N$2 -> 14812.552 | O24: 8235.485
C25: 1007423760 | D25: QUT | E25: 45390 | F25: N | H25: 12552.44 | I25: 781.5 | J25: 148.75 | K25: 4 | L25: 13928.94 | M25: =L25/$N$2 -> 17090.724
A26: 92776317 | B26: NK 125-380/360 | C26: 1007589574 | D26: TPCH | E26: 45463 | F26: N | H26: 13457.4 | I26: 755 | J26: 148.75 | K26: 4 | L26: 14807.4 | M26: =L26/$N$2 -> 18168.589 | O26: 11265.66
C27: 1007595706 | D27: QEII | E27: 45467 | F27: N | H27: 13344.71 | I27: 791 | J27: 148.75 | K27: 4 | L27: 14730.71 | M27: =L27/$N$2 -> 18074.491
A28: 92775867 | B28: NK 80-180/174 | C28: 1007423760 | D28: QUT | E28: 45390 | F28: N | H28: 4821.56 | I28: 629 | J28: 148.75 | K28: 4 | L28: 6045.56 | M28: =L28/$N$2 -> 7417.865 | O28: 4169.18
C29: 1007528826 | D29: Sydney Biomedical Accelerator | E29: 45436 | F29: N | H29: 4818.76 | I29: 636.25 | J29: 57.75 | K29: 4 | L29: 5686.01 | M29: =L29/$N$2 -> 6976.6994
C30: 1007595706 | D30: QEII | E30: 45467 | F30: Y | H30: 4517.12 | I30: 791 | J30: 148.75 | K30: 4 | L30: 5903.12 | M30: =L30/$N$2 -> 7243.092
C31: 1008060801 | D31: TRI Stage 2 | E31: 45692 | F31: Y | G31: 55 | H31: 4910.44 | I31: 520.16 | J31: 133.86 | K31: 4 | L31: =(K31*J31)+H31+I31 -> 5966.04 | M31: =L31/$N$2 -> 7320.2945
C32: 1008060801 | D32: TRI Stage 2 | E32: 45692 | F32: Y | G32: 56 | H32: 4991.96 | I32: 520.16 | J32: 133.86 | K32: 4 | L32: =(K32*J32)+H32+I32 -> 6047.56 | M32: =L32/$N$2 -> 7420.319
A33: 92775927 | B33: NK 100-225/185 | C33: 1007528826 | D33: Sydney Biomedical Accelerator | E33: 45436 | F33: N | H33: 6945.71 | I33: 677.5 | J33: 148.75 | K33: 4 | L33: 8218.21 | M33: =L33/$N$2 -> 10083.693 | O33: 6211.61
C34: 1007595706 | D34: QEII | E34: 45467 | F34: Y | H34: 6826.14 | I34: 791 | J34: 148.75 | K34: 4 | L34: 8212.14 | M34: =L34/$N$2 -> 10076.245
C35: 1007423760 | D35: QUT | E35: 45390 | F35: N | H35: 6949.75 | I35: 677.5 | J35: 148.75 | K35: 4 | L35: 8222.25 | M35: =L35/$N$2 -> 10088.65
A36: 92775946 | B36: NK 100-350/326 | C36: 1007595706 | D36: QEII | E36: 45467 | F36: N | H36: 6253.88 | I36: 791 | J36: 148.75 | K36: 4 | L36: 7639.88 | M36: =L36/$N$2 -> 9374.0859 | O36: 6067
C37: 1007687288 | D37: Redcliffe Hospital | E37: 45509 | F37: N | H37: 6253.88 | I37: 982.46 | J37: 152.03 | K37: 4 | L37: =(K37*J37)+H37+I37 -> 7844.46 | M37: =L37/$N$2 -> 9625.1043
A38: 93055792 | B38: NK 200-300/288 | C38: 1007687288 | D38: Redcliffe Hospital | E38: 45509 | F38: N | H38: 13018.15 | I38: 817.64 | J38: 152.03 | K38: 4 | L38: =(K38*J38)+H38+I38 -> 14443.91 | M38: =L38/$N$2 -> 17722.589 | O38: 10919.31
A39: 93055858 | B39: NK 200-350/260 | C39: 1007687288 | D39: Redcliffe Hospital | E39: 45509 | F39: y | H39: 11295.36 | I39: 817.64 | J39: 152.03 | K39: 4 | L39: =(K39*J39)+H39+I39 -> 12721.12 | M39: =L39/$N$2 -> 15608.736 | O39: 10374.57
A40: 93055631 | B40: NK 150-380/350 | C40: 1007687288 | D40: Redcliffe Hospital | E40: 45509 | F40: Y | H40: 15687.18 | I40: 1121.76 | J40: 152.03 | K40: 6 | L40: =(K40*J40)+H40+I40 -> 17721.12 | M40: =L40/$N$2 -> 21743.706 | O40: 12566.255
A41: 93055747 | B41: NK 50-280/219 | C41: 1007713247 | D41: Brisbane Plant Replacement | E41: 45523 | F41: N | H41: 8494.83 | I41: 531 | J41: 68.5 | K41: 4 | L41: =(K41*J41)+H41+I41 -> 9299.83 | M41: =L41/$N$2 -> 11410.834 | O41: 4888.07 | P41: 4888.07
A42: 93030798 | B42: NK 125-350/289 | C42: 1007713247 | D42: Brisbane Plant Replacement | E42: 45523 | F42: N | H42: 11103.85 | I42: 832 | J42: 155.7 | K42: 4 | L42: =(K42*J42)+H42+I42 -> 12558.65 | M42: =L42/$N$2 -> 15409.387 | O42: 6382.69 | P42: 6382.69
A43: 93055686 | B43: NK 125-380/360 | C43: 1007713247 | D43: Brisbane Plant Replacement | E43: 45523 | F43: N | H43: 22515.79 | I43: 1142 | J43: 176.46 | K43: 6 | L43: =(K43*J43)+H43+I43 -> 24716.55 | M43: =L43/$N$2 -> 30327.055 | O43: 11265.66 | P43: 11265.66
A44: 93055520 | B44: NK 80-350/271 | C44: 1007713247 | D44: Brisbane Plant Replacement | E44: 45523 | F44: N | H44: 8734.17 | I44: 531 | J44: 68.5 | K44: 4 | L44: =(K44*J44)+H44+I44 -> 9539.17 | M44: =L44/$N$2 -> 11704.503 | O44: 5016.97 | P44: 5016.97
C45: 1008072834 | D45: 90 Crown St | E45: 45697 | F45: N | G45: 55 | H45: 5584 | I45: 662.95 | J45: 133.86 | K45: 4 | L45: =(K45*J45)+H45+I45 -> 6782.39 | M45: =L45/$N$2 -> 8321.9509
C46: 1008072834 | D46: 90 Crown St | E46: 45697 | F46: Y | G46: 55 | H46: 6084 | I46: 662.95 | J46: 133.86 | K46: 4 | L46: =(K46*J46)+H46+I46 -> 7282.39 | M46: =L46/$N$2 -> 8935.4479
A47: 93055661 | B47: NK 100-380/390 | C47: 1007713247 | D47: Brisbane Plant Replacement | E47: 45523 | F47: N | H47: 17952.85 | I47: 1142 | J47: 176.46 | K47: 6 | L47: =(K47*J47)+H47+I47 -> 20153.61 | M47: =L47/$N$2 -> 24728.356 | O47: 8635.04 | P47: 8635.04
A48: 92776322 | B48: NK 125-380/333 | C48: 1007716372 | D48: Bond University | E48: 45524 | F48: Y | H48: 9948.43 | I48: 1195.59 | J48: 176.46 | K48: 6 | L48: =(K48*J48)+H48+I48 -> 12202.78 | M48: =L48/$N$2 -> 14972.736 | O48: 9776.645
C49: 1007463845 | D49: Logan Hospital | E49: 45406 | F49: N | H49: 12753.13 | I49: 1050 | J49: 148.75 | K49: 6 | L49: =(K49*J49)+H49+I49 -> 14695.63 | M49: =L49/$N$2 -> 18031.448
A50: 93056070 | B50: NK 125-350/319 | C50: 1007719264 | D50: Atlassian | E50: 45526 | F50: Y | H50: 8499.46 | I50: 817.64 | J50: 152.03 | K50: 4 | L50: =(K50*J50)+H50+I50 -> 9925.22 | M50: =L50/$N$2 -> 12178.184 | O50: 7449.64
C51: 1008030596 | D51: Metro West - Burwood North | E51: 45678 | F51: N | G51: 55 | H51: 7648.02 | I51: 777.68 | J51: 151.71 | K51: 4 | L51: =(K51*J51)+H51+I51 -> 9032.54 | M51: =L51/$N$2 -> 11082.871
A52: 93055999 | B52: NK 80-350/299 | C52: 1007719264 | D52: Atlassian | E52: 45527 | F52: Y | H52: 5860.91 | I52: 664.34 | J52: 152.03 | K52: 4 | L52: =(K52*J52)+H52+I52 -> 7133.37 | M52: =L52/$N$2 -> 8752.6012 | O52: 5186.005
A53: 93055965 | B53: NK 80-180/172 | C53: 1007719264 | D53: Atlassian | E53: 45528 | F53: Y | H53: 4304.69 | I53: 605.57 | J53: 152.03 | K53: 4 | L53: =(K53*J53)+H53+I53 -> 5518.38 | M53: =L53/$N$2 -> 6771.0184 | O53: 3548.845
A54: 93055546 | B54: NK 100-225/172 | C54: 1007719264 | D54: Atlassian | E54: 45529 | F54: Y | H54: 5446.36 | I54: 817.64 | J54: 152.03 | K54: 4 | L54: =(K54*J54)+H54+I54 -> 6872.12 | M54: =L54/$N$2 -> 8432.0491 | O54: 5825.435
A55: 93056108 | B55: NK 150-350/318-314 | C55: 1007719264 | D55: Atlassian | E55: 45530 | F55: N | H55: 11932.8 | I55: 817.64 | J55: 152.03 | K55: 4 | L55: =(K55*J55)+H55+I55 -> 13358.56 | M55: =L55/$N$2 -> 16390.871 | O55: 9948.85
A56: 93056071 | B56: NK 125-350/289 | C56: 1007719264 | D56: Atlassian | E56: 45531 | F56: N | H56: 7179.84 | I56: 817.64 | J56: 152.03 | K56: 4 | L56: =(K56*J56)+H56+I56 -> 8605.6 | M56: =L56/$N$2 -> 10559.018 | O56: 6382.69
A57: 93056157 | B57: NK 100-380/367 | C57: 1007719264 | D57: Atlassian | E57: 45532 | F57: N | H57: 10176.47 | I57: 817.64 | J57: 152.03 | K57: 4 | L57: =(K57*J57)+H57+I57 -> 11602.23 | M57: =L57/$N$2 -> 14235.865 | O57: 8293.15
A58: 93055564 | B58: NK 100-350/326 | C58: 1007719264 | D58: Atlassian | E58: 45533 | F58: Y | H58: 5628.57 | I58: 817.64 | J58: 152.03 | K58: 4 | L58: =(K58*J58)+H58+I58 -> 7054.33 | M58: =L58/$N$2 -> 8655.6196 | O58: 6067
A59: 93055923 | B59: NK 65-180/169 | C59: 1007719264 | D59: Atlassian | E59: 45534 | F59: N | H59: 3669.05 | I59: 605.57 | J59: 133.84 | K59: 4 | L59: =(K59*J59)+H59+I59 -> 4809.98 | M59: =L59/$N$2 -> 5901.816 | O59: 3250.535
A60: 93055450 | B60: NK 65-180/154 | C60: 1007719264 | D60: Atlassian | E60: 45535 | F60: N | H60: 2371.75 | I60: 637.52 | J60: 59.02 | K60: 4 | L60: =(K60*J60)+H60+I60 -> 3245.35 | M60: =L60/$N$2 -> 3982.0245 | O60: 2725.595
A61: 92776275 | B61: NK 100-380/367 | D61: Visy | E61: 45343 | F61: N | H61: 9340 | I61: 817.64 | J61: 152.03 | K61: 4 | L61: =(K61*J61)+H61+I61 -> 10765.76 | M61: =L61/$N$2 -> 13209.521 | O61: 8293.15
C62: 1008030596 | D62: Metro West - Burwood North | E62: 45678 | F62: Y | G62: 55 | H62: 8954.62 | I62: 815.92 | J62: 151.71 | K62: 4 | L62: 14730.71 | M62: =L62/$N$2 -> 18074.491
A63: 93053105 | B63: NK 80-350/328 | C63: 1007748820 | D63: Windsor Medical Centre | E63: 45539 | F63: Y | H63: 5709.29 | I63: 980.39 | J63: 151.71 | K63: 4 | L63: =(K63*J63)+H63+I63 -> 7296.52 | M63: =L63/$N$2 -> 8952.7853 | O63: 5611.79
C64: 1008008615 | D64: GU N34 & N44 | E64: 45667 | F64: Y | G64: 56 | H64: 6235.75 | I64: 981.49 | J64: 151.71 | K64: 4 | L64: =(K64*J64)+H64+I64 -> 7824.08 | M64: =L64/$N$2 -> 9600.0982
C65: 1008060801 | D65: TRI Stage 2 | E65: 45692 | F65: Y | G65: 55 | H65: 6433.44 | I65: 648.92 | J65: 133.86 | K65: 4 | L65: =(K65*J65)+H65+I65 -> 7617.8 | M65: =L65/$N$2 -> 9346.9939
C66: 1008060993 | D66: TRI Stage 2 | E66: 45692 | F66: Y | G66: 56 | H66: 6542.7 | I66: 648.91 | J66: 133.86 | K66: 4 | L66: =(K66*J66)+H66+I66 -> 7727.05 | M66: =L66/$N$2 -> 9481.0429
A67: 92775827 | B67: NK 50-350/340-336 | C67: 1007748820 | D67: Windsor Medical Centre | E67: 45540 | F67: Y | H67: 4894.32 | I67: 980.4 | J67: 151.71 | K67: 4 | L67: =(K67*J67)+H67+I67 -> 6481.56 | M67: =L67/$N$2 -> 7952.8344 | O67: 4809.14
A68: 92776041 | B68: NK 150-350/294 | C68: 1007801318 | D68: Brisbane CBD Project | E68: 45562 | F68: N | H68: 9629.48 | I68: 1528.81 | J68: 151.71 | K68: 4 | L68: =(K68*J68)+H68+I68 -> 11765.13 | M68: =L68/$N$2 -> 14435.742 | O68: 9101.895
A69: 92776276 | B69: NK 100-380/341 | C69: 1007801318 | D69: Brisbane CBD Project | E69: 45562 | F69: Y | H69: 6780.48 | I69: 1015.62 | J69: 151.71 | K69: 4 | L69: =(K69*J69)+H69+I69 -> 8402.94 | M69: =L69/$N$2 -> 10310.356 | O69: 7177.535
A70: 92775902 | B70: NK 80-350/299 | C70: 1007801318 | D70: Brisbane CBD Project | E70: 45564 | F70: N | H70: 4626.1 | I70: 715.21 | J70: 133.86 | K70: 4 | L70: =(K70*J70)+H70+I70 -> 5876.75 | M70: =L70/$N$2 -> 7210.7362 | O70: 5186.005
A71: 92775880 | B71: NK 80-225/183 | C71: 1007813843 | D71: DLR SY14 | E71: 45568 | F71: Y | H71: 6135.3 | I71: 980.39 | J71: 151.71 | K71: 4 | L71: =(K71*J71)+H71+I71 -> 7722.53 | M71: =L71/$N$2 -> 9475.4969 | O71: 5635.1
C72: 1008027134 | D72: Erina Fair | E72: 45676 | F72: Y | G72: 55 | H72: 6140.47 | I72: 980.4 | J72: 151.71 | K72: 4 | L72: =(K72*J72)+H72+I72 -> 7727.71 | M72: =L72/$N$2 -> 9481.8528
A73: 93055430 | B73: NK 50-225/172 | C73: 1007956737 | D73: Windsor Medical Centre | E73: 45632 | F73: Y | H73: 3648.9 | I73: 662.95 | J73: 133.86 | K73: 4 | L73: =(K73*J73)+H73+I73 -> 4847.29 | M73: =L73/$N$2 -> 5947.5951 | O73: 3376.07
A74: 93055650 | B74: NK 32-180/177 | C74: 1007956737 | D74: Windsor Medical Centre | E74: 45632 | F74: Y | H74: 2615.53 | I74: 647.65 | J74: 58.9 | K74: 4 | L74: =(K74*J74)+H74+I74 -> 3498.78 | M74: =L74/$N$2 -> 4292.9816 | O74: 2418.3
A75: 93053375 | B75: NK 100-280/215 | C75: 1007987319 | D75: Caboolture Admin | E75: 45649 | F75: Y | H75: 4963 | I75: 641.24 | J75: 58.9 | K75: 4 | L75: =(K75*J75)+H75+I75 -> 5839.84 | M75: =L75/$N$2 -> 7165.4479
A76: 93226247 | B76: NK 125-320/248 | C76: 1007999915 | D76: UQ Commerce Hill | E76: 45664 | F76: Y | H76: 5987.5 | I76: 981.5 | J76: 151.71 | K76: 4 | L76: =(K76*J76)+H76+I76 -> 7575.84 | M76: =L76/$N$2 -> 9295.5092
A77: 93053308 | B77: NK 100-225/235 | C77: 1007999915 | D77: UQ Commerce Hill | E77: 45664 | F77: Y | H77: 4020.5 | I77: 905.12 | J77: 151.71 | K77: 4 | L77: =(K77*J77)+H77+I77 -> 5532.46 | M77: =L77/$N$2 -> 6788.2945 | O77: 3748.31
A78: 55 | B78: NK 150-360/302-296 | C78: 1007999915 | D78: UQ Commerce Hill | E78: 45664 | F78: Y | H78: 12496.5 | I78: 1040 | J78: 151.71 | K78: 4 | L78: =(K78*J78)+H78+I78 -> 14143.34 | M78: =L78/$N$2 -> 17353.791
C79: 1008088759 | D79: Mounties | E79: 45705 | F79: Y | G79: 55 | H79: 10727.55 | I79: 1302.04 | J79: 151.71 | K79: 6 | L79: =(K79*J79)+H79+I79 -> 12939.85 | M79: =L79/$N$2 -> 15877.117
A80: 93053436 | B80: NK 100-350/308 | C80: 1007999915 | D80: UQ Commerce Hill | E80: 45664 | F80: Y | H80: 6334.5 | I80: 981.5 | J80: 151.71 | K80: 4 | L80: =(K80*J80)+H80+I80 -> 7922.84 | M80: =L80/$N$2 -> 9721.2761 | O80: 5880.52
C81: 1007378231 | D81: Mt Gravatt Cinemas | E81: 45369 | F81: Y | H81: 6829.09 | I81: 1000 | J81: 148.75 | K81: 4 | L81: =(K81*J81)+H81+I81 -> 8424.09 | M81: =L81/$N$2 -> 10336.307
A82: 93053635 | B82: NK 125-350/333-329 | C82: 1007999915 | D82: UQ Commerce Hill | E82: 45664 | F82: N | H82: 10430.5 | I82: 1040 | J82: 151.71 | K82: 4 | L82: =(K82*J82)+H82+I82 -> 12077.34 | M82: =L82/$N$2 -> 14818.822
A83: 93053416 | B83: NK 100-350/326 | C83: 1007999915 | D83: UQ Commerce Hill | E83: 45664 | F83: N | H83: 6150.5 | I83: 981.5 | J83: 151.71 | K83: 4 | L83: =(K83*J83)+H83+I83 -> 7738.84 | M83: =L83/$N$2 -> 9495.5092 | O83: 6067
C84: 1008088759 | D84: Mounties | E84: 45705 | F84: N | G84: 55 | H84: 6417.56 | I84: 658.04 | J84: 151.71 | K84: 4 | L84: =(K84*J84)+H84+I84 -> 7682.44 | M84: =L84/$N$2 -> 9426.3067
A85: 93052969 | B85: NK 65-280/270 | C85: 1008015251 | D85: Caboolture Admin | E85: 45671 | F85: Y | G85: 55 | H85: 3572 | I85: 636.35 | J85: 58.9 | K85: 4 | L85: =(K85*J85)+H85+I85 -> 4443.95 | M85: =L85/$N$2 -> 5452.6994 | O85: 3264.19
A86: 93053023 | B86: NK 80-225/205 | C86: 1008015251 | D86: Caboolture Admin | E86: 45671 | F86: N | G86: 55 | H86: 3374.5 | I86: 636.34 | J86: 58.9 | K86: 4 | L86: =(K86*J86)+H86+I86 -> 4246.44 | M86: =L86/$N$2 -> 5210.3558 | O86: 8156.57 | P86: 8156.57
A87: 93053636 | B87: NK 125-350/276 | C87: 1008027134 | D87: Erina Fair | E87: 45676 | F87: N | G87: 55 | H87: 6431.28 | I87: 734.33 | J87: 151.71 | K87: 4 | L87: =(K87*J87)+H87+I87 -> 7772.45 | M87: =L87/$N$2 -> 9536.7485 | O87: 6258.855
A88: 93055390 | B88: NK 40-180/176 | C88: 1008030596 | D88: Metro West - Burwood North | E88: 45678 | F88: Y | G88: 55 | H88: 3354.84 | I88: 604.3 | J88: 58.9 | K88: 4 | L88: =(K88*J88)+H88+I88 -> 4194.74 | M88: =L88/$N$2 -> 5146.9202 | O88: 3073.74
A89: 93053107 | B89: NK 80-350/299 | C89: 1008043385 | D89: 450 Queen St | E89: 45683 | F89: Y | G89: 55 | H89: 5386.66 | I89: 1015.62 | J89: 151.71 | K89: 4 | L89: =(K89*J89)+H89+I89 -> 7009.12 | M89: =L89/$N$2 -> 8600.1472 | O89: 5186.005
A90: 93053509 | B90: NK 125-225/223 | C90: 1008043385 | D90: 450 Queen St | E90: 45683 | F90: N | G90: 55 | H90: 4996.6 | I90: 1015.62 | J90: 151.71 | K90: 4 | L90: =(K90*J90)+H90+I90 -> 6619.06 | M90: =L90/$N$2 -> 8121.546 | O90: 4860.675
C91: 1007378231 | D91: Mt Gravatt Cinemas | E91: 45369 | F91: N | G91: 55 | H91: 5275.36 | I91: 1000 | J91: 148.75 | K91: 6 | L91: =(K91*J91)+H91+I91 -> 7167.86 | M91: =L91/$N$2 -> 8794.9202
A92: 93053373 | B92: NK 100-280/240 | C92: 1008043385 | D92: 450 Queen St | E92: 45683 | F92: N | G92: 55 | H92: 5216.36 | I92: 1015.62 | J92: 151.71 | K92: 4 | L92: =(K92*J92)+H92+I92 -> 6838.82 | M92: =L92/$N$2 -> 8391.1902
A93: 93053438 | B93: NK 100-350/290 | C93: 1008043385 | D93: 450 Queen St | E93: 45683 | F93: N | G93: 55 | H93: 5554 | I93: 1015.64 | J93: 151.71 | K93: 4 | L93: =(K93*J93)+H93+I93 -> 7176.48 | M93: =L93/$N$2 -> 8805.4969 | O93: 5402.72
A94: 93052879 | B94: NK 50-350/304 | C94: 1008060801 | D94: TRI Stage 2 | E94: 45692 | F94: Y | G94: 55 | H94: 4950.14 | I94: 942.14 | J94: 133.86 | K94: 4 | L94: =(K94*J94)+H94+I94 -> 6427.72 | M94: =L94/$N$2 -> 7886.773 | O94: 4190.24
C95: 1008060993 | D95: TRI Stage 2 | E95: 45692 | F95: Y | G95: 56 | H95: 5010.84 | I95: 648.92 | J95: 133.86 | K95: 4 | L95: =(K95*J95)+H95+I95 -> 6195.2 | M95: =L95/$N$2 -> 7601.4724
A96: 93052609 | B96: NK 40-180/155 | C96: 1008060801 | D96: TRI Stage 2 | E96: 45692 | F96: Y | G96: 55 | H96: 3112.45 | I96: 942.14 | J96: 133.86 | K96: 4 | L96: =(K96*J96)+H96+I96 -> 4590.03 | M96: =L96/$N$2 -> 5631.9387 | O96: 2467.19
C97: 1008060993 | D97: TRI Stage 2 | E97: 45692 | F97: Y | G97: 56 | H97: 3183.16 | I97: 942.14 | J97: 133.86 | K97: 4 | L97: =(K97*J97)+H97+I97 -> 4660.74 | M97: =L97/$N$2 -> 5718.6994
A98: 93055519 | B98: NK 80-350/299 | C98: 1008072834 | D98: 90 Crown St | E98: 45697 | F98: N | G98: 55 | H98: 5100.5 | I98: 662.94 | J98: 133.86 | K98: 4 | L98: =(K98*J98)+H98+I98 -> 6298.88 | M98: =L98/$N$2 -> 7728.6871 | O98: 5186.005
A99: 93054075 | B99: NK 125-380/333 | C99: 1008088759 | D99: Mounties | E99: 45705 | F99: Y | G99: 55 | H99: 10832.8 | I99: 1302.04 | J99: 128.37 | K99: 4 | L99: =(K99*J99)+H99+I99 -> 12648.32 | M99: =L99/$N$2 -> 15519.411 | O99: 9776.645
A100: 93053982 | B100: NK 100-380/426 | C100: 1008088759 | D100: Mounties | E100: 45705 | F100: N | G100: 55 | H100: 6497.3 | I100: 815.93 | J100: 151.71 | K100: 4 | L100: =(K100*J100)+H100+I100 -> 7920.07 | M100: =L100/$N$2 -> 9717.8773 | O100: 11298.82 | P100: 11298.82

Sheet Seismic Springs
A1: Type | B1: Max Load kg | C1: Static Deflection | D1: Spring Constant kg/mm | E1: Stripe 1 | F1: Stripe 2 | G1: Part Number | H1: Net price | I1: Quoted Net Cost | K1: CSM/CLM/CWM Technical Datasheet
A2: CSM-9 | B2: 10 | C2: 33 | D2: 0.3 | E2: Yellow | F2: -
A3: CSM-10 | B3: 15 | C3: 33 | D3: 0.45 | E3: Brown | F3: - | G3: 92958833 | H3: $68.50 | J3: Spring Calculation
A4: CSM-11 | B4: 30 | C4: 33 | D4: 0.9 | E4: Blue | F4: - | G4: 92926537 | H4: $68.50 | J4: Actual Intertia Base Weight | K4: 1632
A5: CSM-12 | B5: 50 | C5: 28 | D5: 1.8 | E5: Black | F5: - | G5: 92926485 | H5: $68.50 | J5: Spring Qty | K5: 6
A6: CSM-13 | B6: 75 | C6: 25 | D6: 3 | E6: Red | F6: - | G6: 92958789 | H6: $68.50 | J6: Static Deflection | K6: 25mm
A7: CSM-14 | B7: 125 | C7: 25 | D7: 5 | E7: Green | F7: - | G7: 92932672 | H7: $68.50 | J7: Spring Load | K7: =K4/K5 -> 272
A8: CSM-16 | B8: 175 | C8: 20 | D8: 8.8 | E8: Grey | F8: - | G8: 92932673 | H8: $68.50
A9: CSM-17 | B9: 200 | C9: 15 | D9: 13.3 | E9: Orange | F9: - | G9: 91338157 | H9: $68.50
A10: CLM-89 | B10: 10 | C10: 40 | D10: 0.3 | E10: White | F10: -
A11: CLM-90 | B11: 20 | C11: 38 | D11: 0.5 | E11: Violet | F11: -
A12: CLM-91 | B12: 35 | C12: 35 | D12: 1 | E12: Violet | F12: Black
A13: CLM-92 | B13: 50 | C13: 33 | D13: 1.5 | E13: Yellow | F13: - | G13: 91338013 | H13: $155.70
A14: CLM-93 | B14: 100 | C14: 33 | D14: 3 | E14: Brown | F14: - | G14: 91338014 | H14: $155.70
A15: CLM-94 | B15: 150 | C15: 30 | D15: 5 | E15: Blue | F15: - | G15: 91338015 | H15: $155.70
A16: CLM-95 | B16: 200 | C16: 30 | D16: 6.7 | E16: Black | F16: - | G16: 91338016 | H16: $155.70 | I16: 134.14
A17: CLM-96 | B17: 250 | C17: 28 | D17: 8.9 | E17: Red | F17: - | G17: 91338017 | H17: $155.70
A18: CLM-97 | B18: 300 | C18: 28 | D18: 10.7 | E18: Green | F18: - | G18: 91338018 | H18: $176.46 | I18: 152.03
A19: CLM-98 | B19: 400 | C19: 25 | D19: 16 | E19: Grey | F19: - | G19: 91338019 | H19: $176.46
A20: CLM-99 | B20: 550 | C20: 23 | D20: 23.9 | E20: Orange | F20: - | G20: 91338020 | H20: $176.46
A21: CLM-100 | B21: 650 | C21: 20 | D21: 32.5 | E21: Orange | F21: Black | G21: 91338021 | H21: $176.46 | I21: =H21/0.85*4 -> 830.4
E22: Outer | F22: Inner
A23: CWM-423 | B23: 300 | C23: 33 | D23: 9.1 | E23: Black | F23: Yellow
A24: CWM-425 | B24: 380 | C24: 30 | D24: 12.7 | E24: Black | F24: Red
A25: CWM-1000 | B25: 450 | C25: 25 | D25: 18 | E25: Green | F25: -
A26: CWM-1021 | B26: 480 | C26: 25 | D26: 19.2 | E26: Green | F26: Black
A27: CWM-1023 | B27: 510 | C27: 25 | D27: 20.4 | E27: Green | F27: Yellow
A28: CWM-1024 | B28: 550 | C28: 25 | D28: 22 | E28: Green | F28: Green
A29: CWM-1025 | B29: 580 | C29: 25 | D29: 23.2 | E29: Green | F29: Red
A30: CWM-1026 | B30: 690 | C30: 25 | D30: 27.6 | E30: Green | F30: White
A31: CWM-1600 | B31: 775 | C31: 25 | D31: 31 | E31: Grey | F31: -
A32: CWM-1622 | B32: 820 | C32: 25 | D32: 32.8 | E32: Grey | F32: Blue
A33: CWM-1624 | B33: 875 | C33: 25 | D33: 35 | E33: Grey | F33: Green
A34: CWM-1626 | B34: 1000 | C34: 25 | D34: 40 | E34: Grey | F34: White
... A37: CWM-1731 | B37: 1275 | C37: 20 | D37: 63.8 | E37: Orange | F37: Grey/Yellow
A39: CWDM-33 | B39: 50 | C39: 50 | D39: 1 | E39: White | G39: 93176730 | H39: $288.58 | K39: CWDM/CDM Technical Datasheet
A40: CWDM-34 | B40: 75 | C40: 50 | D40: 1.5 | E40: Violet | G40: 93176746 | H40: $288.58
A41: CWDM-35 | B41: 110 | C41: 50 | D41: 2.2 | E41: Yellow | G41: 93176748 | H41: $288.58
A42: CWDM-36 | B42: 150 | C42: 50 | D42: 3 | E42: Brown | G42: 93176749 | H42: $288.58
A43: CWDM-37 | B43: 200 | C43: 50 | D43: 4 | E43: Orange | G43: 93176761 | H43: $288.58
A44: CWDM-38 | B44: 250 | C44: 50 | D44: 5 | E44: Orange | F44: Black | G44: 93176760 | H44: $288.58
A45: CWDM-39 | B45: 350 | C45: 40 | D45: 8.8 | E45: Orange | F45: Green | G45: 93176762 | H45: $288.58
E46: Outer | F46: Inner
A47: CDM-50 | B47: 65 | C47: 50 | D47: 1.3 | E47: Blue
A48: CDM-51 | B48: 125 | C48: 50 | D48: 2.5 | E48: Black
A49: CDM-510 | B49: 195 | C49: 50 | D49: 3.9 | E49: Black | F49: Blue
A50: CDM-52 | B50: 225 | C50: 50 | D50: 4.5 | E50: Red
A51: CDM-520 | B51: 295 | C51: 50 | D51: 5.9 | E51: Red | F51: Blue
A52: CDM-521 | B52: 350 | C52: 50 | D52: 7 | E52: Red | F52: Black
A53: CDM-53 | B53: 450 | C53: 50 | D53: 9 | E53: Green
A54: CDM-530 | B54: 520 | C54: 50 | D54: 10.4 | E54: Green | F54: Blue
A55: CDM-531 | B55: 575 | C55: 50 | D55: 11.5 | E55: Green | F55: Black
A56: CDM-532 | B56: 700 | C56: 50 | D56: 14 | E56: Green | F56: Red
A57: CDM-55 | B57: 650 | C57: 50 | D57: 13 | E57: Grey
A58: CDM-551 | B58: 775 | C58: 50 | D58: 15.5 | E58: Grey | F58: Black
A59: CDM-552 | B59: 900 | C59: 50 | D59: 18 | E59: Grey | F59: Red
A60: CDM-553 | B60: 1000 | C60: 50 | D60: 20 | E60: Grey | F60: Green
A61: CDM-553 | B61: 1000 | C61: 50 | D61: 20 | E61: Grey | F61: Green

Sheet Seismic Springs 2025
A1: Part Number | B1: Description | C1: Max Load (Kg) | D1: Static Deflection (mm) | E1: Spring Constant | F1: Stripe 1 | G1: Stripe 2 | H1: List | I1: Unit Nett | J1: 4x Spring Cost | K1: CSM/CLM/CWM Technical Datasheet
B2: CSM-9 | C2: 10 | D2: 33 | E2: 0.3 | F2: Yellow | G2: - | L2: Spring | M2: Part Number | N2: Description | O2: Max Load (Kg) | P2: Static Deflection (mm) | Q2: Spring Constant | R2: Stripe 1 | S2: Stripe 2 | T2: Unit Cost | U2: 4x Spring Cost
A3: 92958833 | B3: CSM-10 | C3: 15 | D3: 33 | E3: 0.45 | F3: Brown | G3: - | H3: 102 | I3: =H3*0.65 -> 66.3 | J3: =I3*4 -> 265.2 | L3: 92932672-CSM14-125 | M3: 92932672 | N3: CSM-14 | O3: 125 | P3: 25 | Q3: 5 | R3: Green | S3: - | T3: 59.52 | U3: 238.08
A4: 92926537 | B4: CSM-11 | C4: 30 | D4: 33 | E4: 0.9 | F4: Blue | G4: - | H4: 102 | I4: =H4*0.65 -> 66.3 | J4: =I4*4 -> 265.2 | L4: 92932673-CSM16-175 | M4: 92932673 | N4: CSM-16 | O4: 175 | P4: 20 | Q4: 8.8 | R4: Grey | S4: - | T4: 59.52 | U4: 238.08
A5: 92926485 | B5: CSM-12 | C5: 50 | D5: 28 | E5: 1.8 | F5: Black | G5: - | H5: 102 | I5: =H5*0.65 -> 66.3 | J5: =I5*4 -> 265.2 | L5: 91338157-CSM17-200 | M5: 91338157 | N5: CSM-17 | O5: 200 | P5: 15 | Q5: 13.3 | R5: Orange | S5: - | T5: 59.52 | U5: 238.08
A6: 92958789 | B6: CSM-13 | C6: 75 | D6: 25 | E6: 3 | F6: Red | G6: - | H6: 102 | I6: =H6*0.65 -> 66.3 | J6: =I6*4 -> 265.2 | L6: 91338016-CLM96-250 | M6: 91338016 | N6: CLM-96 | O6: 250 | P6: 28 | Q6: 8.9 | R6: Red | S6: - | T6: 135.26 | U6: 541.04
A7: 92932672 | B7: CSM-14 | C7: 125 | D7: 25 | E7: 5 | F7: Green | G7: - | H7: 102 | I7: =H7*0.65 -> 66.3 | J7: =I7*4 -> 265.2 | L7: 91338018-CLM97-300 | M7: 91338018 | N7: CLM-97 | O7: 300 | P7: 28 | Q7: 10.7 | R7: Green | S7: - | T7: 170.3 | U7: 613.2
A8: 92932673 | B8: CSM-16 | C8: 175 | D8: 20 | E8: 8.8 | F8: Grey | G8: - | H8: 102 | I8: =H8*0.65 -> 66.3 | J8: =I8*4 -> 265.2 | L8: 91338019-CLM98-400 | M8: 91338019 | N8: CLM-98 | O8: 400 | P8: 25 | Q8: 16 | R8: Grey | S8: - | T8: 170.3 | U8: 613.2
A9: 91338157 | B9: CSM-17 | C9: 200 | D9: 15 | E9: 13.3 | F9: Orange | G9: - | H9: 102 | I9: =H9*0.65 -> 66.3 | J9: =I9*4 -> 265.2 | L9: 91338020-CLM99-550 | M9: 91338020 | N9: CLM-99 | O9: 550 | P9: 23 | Q9: 23.9 | R9: Orange | S9: - | T9: 170.3 | U9: 613.2
B10: CLM-89 | C10: 10 | D10: 40 | E10: 0.3 | F10: White | G10: - | L10: 91338021-CLM100-650 | M10: 91338021 | N10: CLM-100 | O10: 650 | P10: 20 | Q10: 32.5 | R10: Orange | S10: Black | T10: 170.3 | U10: 613.2
B11: CLM-90 | C11: 20 | D11: 38 | E11: 0.5 | F11: Violet | G11: -
B12: CLM-91 | C12: 35 | D12: 35 | E12: 1 | F12: Violet | G12: Black
A13: 91338013 | B13: CLM-92 | C13: 50 | D13: 33 | E13: 1.5 | F13: Yellow | G13: - | H13: 205.94
A14: 91338014 | B14: CLM-93 | C14: 100 | D14: 33 | E14: 3 | F14: Brown | G14: - | H14: 205.94 | I14: 135.26 | J14: =I14*4 -> 541.04 | K14: =206*0.6 -> 123.6
A15: 91338015 | B15: CLM-94 | C15: 150 | D15: 30 | E15: 5 | F15: Blue | G15: - | H15: 205.94 | I15: 135.26 | J15: =I15*4 -> 541.04 | K15: =K14*4 -> 494.4
A16: 91338016 | B16: CLM-95 | C16: 200 | D16: 30 | E16: 6.7 | F16: Black | G16: - | H16: 205.94 | I16: 135.26 | J16: =I16*4 -> 541.04
A17: 91338017 | B17: CLM-96 | C17: 250 | D17: 28 | E17: 8.9 | F17: Red | G17: - | I17: 135.26 | J17: =I17*4 -> 541.04 | M17: Spring Calculation
A18: 91338018 | B18: CLM-97 | C18: 300 | D18: 28 | E18: 10.7 | F18: Green | G18: - | I18: 170.3 | J18: =I18*4 -> 681.2 | M18: Actual Intertia Base Weight | N18: 1632
A19: 91338019 | B19: CLM-98 | C19: 400 | D19: 25 | E19: 16 | F19: Grey | G19: - | I19: 170.3 | J19: =I19*4 -> 681.2 | M19: Spring Qty | N19: 6
A20: 91338020 | B20: CLM-99 | C20: 550 | D20: 23 | E20: 23.9 | F20: Orange | G20: - | H20: 233.4 | I20: 170.3 | J20: =I20*4 -> 681.2 | M20: Static Deflection | N20: 25mm
A21: 91338021 | B21: CLM-100 | C21: 650 | D21: 20 | E21: 32.5 | F21: Orange | G21: Black | H21: 233.4 | I21: 170.3 | J21: =I21*4 -> 681.2 | K21: =6112+2826 -> 8938 | M21: Spring Load | N21: =N18/N19 -> 272
F22: Outer | G22: Inner
B23: CWM-423 | C23: 300 | D23: 33 | E23: 9.1 | F23: Black | G23: Yellow | K23: =2627*2 -> 5254
B24: CWM-425 | C24: 380 | D24: 30 | E24: 12.7 | F24: Black | G24: Red
B25: CWM-1000 | C25: 450 | D25: 25 | E25: 18 | F25: Green | G25: - | K25: =K21-K23 -> 3684
B26: CWM-1021 | C26: 480 | D26: 25 | E26: 19.2 | F26: Green | G26: Black
B27: CWM-1023 | C27: 510 | D27: 25 | E27: 20.4 | F27: Green | G27: Yellow
B28: CWM-1024 | C28: 550 | D28: 25 | E28: 22 | F28: Green | G28: Green | P28: CSM-14 | Q28: 125 | R28: 93176749 | S28: CWDM-36 | T28: 150 | U28: 50 | V28: $288.58
B29: CWM-1025 | C29: 580 | D29: 25 | E29: 23.2 | F29: Green | G29: Red | P29: CSM-16 | Q29: 175 | R29: 93176761 | S29: CWDM-37 | T29: 200 | U29: 50 | V29: $288.59
B30: CWM-1026 | C30: 690 | D30: 25 | E30: 27.6 | F30: Green | G30: White | P30: CSM-17 | Q30: 200 | R30: 93176761 | S30: CWDM-37 | T30: 200 | U30: 50 | V30: $288.60
B31: CWM-1600 | C31: 775 | D31: 25 | E31: 31 | F31: Grey | G31: - | P31: CLM-96 | Q31: 250 | R31: 93176760 | S31: CWDM-38 | T31: 250 | U31: 50 | V31: $288.61
B32: CWM-1622 | C32: 820 | D32: 25 | E32: 32.8 | F32: Grey | G32: Blue | I32: 693.55 | J32: =I32*4 -> 2774.2 | P32: CLM-97 | Q32: 300 | R32: 93176762 | S32: CDM-521 | T32: 350 | U32: 50 | V32: 668.94
B33: CWM-1624 | C33: 875 | D33: 25 | E33: 35 | F33: Grey | G33: Green | P33: CLM-98 | Q33: 400 | S33: CDM-53 | T33: 450 | U33: 50 | V33: 668.94
B34: CWM-1626 | C34: 1000 | D34: 25 | E34: 40 | F34: Grey | G34: White | P34: CLM-99 | Q34: 550 | S34: CDM-531 | T34: 575 | U34: 50 | V34: 717.41
B35: CWM-1627 | C35: 1100 | D35: 25 | E35: 44 | F35: Grey | G35: Orange | P35: CLM-100 | Q35: 650 | S35: CDM-55 | T35: 650 | U35: 50 | V35: 717.41
B36: CWM-1628 | C36: 1150 | D36: 24 | E36: 47.9 | F36: Grey | G36: Grey
B37: CWM-1731 | C37: 1275 | D37: 20 | E37: 63.8 | F37: Orange | G37: Grey/Yellow
A39: 93176730 | B39: CWDM-33 | C39: 50 | D39: 50 | E39: 1 | F39: White | I39: $288.58 | J39: =I39*4 -> 1154.32 | K39: CWDM/CDM Technical Datasheet
A40: 93176746 | B40: CWDM-34 | C40: 75 | D40: 50 | E40: 1.5 | F40: Violet | I40: $288.58 | J40: =I40*4 -> 1154.32
A41: 93176748 | B41: CWDM-35 | C41: 110 | D41: 50 | E41: 2.2 | F41: Yellow | I41: $288.58 | J41: =I41*4 -> 1154.32
A42: 93176749 | B42: CWDM-36 | C42: 150 | D42: 50 | E42: 3 | F42: Brown | I42: $288.58 | J42: =I42*4 -> 1154.32
A43: 93176761 | B43: CWDM-37 | C43: 200 | D43: 50 | E43: 4 | F43: Orange | I43: $288.58 | J43: =I43*4 -> 1154.32
A44: 93176760 | B44: CWDM-38 | C44: 250 | D44: 50 | E44: 5 | F44: Orange | G44: Black | I44: $288.58 | J44: =I44*4 -> 1154.32
A45: 93176762 | B45: CWDM-39 | C45: 350 | D45: 40 | E45: 8.8 | F45: Orange | G45: Green | I45: $288.58 | J45: =I45*4 -> 1154.32
F46: Outer | G46: Inner
B47: CDM-50 | C47: 65 | D47: 50 | E47: 1.3 | F47: Blue
B48: CDM-51 | C48: 125 | D48: 50 | E48: 2.5 | F48: Black
B49: CDM-510 | C49: 195 | D49: 50 | E49: 3.9 | F49: Black | G49: Blue
B50: CDM-52 | C50: 225 | D50: 50 | E50: 4.5 | F50: Red
B51: CDM-520 | C51: 295 | D51: 50 | E51: 5.9 | F51: Red | G51: Blue
E52: 7 | F52: Red | G52: Black
B53: CDM-53 | C53: 450 | D53: 50 | E53: 9 | F53: Green | I53: 668.94 | J53: =I53*4 -> 2675.76
A54: 99227705 | B54: CDM-530 | C54: 520 | D54: 50 | E54: 10.4 | F54: Green | G54: Blue | I54: 629 | J54: =I54*4 -> 2516
B55: CDM-531 | C55: 575 | D55: 50 | E55: 11.5 | F55: Green | G55: Black | I55: 717.41 | J55: =I55*4 -> 2869.64
B56: CDM-55 | C56: 650 | D56: 50 | E56: 13 | F56: Grey
B57: CDM-532 | C57: 700 | D57: 50 | E57: 14 | F57: Green | G57: Red
A58: CDM-551 | B58: CDM-551 | C58: 775 | D58: 50 | E58: 15.5 | F58: Grey | G58: Black | I58: 800
B59: CDM-552 | C59: 900 | D59: 50 | E59: 18 | F59: Grey | G59: Red
B60: CDM-553 | C60: 1000 | D60: 50 | E60: 20 | F60: Grey | G60: Green

Sheet Rubber Mounts
A1: Sku | B1: Item Descr. | C1: Static Deflection | D1: Unit Nett
A2: 92859753 | B2: RUBBER MOUNT NR1 BLUE (17KG) EMBELTON | C2: 5mm | D2: 11.83 | E2: Datasheet
A3: 92907385 | B3: RUBBER MOUNT NR1 WHITE (25KG) EMBELTON | C3: 5mm | D3: 11.83
A4: 92996501 | B4: RUBBER MOUNT NR1 YELLOW (80KG) EMBELTON | C4: 5mm | D4: 11.83
A5: 93035837 | B5: RUBBER MOUNT NR2 RED(100KG) | D5: 15.25
B8: RUBBER MOUNT NR1 RED (40KG) EMBELTON | C8: 5mm
B9: RUBBER MOUNT NR1 GREEN (55KG) EMBELTON | C9: 5mm
D11: =Crossbars!C2*2 -> 284.76

Sheet Crossbars
A1: Part Number | B1: Description | C1: Unit Nett
A2: 93209230 | B2: SPRING MOUNT CROSSBAR 366MM FRAME | C2: 142.38
A3: 93232240 | B3: SPRING MOUNT CROSSBAR 462MM FRAME | C3: 142.38
A4: 92948830 | B4: SPRING MOUNT CROSSBAR 512MM BASE | C4: 142.38
A5: 93002398 | B5: SPRING MOUNT CROSSBAR 576MM BASE (CSM) | C5: 142.38

Sheet Inertia Base Models
B1: Part Number | C1: Length | D1: Width | E1: Height | F1: Spring Mount | G1: Weight | H1: Cost Price | I1: 15% GM
A2: 1-151-800-630-125 | B2: 98336369 | C2: 800 | D2: 630 | E2: 125 | F2: 75 | G2: 151 | H2: 565.52 | I2: =H2/0.85 -> 665.31765 | J2: 800 x 630 x 125
A3: 2-317-1100-800-150 | B3: 92513065 | C3: 1100 | D3: 800 | E3: 150 | F3: 75 | G3: 317 | H3: 610.6 | I3: =H3/0.85 -> 718.35294 | J3: 1100 x 800 x 150
A4: 3-461-1200-800-200 | B4: 98327389 | C4: 1200 | D4: 800 | E4: 200 | F4: 75 | G4: 461 | H4: 663.42 | I4: =H4/0.85 -> 780.49412 | J4: 1200 x 800 x 200
A5: 4-648-1500-800-225 | B5: 99051550 | C5: 1500 | D5: 800 | E5: 225 | F5: 75 | G5: 648 | H5: 741.99 | I5: =H5/0.85 -> 872.92941 | J5: 1500 x 800 x 225
A6: 5-972-1500-900-300 | B6: 98299752 | C6: 1500 | D6: 900 | E6: 300 | F6: 75 | G6: 972 | H6: 824.44 | I6: =H6/0.85 -> 969.92941 | J6: 1500 x 900 x 300
A7: 6-1512-2100-1000-300 | B7: TBA | C7: 2100 | D7: 1000 | E7: 300 | F7: 75 | G7: 1512 | J7: 2100 x 1000 x 300
A8: 7-246-950-720-150 | B8: 98327382 | C8: 950 | D8: 720 | E8: 150 | F8: 75 | G8: 246 | H8: 532.03 | J8: 950 x 720 x 150
I9: =AVERAGE(I2:I6) -> 801.40471

Sheet Inertia Bases 2025
A1: Part number | B1: Correct Weight (kg) | C1: Length | D1: Width | E1: Depth | F1: Mount Height | G1: List Price | H1: Net Cost
A2: 97758051 | B2: 194.4 | C2: 600 | D2: 600 | E2: 225 | F2: 90 | G2: 966.95 | H2: 635.08
A3: 99102010 | B3: 285.9936 | C3: 620 | D3: 620 | E3: 310 | F3: 75 | G3: 984.6 | H3: 646.67
A4: 91338199 | B4: 105 | C4: 700 | D4: 500 | E4: 125 | F4: 75 | G4: 843.39 | H4: 553.92
A5: 92526365 | B5: 126 | C5: 700 | D5: 500 | E5: 150 | F5: 75 | G5: 915.95 | H5: 601.58
A6: 92584091 | B6: 268.8 | C6: 700 | D6: 800 | E6: 200 | F6: 100 | G6: 972.84 | H6: 638.94
A7: 99551448 | B7: 132 | C7: 800 | D7: 550 | E7: 125 | F7: 75 | G7: 1641.68 | H7: 1078.22
A8: 98336369 | B8: 151.2 | C8: 800 | D8: 630 | E8: 125 | F8: 75 | G8: 882.63 | H8: 565.52
A9: 91338256 | B9: 162 | C9: 900 | D9: 600 | E9: 125 | F9: 75 | G9: 1019.92 | H9: 579.7
A10: 91334365 | B10: 162 | C10: 900 | D10: 600 | E10: 125 | F10: 75 | G10: 861.04 | H10: 669.87
A11: 98442977 | B11: 217.08 | C11: 900 | D11: 670 | E11: 150 | F11: 75 | G11: 996.38 | H11: 654.41
A12: 98327382 | B12: 246.24 | C12: 950 | D12: 720 | E12: 150 | F12: 75 | G12: 810.05 | H12: 532.03
A13: 98140864 | B13: 328.32 | C13: 950 | D13: 720 | E13: 200 | F13: 75 | G13: 1092.48 | H13: 717.52
... A29: 93026537 | B29: 795.6 | C29: 1300 | D29: 850 | E29: 300 | F29: 100 | G29: 1225.86 | H29: 805.13
A30: 93000796 | B30: 998.4 | C30: 1300 | D30: 800 | E30: 400 | G30: 1602.44 | H30: 1052.46
A31: 91338087 | B31: 293.04 | C31: 1320 | D31: 740 | E31: 125 | F31: 75 | G31: 823.78 | H31: 541.04
A32: 99051564 | B32: 453.6 | C32: 1350 | D32: 800 | E32: 175 | F32: 75 | G32: 1100.33 | H32: 722.67
A33: 99067490 | B33: 1166.4 | C33: 1350 | D33: 900 | E33: 400 | F33: 80 | G33: 1602.44 | H33: 1052.46
A34: 98301913 | B34: 302.4 | C34: 1400 | D34: 720 | E34: 125 | F34: 75 | G34: 1004.23 | H34: 659.56
A35: 93047546 | B35: 411.6 | C35: 1400 | D35: 700 | E35: 175 | F35: 75 | G35: 1110.13 | H35: 729.11
A36: 92513002 | B36: 646.8 | C36: 1400 | D36: 1100 | E36: 175 | F36: 100 | G36: 1655.39 | H36: 1087.05
A37: 99051548 | B37: 487.2 | C37: 1450 | D37: 800 | E37: 175 | F37: 75 | G37: 1151.32 | H37: 756.17
A38: 99051549 | B38: 556.8 | C38: 1450 | D38: 800 | E38: 200 | F38: 75 | G38: 800.24 | H38: 525.59
A39: 99051550 | B39: 648 | C39: 1500 | D39: 800 | E39: 225 | F39: 75 | G39: 1129.74 | H39: 741.99
A40: 98565389 | B40: 712.8 | C40: 1500 | D40: 900 | E40: 220 | F40: 75 | G40: 1196.43 | H40: 785.8
A41: 98299752 | B41: 972 | C41: 1500 | D41: 900 | E41: 300 | F41: 75 | G41: 1255.27 | H41: 824.44
A42: 98565406 | B42: 1296 | C42: 1500 | D42: 900 | E42: 400 | F42: 80 | H42: 1249.3
A43: 98100247 | B43: 412.92 | C43: 1550 | D43: 740 | E43: 150 | F43: 75 | G43: 1614.2 | H43: 1060.18
A44: 93047624 | B44: 691.2 | C44: 1600 | D44: 800 | E44: 225 | F44: 75 | G44: 1184.67 | H44: 785.8
A45: 99629821 | B45: 642.6 | C45: 1700 | D45: 900 | E45: 175 | F45: 75 | G45: 1480.84 | H45: 972.6
A46: 93369540 | B46: 780.3 | C46: 1700 | D46: 850 | E46: 225 | F46: 75 | H46: 859.95
A47: 91338088 | B47: 660.96 | C47: 1700 | D47: 810 | E47: 200 | F47: 80 | G47: 833.59 | H47: 547.49
A48: 92792038 | B48: 734.4 | C48: 1700 | D48: 900 | E48: 200 | F48: 75 | G48: 1188.58 | H48: 780.65
A49: TBA-4 | B49: 979.2 | C49: 1700 | D49: 1200 | E49: 200 | H49: 1550
A50: TBA-5 | B50: 864 | C50: 1800 | D50: 800 | E50: 250 | H50: 1550
A51: TBA-1 | B51: 2188.8 | C51: 1900 | D51: 1200 | E51: 400 | H51: 1550
A52: TBA-5 | B52: 1368 | C52: 1900 | D52: 1200 | E52: 250 | H52: 1550
A53: TBA-6 | B53: 912 | C53: 1900 | D53: 800 | E53: 250 | H53: 1550
A54: TBA-7 | B54: 1764 | C54: 2100 | D54: 1400 | E54: 250 | H54: 1550
A55: TBA-2 | B55: 2217.6 | C55: 2200 | D55: 1400 | E55: 300 | H55: 1550
A56: TBA-3 | B56: 2073.6 | C56: 2400 | D56: 1200 | E56: 300 | H56: 1550
A57: TBA-9 | B57: 1080 | C57: 1800 | D57: 1000 | E57: 250 | H57: 1550

Sheet NBG Duties
A1: SKU | B1: Name | C1: Flow (L/s) | D1: Head (kPa) | E1: SKU
A2: 99796410 | B2: Grundfos NBG 50-32-200/176 4kW 2P | C2: 1.9 | D2: 300 | E2: 99796410
A3: 99801285 | B3: Grundfos NBG 65-40-315/283 3kW 4P | C3: 2.48 | D3: 225 | E3: 99801285
A4: 99801276 | B4: Grundfos NBG 50-32-200/216 1.1kW 4P | C4: 2.7 | D4: 150 | E4: 99801276 | G4: https://product-selection.grundfos.com/au/products/nbg-nbge/nbg/nbg-80-65-160175-99801305
A5: 99796410 | B5: Grundfos NBG 50-32-200/176 4kW 2P | C5: 3 | D5: 300 | E5: 99796410
A6: 99796411 | B6: Grundfos NBG 50-32-200/190 5.5kW 2P | C6: 3.27 | D6: 400 | E6: 99796411
A7: 99801277 | B7: Grundfos NBG 50-32-200/219 1.5kW 4P | C7: 3.29 | D7: 152 | E7: 99801277
A8: 99801285 | B8: Grundfos NBG 65-40-315/283 3kW 4P | C8: 3.3 | D8: 200 | E8: 99801285
A9: 99796410 | B9: Grundfos NBG 50-32-200/176 4kW 2P | C9: 3.3 | D9: 300 | E9: 99796410
A10: 99796411 | B10: Grundfos NBG 50-32-200/190 5.5kW 2P | C10: 3.3 | D10: 400 | E10: 99796411
A11: 99801297 | B11: Grundfos NBG 80-50-250/263 4kW 4P | C11: 3.4 | D11: 100 | E11: 99801297
A12: 99801101 | B12: Grundfos NBG 80-65-160/177 15kW 2P | C12: 3.44 | D12: 50 | E12: 99801101
A13: 99801100 | B13: Grundfos NBG 80-65-160/167 11kW 2P | C13: 3.7 | D13: 300 | E13: 99801100
A14: 99801287 | B14: Grundfos NBG 65-40-315/334 5.5kW 4P | C14: 4 | D14: 350 | E14: 99801287
A15: 99796411 | B15: Grundfos NBG 50-32-200/190 5.5kW 2P | C15: 4 | D15: 370 | E15: 99796411
A16: 99796408 | B16: Grundfos NBG 50-32-160/163 4kW 2P | C16: 4.04 | D16: 250 | E16: 99796408
... A906: 99801151 | B906: Grundfos NBG 200-150-200/218-202 90kW 2P | C906: 180.8 | D906: 350 | E906: 99801151

Sheet Sheet39
A1: Name | B1: Flow L/s | C1: Head kPa
A2: Grundfos NBG 80-65-160/177 15kW 2P | B2: 3.44 | C2: 50 | J2: Grundfos NBG 80-65-160/150 7.5kW 2P | K2: 20
A3: Grundfos NBG 100-80-160/149 1.1kW 4P | B3: 15 | C3: 50 | J3: Grundfos NBG 100-80-160/157 11kW 2P | K3: 22
A4: Grundfos NBG 80-65-160/175 1.5kW 4P | B4: 9.8 | C4: 80 | J4: Grundfos NBG 65-50-160/172 7.5kW 2P | K4: 22
A5: Grundfos NBG 125-80-160/177 4kW 4P | B5: 26.05 | C5: 80
A6: Grundfos NBG 80-50-250/263 4kW 4P | B6: 3.4 | C6: 100
A7: Grundfos NBG 65-40-200/198 1.1kW 4P | B7: 5.2 | C7: 100
A8: Grundfos NBG 65-40-200/198 1.1kW 4P | B8: 5.5 | C8: 100
A9: Grundfos NBG 80-50-200/210 2.2kW 4P | B9: 11 | C9: 100
A10: Grundfos NBG 100-65-200/205 3kW 4P | B10: 17.9 | C10: 100
A11: Grundfos NBG 125-100-200/195 5.5kW 4P | B11: 34.3 | C11: 100
A12: Grundfos NBG 125-100-200/195 5.5kW 4P | B12: 34.49 | C12: 105
A13: Grundfos NBG 65-40-200/217 1.5kW 4P | B13: 7.5 | C13: 110
A14: Grundfos NBG 80-50-200/210 2.2kW 4P | B14: 11.3 | C14: 110
A15: Grundfos NBG 80-50-200/219 3kW 4P | B15: 12 | C15: 110
A16: Grundfos NBG 100-65-200/205 3kW 4P | B16: 15.53 | C16: 110
... A527: Grundfos NBG 80-50-250/233 22kW 2P | B527: 17.9 | C527: 650

Sheet Sheet41

Sheet RACP Duties
A1: 2.4 L/s @ 150kPa)
A3: CM 10-2 | B3: 1852
A4: CME 10-1 | B4: 2470
A5: CR 10-2 | B5: 2110
A6: CRE 5-2 | B6: 2609
A7: TP 32-200 | B7: 2909
A8: TPE3 32-200 | B8: 8117

Sheet NBG Details
A1: Part Number | B1: Name | C1: Pump LIST | D1: Poles | E1: kW | F1: MEI | G1: Weight (kg) | H1: Length (mm) | I1: Width (mm) | J1: Height (mm) | K1: Required Weight
A2: 99796406 | B2: NBG 50-32-160/139 | C2: 3880 | D2: 2 | E2: 2.2 | F2: 0.59 | G2: 58 | H2: 426 | I2: 103 | J2: 194 | K2: =G2*1.5 -> 87 | M2: =(H2+200)/1000 -> 0.626 | N2: =(I2+200)/1000 -> 0.303 | O2: =M2*N2 -> 0.189678
A3: 99796407 | B3: NBG 50-32-160/151 | C3: 3947 | D3: 2 | E3: 3 | F3: 0.59 | G3: 68 | H3: 504 | I3: 103 | J3: 194 | K3: =G3*1.5 -> 102 | M3: =(H3+200)/1000 -> 0.704 | N3: =(I3+200)/1000 -> 0.303 | O3: =M3*N3 -> 0.213312
A4: 99796408 | B4: NBG 50-32-160/163 | C4: 5470 | D4: 2 | E4: 4 | F4: 0.59 | G4: 77 | H4: 504 | I4: 141 | J4: 194 | K4: =G4*1.5 -> 115.5 | M4: =(H4+200)/1000 -> 0.704 | N4: =(I4+200)/1000 -> 0.341 | O4: =M4*N4 -> 0.240064
A5: 99796409 | B5: NBG 50-32-160/177 | C5: 4397 | D5: 2 | E5: 5.5 | F5: 0.59 | G5: 117 | H5: 593 | I5: 141 | J5: 194 | K5: =G5*1.5 -> 175.5 | M5: =(H5+200)/1000 -> 0.793 | N5: =(I5+200)/1000 -> 0.341 | O5: =M5*N5 -> 0.270413
A6: 99796410 | B6: NBG 50-32-200/176 | C6: 4489 | D6: 2 | E6: 4 | F6: 0.68 | G6: 82 | H6: 503.5 | I6: 141 | J6: 194 | K6: =G6*1.5 -> 123 | M6: =(H6+200)/1000 -> 0.7035 | N6: =(I6+200)/1000 -> 0.341 | O6: =M6*N6 -> 0.2398935
A7: 99796411 | B7: NBG 50-32-200/190 | C7: 4715 | D7: 2 | E7: 5.5 | F7: 0.68 | G7: 122 | H7: 592.5 | I7: 141 | J7: 194 | K7: =G7*1.5 -> 183 | M7: =(H7+200)/1000 -> 0.7925 | N7: =(I7+200)/1000 -> 0.341 | O7: =M7*N7 -> 0.2702425
A8: 99796412 | B8: NBG 50-32-200/206 | C8: 5104 | D8: 2 | E8: 7.5 | F8: 0.68 | G8: 130 | H8: 592.5 | I8: 141 | J8: 194 | K8: =G8*1.5 -> 195 | M8: =(H8+200)/1000 -> 0.7925 | N8: =(I8+200)/1000 -> 0.341 | O8: =M8*N8 -> 0.2702425
A9: 99796413 | B9: NBG 50-32-200/219 | C9: 6029 | D9: 2 | E9: 11 | F9: 0.68 | G9: 166 | H9: 810.5 | I9: 269 | J9: 340 | K9: =G9*1.5 -> 249 | M9: =(H9+200)/1000 -> 1.0105 | N9: =(I9+200)/1000 -> 0.469 | O9: =M9*N9 -> 0.4739245
A10: 99796414 | B10: NBG 65-40-200/172 | C10: 5137 | D10: 2 | E10: 5.5 | F10: 0.65 | G10: 123 | H10: 612.5 | I10: 141 | J10: 216 | K10: =G10*1.5 -> 184.5 | M10: =(H10+200)/1000 -> 0.8125 | N10: =(I10+200)/1000 -> 0.341 | O10: =M10*N10 -> 0.2770625
A11: 99796415 | B11: NBG 65-40-200/188 | C11: 5320 | D11: 2 | E11: 7.5 | F11: 0.65 | G11: 132 | H11: 612.5 | I11: 141 | J11: 216 | K11: =G11*1.5 -> 198 | M11: =(H11+200)/1000 -> 0.8125 | N11: =(I11+200)/1000 -> 0.341 | O11: =M11*N11 -> 0.2770625
A12: 99796416 | B12: NBG 65-40-200/206 | C12: 6455 | D12: 2 | E12: 11 | F12: 0.65 | G12: 169 | H12: 830.5 | I12: 297 | J12: 340 | K12: =G12*1.5 -> 253.5 | M12: =(H12+200)/1000 -> 1.0305 | N12: =(I12+200)/1000 -> 0.497 | O12: =M12*N12 -> 0.5121585
A13: 99796417 | B13: NBG 65-40-200/219 | C13: 6536 | D13: 2 | E13: 15 | F13: 0.65 | G13: 174 | H13: 830.5 | I13: 297 | J13: 340 | K13: =G13*1.5 -> 261 | M13: =(H13+200)/1000 -> 1.0305 | N13: =(I13+200)/1000 -> 0.497 | O13: =M13*N13 -> 0.5121585
... A218: 99817807 | B218: NBG 125-100-315/334 | C218: 14032 | D218: 4 | E218: 30 | F218: 0.7 | G218: 424 | H218: 1068 | I218: 472 | J218: 565 | K218: =G218*1.5 -> 636 | M218: =(H218+200)/1000 -> 1.268 | N218: =(I218+200)/1000 -> 0.672 | O218: =M218*N218 -> 0.852096
